<?xml version="1.0" encoding="UTF-8"?>
<root t='150' id='1' V150='13' creationTimestamp='0x19077fc684a' V1='4' name='PropertyIVO' incarnation='26'>
  <rootElem t='167' id='2' V167='21' V283='2' occurMaxTimes='1' minSize='-1' maxSize='-1' groupType='3' repHandlerStruct='' visible='true' inheritsFrom='' namespaceIndex='1' V281='13' V1='4' name='PropertyIVO'>
    <structNode t='150' idref='1'/>
    <child t='167' id='3' V167='21' V283='2' occurMaxTimes='1' minSize='-1' maxSize='-1' groupType='3' repHandlerStruct='' inheritsFrom='' V281='13' V1='4' name='Attributes'>
      <structNode t='150' idref='1'/>
      <child t='167' id='4' V167='21' V283='2' occurMaxTimes='1' minSize='-1' maxSize='-1' dataType='13' elemType='1' repHandlerStruct='' visible='true' inheritsFrom='' V281='13' V1='4' name='id'>
        <structNode t='150' idref='1'/>
      </child>
      <child t='167' id='5' V167='21' V283='2' occurMaxTimes='1' minSize='-1' maxSize='-1' dataType='1' elemType='1' repHandlerStruct='' visible='true' inheritsFrom='' V281='13' V1='4' name='main'>
        <structNode t='150' idref='1'/>
      </child>
      <child t='167' id='6' V167='21' V283='2' occurMaxTimes='1' minSize='-1' maxSize='-1' dataType='13' elemType='1' repHandlerStruct='' visible='true' inheritsFrom='' V281='13' V1='4' name='system_id'>
        <structNode t='150' idref='1'/>
      </child>
      <child t='167' id='7' V167='21' V283='2' occurMaxTimes='1' minSize='-1' maxSize='-1' dataType='13' elemType='1' repHandlerStruct='' visible='true' inheritsFrom='' V281='13' V1='4' name='updateVersion'>
        <structNode t='150' idref='1'/>
      </child>
    </child>
    <child t='167' id='8' V167='21' V283='2' occurMaxTimes='1' minSize='-1' maxSize='-1' groupType='1' repHandlerStruct='' visible='true' inheritsFrom='' V281='13' V1='4' name='mortgageVOList'>
      <structNode t='150' idref='1'/>
      <child t='167' id='9' V167='21' inheritsFromIncarnation='8' inheritsFromTimestamp='0x19077fc6831' inheritsInThisStruct='true' V283='2' occurMaxTimes='-1' minSize='-1' maxSize='-1' inheritsFromCopyRule='20' groupType='3' repHandlerStruct='' visible='true' inheritsFrom='Structures/CI_QA_all_interfaces_20240703/Types/interfaces/MortgageIVO.xml' V281='13' V1='4' name='mortgageVO' description='Liste der AktivhypothekenList of asset mortgagesList of asset mortgages' checksumValid='true' checksum='6lWfWcRnfdYDu7vK2Q8pvVHgOsE='>
        <structNode t='150' idref='1'/>
        <savedDerivedCopy t='167' id='10' V167='21' needInheritInit='true' inheritsInThisStruct='true' V283='2' occurMaxTimes='-1' minSize='-1' maxSize='-1' inheritsFromCopyRule='20' dataType='2' repHandlerStruct='' visible='true' inheritsFrom='Structures/CI_QA_all_interfaces_20240703/Types/interfaces/MortgageIVO.xml' V281='13' V1='4' name='mortgageVO' description='Liste der AktivhypothekenList of asset mortgagesList of asset mortgages'>
        </savedDerivedCopy>
        <savedOrigCopyAtInheritsFrom t='167' id='11' V167='21' V283='2' occurMaxTimes='1' minSize='-1' maxSize='-1' groupType='3' repHandlerStruct='' visible='true' inheritsFrom='' namespaceIndex='1' V281='13' V1='4' name='MortgageIVO'>
        </savedOrigCopyAtInheritsFrom>
      </child>
    </child>
    <child t='167' id='12' V167='21' V283='2' occurMaxTimes='1' minSize='-1' maxSize='-1' dataType='13' repHandlerStruct='' visible='true' inheritsFrom='' V281='13' V1='4' name='fireExtingNumber' description='Anzahl der BrandschutzvorrichtungenNumber of anti-fire devicesNumber of anti-fire devices'>
      <structNode t='150' idref='1'/>
    </child>
    <child t='167' id='13' V167='21' V283='2' occurMaxTimes='1' minSize='-1' maxSize='-1' dataType='13' repHandlerStruct='' visible='true' inheritsFrom='' V281='13' V1='4' name='rooms' description='Anzahl der RäumeNumber of roomsNumber of rooms'>
      <structNode t='150' idref='1'/>
    </child>
    <child t='167' id='14' V167='21' V283='2' occurMaxTimes='1' minSize='-1' maxSize='-1' dataType='2' repHandlerStruct='' visible='true' inheritsFrom='' V281='13' V1='4' name='peakFrom1' description='Startdatum der Geschäftsspitzenperiode 1 - wird für Immobilien des Geschäftstyps verwendetBusiness peak period 1 start date - us...'>
      <structNode t='150' idref='1'/>
      <longDesc>Startdatum der Geschäftsspitzenperiode 1 - wird für Immobilien des Geschäftstyps verwendetBusiness peak period 1 start date - used for business type propertyBusiness peak period 1 start date - used for business type property</longDesc>
    </child>
    <child t='167' id='15' V167='21' V283='2' occurMaxTimes='1' minSize='-1' maxSize='-1' dataType='2' repHandlerStruct='' visible='true' inheritsFrom='' V281='13' V1='4' name='peakFrom2' description='Startdatum der Geschäftsspitzenperiode 2 - wird für Geschäftsimmobilien verwendetBusiness peak period 2 start date - used for bu...'>
      <structNode t='150' idref='1'/>
      <longDesc>Startdatum der Geschäftsspitzenperiode 2 - wird für Geschäftsimmobilien verwendetBusiness peak period 2 start date - used for business type propertyBusiness peak period 2 start date - used for business type property</longDesc>
    </child>
    <child t='167' id='16' V167='21' V283='2' occurMaxTimes='1' minSize='-1' maxSize='-1' dataType='13' repHandlerStruct='' visible='true' inheritsFrom='' V281='13' V1='4' name='renovationYear' description='Eigentum letzten RenovierungsjahrProperty last renovation yearProperty last renovation year'>
      <structNode t='150' idref='1'/>
    </child>
    <child t='167' id='17' V167='21' V283='2' occurMaxTimes='1' minSize='-1' maxSize='-1' groupType='1' repHandlerStruct='' visible='true' inheritsFrom='' V281='13' V1='4' name='officeComputerList'>
      <structNode t='150' idref='1'/>
      <child t='167' id='18' V167='21' inheritsFromIncarnation='8' inheritsFromTimestamp='0x19077fc67eb' inheritsInThisStruct='true' V283='2' occurMaxTimes='-1' minSize='-1' maxSize='-1' inheritsFromCopyRule='20' groupType='3' repHandlerStruct='' visible='true' inheritsFrom='Structures/CI_QA_all_interfaces_20240703/Types/interfaces/AssetOfficeComputerIVO.xml' V281='13' V1='4' name='officeComputer' description='Liste der Details zu BürocomputernList of office computers detailsList of office computers details'>
        <structNode t='150' idref='1'/>
        <savedDerivedCopy t='167' id='19' V167='21' needInheritInit='true' inheritsInThisStruct='true' V283='2' occurMaxTimes='-1' minSize='-1' maxSize='-1' inheritsFromCopyRule='20' dataType='2' repHandlerStruct='' visible='true' inheritsFrom='Structures/CI_QA_all_interfaces_20240703/Types/interfaces/AssetOfficeComputerIVO.xml' V281='13' V1='4' name='officeComputer' description='Liste der Details zu BürocomputernList of office computers detailsList of office computers details'>
        </savedDerivedCopy>
        <savedOrigCopyAtInheritsFrom t='167' id='20' V167='21' V283='2' occurMaxTimes='1' minSize='-1' maxSize='-1' groupType='3' repHandlerStruct='' visible='true' inheritsFrom='' namespaceIndex='1' V281='13' V1='4' name='AssetOfficeComputerIVO'>
        </savedOrigCopyAtInheritsFrom>
      </child>
    </child>
    <child t='167' id='21' V167='21' V283='2' occurMaxTimes='1' minSize='-1' maxSize='-1' dataType='30' repHandlerStruct='' visible='true' inheritsFrom='' V281='13' V1='4' name='rateDate'>
      <structNode t='150' idref='1'/>
    </child>
    <child t='167' id='22' V167='21' V283='2' occurMaxTimes='1' minSize='-1' maxSize='-1' dataType='2' repHandlerStruct='' visible='true' inheritsFrom='' V281='13' V1='4' name='accessdoorStandardRef' description='dynamic table type and id: class com.idit.reference.server.ejb3.vo.TDynamicReferenceDataVO and dynamic tabled id is:20916'>
      <structNode t='150' idref='1'/>
      <child t='167' id='23' V167='21' V283='2' occurMaxTimes='1' minSize='-1' maxSize='-1' groupType='3' repHandlerStruct='' inheritsFrom='' V281='13' V1='4' name='Attributes'>
        <structNode t='150' idref='1'/>
        <child t='167' id='24' V167='21' V283='2' occurMinTimes='1' occurMaxTimes='1' minSize='-1' maxSize='-1' dataType='13' elemType='1' repHandlerStruct='' visible='true' inheritsFrom='' V281='13' V1='4' name='id'>
          <structNode t='150' idref='1'/>
        </child>
        <child t='167' id='25' V167='21' V283='2' occurMaxTimes='1' minSize='-1' maxSize='-1' dataType='2' elemType='1' repHandlerStruct='' visible='true' inheritsFrom='' V281='13' V1='4' name='extCode'>
          <structNode t='150' idref='1'/>
        </child>
      </child>
    </child>
    <child t='167' id='26' V167='21' V283='2' occurMaxTimes='1' minSize='-1' maxSize='-1' dataType='2' repHandlerStruct='' visible='true' inheritsFrom='' V281='13' V1='4' name='assetIdentifier' description='Asset-ID (Freitext) - für einige Kunden-IDsAsset identifier (free text) - for some customer identifiersAsset identifier (free te...'>
      <structNode t='150' idref='1'/>
      <longDesc>Asset-ID (Freitext) - für einige Kunden-IDsAsset identifier (free text) - for some customer identifiersAsset identifier (free text) - for some customer identifiers</longDesc>
    </child>
    <child t='167' id='27' V167='21' V283='2' occurMaxTimes='1' minSize='-1' maxSize='-1' dataType='2' repHandlerStruct='' visible='true' inheritsFrom='' V281='13' V1='4' name='windowStandardsRef' description='dynamic table type and id: class com.idit.reference.server.ejb3.vo.TDynamicReferenceDataVO and dynamic tabled id is:20920'>
      <structNode t='150' idref='1'/>
      <child t='167' id='28' V167='21' V283='2' occurMaxTimes='1' minSize='-1' maxSize='-1' groupType='3' repHandlerStruct='' inheritsFrom='' V281='13' V1='4' name='Attributes'>
        <structNode t='150' idref='1'/>
        <child t='167' id='29' V167='21' V283='2' occurMinTimes='1' occurMaxTimes='1' minSize='-1' maxSize='-1' dataType='13' elemType='1' repHandlerStruct='' visible='true' inheritsFrom='' V281='13' V1='4' name='id'>
          <structNode t='150' idref='1'/>
        </child>
        <child t='167' id='30' V167='21' V283='2' occurMaxTimes='1' minSize='-1' maxSize='-1' dataType='2' elemType='1' repHandlerStruct='' visible='true' inheritsFrom='' V281='13' V1='4' name='extCode'>
          <structNode t='150' idref='1'/>
        </child>
      </child>
    </child>
    <child t='167' id='31' V167='21' inheritsFromIncarnation='8' inheritsFromTimestamp='0x19077fc67df' inheritsInThisStruct='true' V283='2' occurMaxTimes='1' minSize='-1' maxSize='-1' inheritsFromCopyRule='20' groupType='3' repHandlerStruct='' visible='true' inheritsFrom='Structures/CI_QA_all_interfaces_20240703/Types/interfaces/AddressIVO.xml' V281='13' V1='4' name='addressVO' checksumValid='true' checksum='G5iwKTgVDBZMYhjN5udWvk8Y6Oo='>
      <structNode t='150' idref='1'/>
      <savedDerivedCopy t='167' id='32' V167='21' needInheritInit='true' inheritsInThisStruct='true' V283='2' occurMaxTimes='1' minSize='-1' maxSize='-1' inheritsFromCopyRule='20' dataType='2' repHandlerStruct='' visible='true' inheritsFrom='Structures/CI_QA_all_interfaces_20240703/Types/interfaces/AddressIVO.xml' V281='13' V1='4' name='addressVO'>
      </savedDerivedCopy>
      <savedOrigCopyAtInheritsFrom t='167' id='33' V167='21' V283='2' occurMaxTimes='1' minSize='-1' maxSize='-1' groupType='3' repHandlerStruct='' visible='true' inheritsFrom='' namespaceIndex='1' V281='13' V1='4' name='AddressIVO'>
      </savedOrigCopyAtInheritsFrom>
    </child>
    <child t='167' id='34' V167='21' V283='2' occurMaxTimes='1' minSize='-1' maxSize='-1' dataType='2' repHandlerStruct='' visible='true' inheritsFrom='' V281='13' V1='4' name='roofMaterialVORef' description='Eigenschaftsdachmaterial - Fremdschlüssel für T_ROOF_MATERIALProperty roof material - foreign key to T_ROOF_MATERIALProperty roo...'>
      <structNode t='150' idref='1'/>
      <longDesc>Eigenschaftsdachmaterial - Fremdschlüssel für T_ROOF_MATERIALProperty roof material - foreign key to T_ROOF_MATERIALProperty roof material - foreign key to T_ROOF_MATERIALoriginal type: class com.idit.reference.common.vo.TRoofMaterialVO</longDesc>
      <child t='167' id='35' V167='21' V283='2' occurMaxTimes='1' minSize='-1' maxSize='-1' groupType='3' repHandlerStruct='' inheritsFrom='' V281='13' V1='4' name='Attributes'>
        <structNode t='150' idref='1'/>
        <child t='167' id='36' V167='21' V283='2' occurMinTimes='1' occurMaxTimes='1' minSize='-1' maxSize='-1' dataType='13' elemType='1' repHandlerStruct='' visible='true' inheritsFrom='' V281='13' V1='4' name='id'>
          <structNode t='150' idref='1'/>
        </child>
        <child t='167' id='37' V167='21' V283='2' occurMaxTimes='1' minSize='-1' maxSize='-1' dataType='2' elemType='1' repHandlerStruct='' visible='true' inheritsFrom='' V281='13' V1='4' name='extCode'>
          <structNode t='150' idref='1'/>
        </child>
      </child>
    </child>
    <child t='167' id='38' V167='21' V283='2' occurMaxTimes='1' minSize='-1' maxSize='-1' dataType='2' repHandlerStruct='' visible='true' inheritsFrom='' V281='13' V1='4' name='basisAmountIndexVORef' description='original type: class com.idit.reference.common.vo.TIndexVO'>
      <structNode t='150' idref='1'/>
      <child t='167' id='39' V167='21' V283='2' occurMaxTimes='1' minSize='-1' maxSize='-1' groupType='3' repHandlerStruct='' inheritsFrom='' V281='13' V1='4' name='Attributes'>
        <structNode t='150' idref='1'/>
        <child t='167' id='40' V167='21' V283='2' occurMinTimes='1' occurMaxTimes='1' minSize='-1' maxSize='-1' dataType='13' elemType='1' repHandlerStruct='' visible='true' inheritsFrom='' V281='13' V1='4' name='id'>
          <structNode t='150' idref='1'/>
        </child>
        <child t='167' id='41' V167='21' V283='2' occurMaxTimes='1' minSize='-1' maxSize='-1' dataType='2' elemType='1' repHandlerStruct='' visible='true' inheritsFrom='' V281='13' V1='4' name='extCode'>
          <structNode t='150' idref='1'/>
        </child>
      </child>
    </child>
    <child t='167' id='42' V167='21' inheritsFromIncarnation='11' inheritsFromTimestamp='0x19077fc684a' inheritsInThisStruct='true' V283='2' occurMaxTimes='1' minSize='-1' maxSize='-1' inheritsFromCopyRule='20' groupType='3' repHandlerStruct='' visible='true' inheritsFrom='Structures/CI_QA_all_interfaces_20240703/Types/interfaces/PropertyTheftIVO.xml' V281='13' V1='4' name='propertyTheftVO' description='Details zum Schutz vor Diebstahl von EigentumProperty theft protection detailsProperty theft protection details' checksumValid='true' checksum='dBjz2p33Bkb/kdGNzxQC6aM71NE='>
      <structNode t='150' idref='1'/>
      <savedDerivedCopy t='167' id='43' V167='21' needInheritInit='true' inheritsInThisStruct='true' V283='2' occurMaxTimes='1' minSize='-1' maxSize='-1' inheritsFromCopyRule='20' dataType='2' repHandlerStruct='' visible='true' inheritsFrom='Structures/CI_QA_all_interfaces_20240703/Types/interfaces/PropertyTheftIVO.xml' V281='13' V1='4' name='propertyTheftVO' description='Details zum Schutz vor Diebstahl von EigentumProperty theft protection detailsProperty theft protection details'>
      </savedDerivedCopy>
      <savedOrigCopyAtInheritsFrom t='167' id='44' V167='21' V283='2' occurMaxTimes='1' minSize='-1' maxSize='-1' groupType='3' repHandlerStruct='' visible='true' inheritsFrom='' namespaceIndex='1' V281='13' V1='4' name='PropertyTheftIVO'>
      </savedOrigCopyAtInheritsFrom>
    </child>
    <child t='167' id='45' V167='21' V283='2' occurMaxTimes='1' minSize='-1' maxSize='-1' groupType='1' repHandlerStruct='' visible='true' inheritsFrom='' V281='13' V1='4' name='assetAdditionalDataList'>
      <structNode t='150' idref='1'/>
      <child t='167' id='46' V167='21' inheritsFromIncarnation='8' inheritsFromTimestamp='0x19077fc67e4' inheritsInThisStruct='true' V283='2' occurMaxTimes='-1' minSize='-1' maxSize='-1' inheritsFromCopyRule='20' groupType='3' repHandlerStruct='' visible='true' inheritsFrom='Structures/CI_QA_all_interfaces_20240703/Types/interfaces/AssetAdditionalDataIVO.xml' V281='13' V1='4' name='assetAdditionalData' description='Asset zusätzliche Daten (Frage und Antwort)Asset additional data (question and answer)Asset additional data (question and answer...'>
        <structNode t='150' idref='1'/>
        <savedDerivedCopy t='167' id='47' V167='21' needInheritInit='true' inheritsInThisStruct='true' V283='2' occurMaxTimes='-1' minSize='-1' maxSize='-1' inheritsFromCopyRule='20' dataType='2' repHandlerStruct='' visible='true' inheritsFrom='Structures/CI_QA_all_interfaces_20240703/Types/interfaces/AssetAdditionalDataIVO.xml' V281='13' V1='4' name='assetAdditionalData' description='Asset zusätzliche Daten (Frage und Antwort)Asset additional data (question and answer)Asset additional data (question and answer...'>
        </savedDerivedCopy>
        <savedOrigCopyAtInheritsFrom t='167' id='48' V167='21' V283='2' occurMaxTimes='1' minSize='-1' maxSize='-1' groupType='3' repHandlerStruct='' visible='true' inheritsFrom='' namespaceIndex='1' V281='13' V1='4' name='AssetAdditionalDataIVO'>
        </savedOrigCopyAtInheritsFrom>
      </child>
    </child>
    <child t='167' id='49' V167='21' V283='2' occurMaxTimes='1' minSize='-1' maxSize='-1' dataType='2' repHandlerStruct='' visible='true' inheritsFrom='' V281='13' V1='4' name='habitantFlagVORef' description='Kennzeichnen Sie, ob der Versicherungsnehmer ein Immobilienbewohner istFlag whether policyholder is a property habitantFlag whet...'>
      <structNode t='150' idref='1'/>
      <longDesc>Kennzeichnen Sie, ob der Versicherungsnehmer ein Immobilienbewohner istFlag whether policyholder is a property habitantFlag whether policyholder is a property habitantoriginal type: class com.idit.reference.common.vo.TYesNoVO</longDesc>
      <child t='167' id='50' V167='21' V283='2' occurMaxTimes='1' minSize='-1' maxSize='-1' groupType='3' repHandlerStruct='' inheritsFrom='' V281='13' V1='4' name='Attributes'>
        <structNode t='150' idref='1'/>
        <child t='167' id='51' V167='21' V283='2' occurMinTimes='1' occurMaxTimes='1' minSize='-1' maxSize='-1' dataType='13' elemType='1' repHandlerStruct='' visible='true' inheritsFrom='' V281='13' V1='4' name='id'>
          <structNode t='150' idref='1'/>
        </child>
        <child t='167' id='52' V167='21' V283='2' occurMaxTimes='1' minSize='-1' maxSize='-1' dataType='2' elemType='1' repHandlerStruct='' visible='true' inheritsFrom='' V281='13' V1='4' name='extCode'>
          <structNode t='150' idref='1'/>
        </child>
      </child>
    </child>
    <child t='167' id='53' V167='21' V283='2' occurMaxTimes='1' minSize='-1' maxSize='-1' dataType='21' repHandlerStruct='' visible='true' inheritsFrom='' V281='13' V1='4' name='roofingPercentage' description='Prozentsatz der ÜberdachungPercentage of roofingPercentage of roofing'>
      <structNode t='150' idref='1'/>
    </child>
    <child t='167' id='54' V167='21' V283='2' occurMaxTimes='1' minSize='-1' maxSize='-1' dataType='2' repHandlerStruct='' visible='true' inheritsFrom='' V281='13' V1='4' name='operatorFlagVORef' description='Markieren Sie, ob der Versicherungsnehmer ein Immobilienbetreiber istFlag whether policyholder is property operatorFlag whether ...'>
      <structNode t='150' idref='1'/>
      <longDesc>Markieren Sie, ob der Versicherungsnehmer ein Immobilienbetreiber istFlag whether policyholder is property operatorFlag whether policyholder is property operatororiginal type: class com.idit.reference.common.vo.TYesNoVO</longDesc>
      <child t='167' id='55' V167='21' V283='2' occurMaxTimes='1' minSize='-1' maxSize='-1' groupType='3' repHandlerStruct='' inheritsFrom='' V281='13' V1='4' name='Attributes'>
        <structNode t='150' idref='1'/>
        <child t='167' id='56' V167='21' V283='2' occurMinTimes='1' occurMaxTimes='1' minSize='-1' maxSize='-1' dataType='13' elemType='1' repHandlerStruct='' visible='true' inheritsFrom='' V281='13' V1='4' name='id'>
          <structNode t='150' idref='1'/>
        </child>
        <child t='167' id='57' V167='21' V283='2' occurMaxTimes='1' minSize='-1' maxSize='-1' dataType='2' elemType='1' repHandlerStruct='' visible='true' inheritsFrom='' V281='13' V1='4' name='extCode'>
          <structNode t='150' idref='1'/>
        </child>
      </child>
    </child>
    <child t='167' id='58' V167='21' V283='2' occurMaxTimes='1' minSize='-1' maxSize='-1' dataType='2' repHandlerStruct='' visible='true' inheritsFrom='' V281='13' V1='4' name='fireExtingBrand' description='Marke von Anti-Feuer-GerätenBrand of anti-fire devicesBrand of anti-fire devices'>
      <structNode t='150' idref='1'/>
    </child>
    <child t='167' id='59' V167='21' V283='2' occurMaxTimes='1' minSize='-1' maxSize='-1' dataType='2' repHandlerStruct='' visible='true' inheritsFrom='' V281='13' V1='4' name='fireExtingMaintenanceVORef' description='Markieren Sie, ob Anti-Feuer-Geräte gewartet werdenFlag whether anti-fire devices are maintainedFlag whether anti-fire devices a...'>
      <structNode t='150' idref='1'/>
      <longDesc>Markieren Sie, ob Anti-Feuer-Geräte gewartet werdenFlag whether anti-fire devices are maintainedFlag whether anti-fire devices are maintainedoriginal type: class com.idit.reference.common.vo.TYesNoVO</longDesc>
      <child t='167' id='60' V167='21' V283='2' occurMaxTimes='1' minSize='-1' maxSize='-1' groupType='3' repHandlerStruct='' inheritsFrom='' V281='13' V1='4' name='Attributes'>
        <structNode t='150' idref='1'/>
        <child t='167' id='61' V167='21' V283='2' occurMinTimes='1' occurMaxTimes='1' minSize='-1' maxSize='-1' dataType='13' elemType='1' repHandlerStruct='' visible='true' inheritsFrom='' V281='13' V1='4' name='id'>
          <structNode t='150' idref='1'/>
        </child>
        <child t='167' id='62' V167='21' V283='2' occurMaxTimes='1' minSize='-1' maxSize='-1' dataType='2' elemType='1' repHandlerStruct='' visible='true' inheritsFrom='' V281='13' V1='4' name='extCode'>
          <structNode t='150' idref='1'/>
        </child>
      </child>
    </child>
    <child t='167' id='63' V167='21' V283='2' occurMaxTimes='1' minSize='-1' maxSize='-1' dataType='2' repHandlerStruct='' visible='true' inheritsFrom='' V281='13' V1='4' name='currencyVORef' description='original type: class com.idit.reference.common.vo.TCurrencyVO'>
      <structNode t='150' idref='1'/>
      <child t='167' id='64' V167='21' V283='2' occurMaxTimes='1' minSize='-1' maxSize='-1' groupType='3' repHandlerStruct='' inheritsFrom='' V281='13' V1='4' name='Attributes'>
        <structNode t='150' idref='1'/>
        <child t='167' id='65' V167='21' V283='2' occurMinTimes='1' occurMaxTimes='1' minSize='-1' maxSize='-1' dataType='13' elemType='1' repHandlerStruct='' visible='true' inheritsFrom='' V281='13' V1='4' name='id'>
          <structNode t='150' idref='1'/>
        </child>
        <child t='167' id='66' V167='21' V283='2' occurMaxTimes='1' minSize='-1' maxSize='-1' dataType='2' elemType='1' repHandlerStruct='' visible='true' inheritsFrom='' V281='13' V1='4' name='extCode'>
          <structNode t='150' idref='1'/>
        </child>
      </child>
    </child>
    <child t='167' id='67' V167='21' V283='2' occurMaxTimes='1' minSize='-1' maxSize='-1' dataType='2' repHandlerStruct='' visible='true' inheritsFrom='' V281='13' V1='4' name='propertyUseVORef' description='original type: class com.idit.policy.common.reference.vo.TPropertyUseVO'>
      <structNode t='150' idref='1'/>
      <child t='167' id='68' V167='21' V283='2' occurMaxTimes='1' minSize='-1' maxSize='-1' groupType='3' repHandlerStruct='' inheritsFrom='' V281='13' V1='4' name='Attributes'>
        <structNode t='150' idref='1'/>
        <child t='167' id='69' V167='21' V283='2' occurMinTimes='1' occurMaxTimes='1' minSize='-1' maxSize='-1' dataType='13' elemType='1' repHandlerStruct='' visible='true' inheritsFrom='' V281='13' V1='4' name='id'>
          <structNode t='150' idref='1'/>
        </child>
        <child t='167' id='70' V167='21' V283='2' occurMaxTimes='1' minSize='-1' maxSize='-1' dataType='2' elemType='1' repHandlerStruct='' visible='true' inheritsFrom='' V281='13' V1='4' name='extCode'>
          <structNode t='150' idref='1'/>
        </child>
      </child>
    </child>
    <child t='167' id='71' V167='21' V283='2' occurMaxTimes='1' minSize='-1' maxSize='-1' dataType='2' repHandlerStruct='' visible='true' inheritsFrom='' V281='13' V1='4' name='inflammableStandardsFlagVORef' description='Kennzeichnen Sie, ob das Eigentum den Standards für brennbare Materialien entsprichtFlag whether property meets inflammable mate...'>
      <structNode t='150' idref='1'/>
      <longDesc>Kennzeichnen Sie, ob das Eigentum den Standards für brennbare Materialien entsprichtFlag whether property meets inflammable materials standardsFlag whether property meets inflammable materials standardsoriginal type: class com.idit.reference.common.vo.TYesNoVO</longDesc>
      <child t='167' id='72' V167='21' V283='2' occurMaxTimes='1' minSize='-1' maxSize='-1' groupType='3' repHandlerStruct='' inheritsFrom='' V281='13' V1='4' name='Attributes'>
        <structNode t='150' idref='1'/>
        <child t='167' id='73' V167='21' V283='2' occurMinTimes='1' occurMaxTimes='1' minSize='-1' maxSize='-1' dataType='13' elemType='1' repHandlerStruct='' visible='true' inheritsFrom='' V281='13' V1='4' name='id'>
          <structNode t='150' idref='1'/>
        </child>
        <child t='167' id='74' V167='21' V283='2' occurMaxTimes='1' minSize='-1' maxSize='-1' dataType='2' elemType='1' repHandlerStruct='' visible='true' inheritsFrom='' V281='13' V1='4' name='extCode'>
          <structNode t='150' idref='1'/>
        </child>
      </child>
    </child>
    <child t='167' id='75' V167='21' V283='2' occurMaxTimes='1' minSize='-1' maxSize='-1' dataType='2' repHandlerStruct='' visible='true' inheritsFrom='' V281='13' V1='4' name='constructionMaterialRef' description='dynamic table type and id: class com.idit.reference.server.ejb3.vo.TDynamicReferenceDataVO and dynamic tabled id is:20919'>
      <structNode t='150' idref='1'/>
      <child t='167' id='76' V167='21' V283='2' occurMaxTimes='1' minSize='-1' maxSize='-1' groupType='3' repHandlerStruct='' inheritsFrom='' V281='13' V1='4' name='Attributes'>
        <structNode t='150' idref='1'/>
        <child t='167' id='77' V167='21' V283='2' occurMinTimes='1' occurMaxTimes='1' minSize='-1' maxSize='-1' dataType='13' elemType='1' repHandlerStruct='' visible='true' inheritsFrom='' V281='13' V1='4' name='id'>
          <structNode t='150' idref='1'/>
        </child>
        <child t='167' id='78' V167='21' V283='2' occurMaxTimes='1' minSize='-1' maxSize='-1' dataType='2' elemType='1' repHandlerStruct='' visible='true' inheritsFrom='' V281='13' V1='4' name='extCode'>
          <structNode t='150' idref='1'/>
        </child>
      </child>
    </child>
    <child t='167' id='79' V167='21' V283='2' occurMaxTimes='1' minSize='-1' maxSize='-1' dataType='13' repHandlerStruct='' visible='true' inheritsFrom='' V281='13' V1='4' name='adultsLivingInProp'>
      <structNode t='150' idref='1'/>
    </child>
    <child t='167' id='80' V167='21' V283='2' occurMaxTimes='1' minSize='-1' maxSize='-1' groupType='1' repHandlerStruct='' visible='true' inheritsFrom='' V281='13' V1='4' name='assetRiskVOsList'>
      <structNode t='150' idref='1'/>
      <child t='167' id='81' V167='21' inheritsFromIncarnation='8' inheritsFromTimestamp='0x19077fc67ee' inheritsInThisStruct='true' V283='2' occurMaxTimes='-1' minSize='-1' maxSize='-1' inheritsFromCopyRule='20' groupType='3' repHandlerStruct='' visible='true' inheritsFrom='Structures/CI_QA_all_interfaces_20240703/Types/interfaces/AssetRiskIVO.xml' V281='13' V1='4' name='assetRiskVOs' description='Liste der VermögensrisikenList of asset risksList of asset risks'>
        <structNode t='150' idref='1'/>
        <savedDerivedCopy t='167' id='82' V167='21' needInheritInit='true' inheritsInThisStruct='true' V283='2' occurMaxTimes='-1' minSize='-1' maxSize='-1' inheritsFromCopyRule='20' dataType='2' repHandlerStruct='' visible='true' inheritsFrom='Structures/CI_QA_all_interfaces_20240703/Types/interfaces/AssetRiskIVO.xml' V281='13' V1='4' name='assetRiskVOs' description='Liste der VermögensrisikenList of asset risksList of asset risks'>
        </savedDerivedCopy>
        <savedOrigCopyAtInheritsFrom t='167' id='83' V167='21' V283='2' occurMaxTimes='1' minSize='-1' maxSize='-1' groupType='3' repHandlerStruct='' visible='true' inheritsFrom='' namespaceIndex='1' V281='13' V1='4' name='AssetRiskIVO'>
        </savedOrigCopyAtInheritsFrom>
      </child>
    </child>
    <child t='167' id='84' V167='21' V283='2' occurMaxTimes='1' minSize='-1' maxSize='-1' groupType='1' repHandlerStruct='' visible='true' inheritsFrom='' V281='13' V1='4' name='assetPropertyRoomsIVOsList'>
      <structNode t='150' idref='1'/>
      <child t='167' id='85' V167='21' inheritsFromIncarnation='8' inheritsFromTimestamp='0x19077fc67ed' inheritsInThisStruct='true' V283='2' occurMaxTimes='-1' minSize='-1' maxSize='-1' inheritsFromCopyRule='20' groupType='3' repHandlerStruct='' visible='true' inheritsFrom='Structures/CI_QA_all_interfaces_20240703/Types/interfaces/AssetPropertyRoomsIVO.xml' V281='13' V1='4' name='assetPropertyRoomsIVOs'>
        <structNode t='150' idref='1'/>
        <savedDerivedCopy t='167' id='86' V167='21' needInheritInit='true' inheritsInThisStruct='true' V283='2' occurMaxTimes='-1' minSize='-1' maxSize='-1' inheritsFromCopyRule='20' dataType='2' repHandlerStruct='' visible='true' inheritsFrom='Structures/CI_QA_all_interfaces_20240703/Types/interfaces/AssetPropertyRoomsIVO.xml' V281='13' V1='4' name='assetPropertyRoomsIVOs'>
        </savedDerivedCopy>
        <savedOrigCopyAtInheritsFrom t='167' id='87' V167='21' V283='2' occurMaxTimes='1' minSize='-1' maxSize='-1' groupType='3' repHandlerStruct='' visible='true' inheritsFrom='' namespaceIndex='1' V281='13' V1='4' name='AssetPropertyRoomsIVO'>
        </savedOrigCopyAtInheritsFrom>
      </child>
    </child>
    <child t='167' id='88' V167='21' V283='2' occurMaxTimes='1' minSize='-1' maxSize='-1' dataType='2' repHandlerStruct='' visible='true' inheritsFrom='' V281='13' V1='4' name='accessDoorstypeRef' description='dynamic table type and id: class com.idit.reference.server.ejb3.vo.TDynamicReferenceDataVO and dynamic tabled id is:20915'>
      <structNode t='150' idref='1'/>
      <child t='167' id='89' V167='21' V283='2' occurMaxTimes='1' minSize='-1' maxSize='-1' groupType='3' repHandlerStruct='' inheritsFrom='' V281='13' V1='4' name='Attributes'>
        <structNode t='150' idref='1'/>
        <child t='167' id='90' V167='21' V283='2' occurMinTimes='1' occurMaxTimes='1' minSize='-1' maxSize='-1' dataType='13' elemType='1' repHandlerStruct='' visible='true' inheritsFrom='' V281='13' V1='4' name='id'>
          <structNode t='150' idref='1'/>
        </child>
        <child t='167' id='91' V167='21' V283='2' occurMaxTimes='1' minSize='-1' maxSize='-1' dataType='2' elemType='1' repHandlerStruct='' visible='true' inheritsFrom='' V281='13' V1='4' name='extCode'>
          <structNode t='150' idref='1'/>
        </child>
      </child>
    </child>
    <child t='167' id='92' V167='21' V283='2' occurMaxTimes='1' minSize='-1' maxSize='-1' dataType='2' repHandlerStruct='' visible='true' inheritsFrom='' V281='13' V1='4' name='heatingStandardsFlagVORef' description='Kennzeichnen Sie, ob das Heizsystem den Standards entsprichtFlag whether heating system meets the standardsFlag whether heating ...'>
      <structNode t='150' idref='1'/>
      <longDesc>Kennzeichnen Sie, ob das Heizsystem den Standards entsprichtFlag whether heating system meets the standardsFlag whether heating system meets the standardsoriginal type: class com.idit.reference.common.vo.TYesNoVO</longDesc>
      <child t='167' id='93' V167='21' V283='2' occurMaxTimes='1' minSize='-1' maxSize='-1' groupType='3' repHandlerStruct='' inheritsFrom='' V281='13' V1='4' name='Attributes'>
        <structNode t='150' idref='1'/>
        <child t='167' id='94' V167='21' V283='2' occurMinTimes='1' occurMaxTimes='1' minSize='-1' maxSize='-1' dataType='13' elemType='1' repHandlerStruct='' visible='true' inheritsFrom='' V281='13' V1='4' name='id'>
          <structNode t='150' idref='1'/>
        </child>
        <child t='167' id='95' V167='21' V283='2' occurMaxTimes='1' minSize='-1' maxSize='-1' dataType='2' elemType='1' repHandlerStruct='' visible='true' inheritsFrom='' V281='13' V1='4' name='extCode'>
          <structNode t='150' idref='1'/>
        </child>
      </child>
    </child>
    <child t='167' id='96' V167='21' V283='2' occurMinTimes='1' occurMaxTimes='1' minSize='-1' maxSize='-1' dataType='2' repHandlerStruct='' visible='true' inheritsFrom='' V281='13' V1='4' name='lodgerTypeVORef' description='Lodger Type (Eigentümer, Mandant) - Fremdschlüssel für T_LODGER_TYPELodger Type (owner, tenant) - foreign key to T_LODGER_TYPELo...'>
      <structNode t='150' idref='1'/>
      <longDesc>Lodger Type (Eigentümer, Mandant) - Fremdschlüssel für T_LODGER_TYPELodger Type (owner, tenant) - foreign key to T_LODGER_TYPELodger Type (owner, tenant) - foreign key to T_LODGER_TYPEoriginal type: class com.idit.product.common.reference.vo.TLodgerTypeVO</longDesc>
      <child t='167' id='97' V167='21' V283='2' occurMaxTimes='1' minSize='-1' maxSize='-1' groupType='3' repHandlerStruct='' inheritsFrom='' V281='13' V1='4' name='Attributes'>
        <structNode t='150' idref='1'/>
        <child t='167' id='98' V167='21' V283='2' occurMinTimes='1' occurMaxTimes='1' minSize='-1' maxSize='-1' dataType='13' elemType='1' repHandlerStruct='' visible='true' inheritsFrom='' V281='13' V1='4' name='id'>
          <structNode t='150' idref='1'/>
        </child>
        <child t='167' id='99' V167='21' V283='2' occurMaxTimes='1' minSize='-1' maxSize='-1' dataType='2' elemType='1' repHandlerStruct='' visible='true' inheritsFrom='' V281='13' V1='4' name='extCode'>
          <structNode t='150' idref='1'/>
        </child>
      </child>
    </child>
    <child t='167' id='100' V167='21' V283='2' occurMaxTimes='1' minSize='-1' maxSize='-1' dataType='2' repHandlerStruct='' visible='true' inheritsFrom='' V281='13' V1='4' name='staircaseTypeVORef' description='Eigenschaftstreppentyp - Fremdschlüssel für T_STAIRCASE_TYPEProperty staircase type - foreign key to T_STAIRCASE_TYPEProperty st...'>
      <structNode t='150' idref='1'/>
      <longDesc>Eigenschaftstreppentyp - Fremdschlüssel für T_STAIRCASE_TYPEProperty staircase type - foreign key to T_STAIRCASE_TYPEProperty staircase type - foreign key to T_STAIRCASE_TYPEoriginal type: class com.idit.policy.common.reference.vo.TPropertyStaircaseTypeVO</longDesc>
      <child t='167' id='101' V167='21' V283='2' occurMaxTimes='1' minSize='-1' maxSize='-1' groupType='3' repHandlerStruct='' inheritsFrom='' V281='13' V1='4' name='Attributes'>
        <structNode t='150' idref='1'/>
        <child t='167' id='102' V167='21' V283='2' occurMinTimes='1' occurMaxTimes='1' minSize='-1' maxSize='-1' dataType='13' elemType='1' repHandlerStruct='' visible='true' inheritsFrom='' V281='13' V1='4' name='id'>
          <structNode t='150' idref='1'/>
        </child>
        <child t='167' id='103' V167='21' V283='2' occurMaxTimes='1' minSize='-1' maxSize='-1' dataType='2' elemType='1' repHandlerStruct='' visible='true' inheritsFrom='' V281='13' V1='4' name='extCode'>
          <structNode t='150' idref='1'/>
        </child>
      </child>
    </child>
    <child t='167' id='104' V167='21' V283='2' occurMaxTimes='1' minSize='-1' maxSize='-1' dataType='21' repHandlerStruct='' visible='true' inheritsFrom='' V281='13' V1='4' name='surface' description='OberflächeSurfaceSurface'>
      <structNode t='150' idref='1'/>
    </child>
    <child t='167' id='105' V167='21' V283='2' occurMaxTimes='1' minSize='-1' maxSize='-1' dataType='2' repHandlerStruct='' visible='true' inheritsFrom='' V281='13' V1='4' name='smokeDetectorsExistsVORef' description='original type: class com.idit.reference.common.vo.TYesNoVO'>
      <structNode t='150' idref='1'/>
      <child t='167' id='106' V167='21' V283='2' occurMaxTimes='1' minSize='-1' maxSize='-1' groupType='3' repHandlerStruct='' inheritsFrom='' V281='13' V1='4' name='Attributes'>
        <structNode t='150' idref='1'/>
        <child t='167' id='107' V167='21' V283='2' occurMinTimes='1' occurMaxTimes='1' minSize='-1' maxSize='-1' dataType='13' elemType='1' repHandlerStruct='' visible='true' inheritsFrom='' V281='13' V1='4' name='id'>
          <structNode t='150' idref='1'/>
        </child>
        <child t='167' id='108' V167='21' V283='2' occurMaxTimes='1' minSize='-1' maxSize='-1' dataType='2' elemType='1' repHandlerStruct='' visible='true' inheritsFrom='' V281='13' V1='4' name='extCode'>
          <structNode t='150' idref='1'/>
        </child>
      </child>
    </child>
    <child t='167' id='109' V167='21' V283='2' occurMaxTimes='1' minSize='-1' maxSize='-1' dataType='2' repHandlerStruct='' visible='true' inheritsFrom='' V281='13' V1='4' name='unoccupancyVORef' description='original type: class com.idit.policy.common.reference.vo.TUnoccupancyVO'>
      <structNode t='150' idref='1'/>
      <child t='167' id='110' V167='21' V283='2' occurMaxTimes='1' minSize='-1' maxSize='-1' groupType='3' repHandlerStruct='' inheritsFrom='' V281='13' V1='4' name='Attributes'>
        <structNode t='150' idref='1'/>
        <child t='167' id='111' V167='21' V283='2' occurMinTimes='1' occurMaxTimes='1' minSize='-1' maxSize='-1' dataType='13' elemType='1' repHandlerStruct='' visible='true' inheritsFrom='' V281='13' V1='4' name='id'>
          <structNode t='150' idref='1'/>
        </child>
        <child t='167' id='112' V167='21' V283='2' occurMaxTimes='1' minSize='-1' maxSize='-1' dataType='2' elemType='1' repHandlerStruct='' visible='true' inheritsFrom='' V281='13' V1='4' name='extCode'>
          <structNode t='150' idref='1'/>
        </child>
      </child>
    </child>
    <child t='167' id='113' V167='21' V283='2' occurMaxTimes='1' minSize='-1' maxSize='-1' dataType='2' repHandlerStruct='' visible='true' inheritsFrom='' V281='13' V1='4' name='assetDescription' description='Asset-BeschreibungAsset descriptionAsset description'>
      <structNode t='150' idref='1'/>
    </child>
    <child t='167' id='114' V167='21' V283='2' occurMaxTimes='1' minSize='-1' maxSize='-1' dataType='2' repHandlerStruct='' visible='true' inheritsFrom='' V281='13' V1='4' name='peakUntil1' description='Enddatum der Geschäftsspitzenperiode 1 - wird für Immobilien vom Geschäftstyp verwendetBusiness peak period 1 end date - used fo...'>
      <structNode t='150' idref='1'/>
      <longDesc>Enddatum der Geschäftsspitzenperiode 1 - wird für Immobilien vom Geschäftstyp verwendetBusiness peak period 1 end date - used for business type propertyBusiness peak period 1 end date - used for business type property</longDesc>
    </child>
    <child t='167' id='115' V167='21' V283='2' occurMaxTimes='1' minSize='-1' maxSize='-1' dataType='2' repHandlerStruct='' visible='true' inheritsFrom='' V281='13' V1='4' name='peakUntil2' description='Enddatum der Geschäftsspitzenperiode 2 - wird für Immobilien vom Geschäftstyp verwendetBusiness peak period 2 end date - used fo...'>
      <structNode t='150' idref='1'/>
      <longDesc>Enddatum der Geschäftsspitzenperiode 2 - wird für Immobilien vom Geschäftstyp verwendetBusiness peak period 2 end date - used for business type propertyBusiness peak period 2 end date - used for business type property</longDesc>
    </child>
    <child t='167' id='116' V167='21' V283='2' occurMaxTimes='1' minSize='-1' maxSize='-1' dataType='2' repHandlerStruct='' visible='true' inheritsFrom='' V281='13' V1='4' name='propertyAlarmTypeVORef' description='Erforderlicher Diebstahlalarmtyp - Fremdschlüssel für T_PROPERTY_ALARM_TYPERequired theft alarm type - foreign key to T_PROPERTY...'>
      <structNode t='150' idref='1'/>
      <longDesc>Erforderlicher Diebstahlalarmtyp - Fremdschlüssel für T_PROPERTY_ALARM_TYPERequired theft alarm type - foreign key to T_PROPERTY_ALARM_TYPERequired theft alarm type - foreign key to T_PROPERTY_ALARM_TYPEoriginal type: class com.idit.reference.common.vo.TPropertyAlarmTypeVO</longDesc>
      <child t='167' id='117' V167='21' V283='2' occurMaxTimes='1' minSize='-1' maxSize='-1' groupType='3' repHandlerStruct='' inheritsFrom='' V281='13' V1='4' name='Attributes'>
        <structNode t='150' idref='1'/>
        <child t='167' id='118' V167='21' V283='2' occurMinTimes='1' occurMaxTimes='1' minSize='-1' maxSize='-1' dataType='13' elemType='1' repHandlerStruct='' visible='true' inheritsFrom='' V281='13' V1='4' name='id'>
          <structNode t='150' idref='1'/>
        </child>
        <child t='167' id='119' V167='21' V283='2' occurMaxTimes='1' minSize='-1' maxSize='-1' dataType='2' elemType='1' repHandlerStruct='' visible='true' inheritsFrom='' V281='13' V1='4' name='extCode'>
          <structNode t='150' idref='1'/>
        </child>
      </child>
    </child>
    <child t='167' id='120' V167='21' V283='2' occurMaxTimes='1' minSize='-1' maxSize='-1' dataType='2' repHandlerStruct='' visible='true' inheritsFrom='' V281='13' V1='4' name='waterLeakDetectExistsVORef' description='original type: class com.idit.reference.common.vo.TYesNoVO'>
      <structNode t='150' idref='1'/>
      <child t='167' id='121' V167='21' V283='2' occurMaxTimes='1' minSize='-1' maxSize='-1' groupType='3' repHandlerStruct='' inheritsFrom='' V281='13' V1='4' name='Attributes'>
        <structNode t='150' idref='1'/>
        <child t='167' id='122' V167='21' V283='2' occurMinTimes='1' occurMaxTimes='1' minSize='-1' maxSize='-1' dataType='13' elemType='1' repHandlerStruct='' visible='true' inheritsFrom='' V281='13' V1='4' name='id'>
          <structNode t='150' idref='1'/>
        </child>
        <child t='167' id='123' V167='21' V283='2' occurMaxTimes='1' minSize='-1' maxSize='-1' dataType='2' elemType='1' repHandlerStruct='' visible='true' inheritsFrom='' V281='13' V1='4' name='extCode'>
          <structNode t='150' idref='1'/>
        </child>
      </child>
    </child>
    <child t='167' id='124' V167='21' V283='2' occurMaxTimes='1' minSize='-1' maxSize='-1' dataType='2' repHandlerStruct='' visible='true' inheritsFrom='' V281='13' V1='4' name='previousClaimsFlagRef' description='Kennzeichnen Sie, ob frühere Ansprüche vorhanden sind - Fremdschlüssel für die Tabelle T_YES_NOFlag whether previous claims exis...'>
      <structNode t='150' idref='1'/>
      <longDesc>Kennzeichnen Sie, ob frühere Ansprüche vorhanden sind - Fremdschlüssel für die Tabelle T_YES_NOFlag whether previous claims exist - foreign key to T_YES_NO tableFlag whether previous claims exist - foreign key to T_YES_NO tableoriginal type: class com.idit.reference.common.vo.TYesNoVO</longDesc>
      <child t='167' id='125' V167='21' V283='2' occurMaxTimes='1' minSize='-1' maxSize='-1' groupType='3' repHandlerStruct='' inheritsFrom='' V281='13' V1='4' name='Attributes'>
        <structNode t='150' idref='1'/>
        <child t='167' id='126' V167='21' V283='2' occurMinTimes='1' occurMaxTimes='1' minSize='-1' maxSize='-1' dataType='13' elemType='1' repHandlerStruct='' visible='true' inheritsFrom='' V281='13' V1='4' name='id'>
          <structNode t='150' idref='1'/>
        </child>
        <child t='167' id='127' V167='21' V283='2' occurMaxTimes='1' minSize='-1' maxSize='-1' dataType='2' elemType='1' repHandlerStruct='' visible='true' inheritsFrom='' V281='13' V1='4' name='extCode'>
          <structNode t='150' idref='1'/>
        </child>
      </child>
    </child>
    <child t='167' id='128' V167='21' V283='2' occurMaxTimes='1' minSize='-1' maxSize='-1' dataType='2' repHandlerStruct='' visible='true' inheritsFrom='' V281='13' V1='4' name='specialHighValueItemsVORef' description='original type: class com.idit.reference.common.vo.TYesNoVO'>
      <structNode t='150' idref='1'/>
      <child t='167' id='129' V167='21' V283='2' occurMaxTimes='1' minSize='-1' maxSize='-1' groupType='3' repHandlerStruct='' inheritsFrom='' V281='13' V1='4' name='Attributes'>
        <structNode t='150' idref='1'/>
        <child t='167' id='130' V167='21' V283='2' occurMinTimes='1' occurMaxTimes='1' minSize='-1' maxSize='-1' dataType='13' elemType='1' repHandlerStruct='' visible='true' inheritsFrom='' V281='13' V1='4' name='id'>
          <structNode t='150' idref='1'/>
        </child>
        <child t='167' id='131' V167='21' V283='2' occurMaxTimes='1' minSize='-1' maxSize='-1' dataType='2' elemType='1' repHandlerStruct='' visible='true' inheritsFrom='' V281='13' V1='4' name='extCode'>
          <structNode t='150' idref='1'/>
        </child>
      </child>
    </child>
    <child t='167' id='132' V167='21' V283='2' occurMaxTimes='1' minSize='-1' maxSize='-1' dataType='2' repHandlerStruct='' visible='true' inheritsFrom='' V281='13' V1='4' name='buildingtypesmeRef' description='dynamic table type and id: class com.idit.reference.server.ejb3.vo.TDynamicReferenceDataVO and dynamic tabled id is:20909'>
      <structNode t='150' idref='1'/>
      <child t='167' id='133' V167='21' V283='2' occurMaxTimes='1' minSize='-1' maxSize='-1' groupType='3' repHandlerStruct='' inheritsFrom='' V281='13' V1='4' name='Attributes'>
        <structNode t='150' idref='1'/>
        <child t='167' id='134' V167='21' V283='2' occurMinTimes='1' occurMaxTimes='1' minSize='-1' maxSize='-1' dataType='13' elemType='1' repHandlerStruct='' visible='true' inheritsFrom='' V281='13' V1='4' name='id'>
          <structNode t='150' idref='1'/>
        </child>
        <child t='167' id='135' V167='21' V283='2' occurMaxTimes='1' minSize='-1' maxSize='-1' dataType='2' elemType='1' repHandlerStruct='' visible='true' inheritsFrom='' V281='13' V1='4' name='extCode'>
          <structNode t='150' idref='1'/>
        </child>
      </child>
    </child>
    <child t='167' id='136' V167='21' V283='2' occurMaxTimes='1' minSize='-1' maxSize='-1' dataType='2' repHandlerStruct='' visible='true' inheritsFrom='' V281='13' V1='4' name='mortgageTypeVORef' description='original type: class com.idit.policy.common.reference.vo.TMortgageTypesVO'>
      <structNode t='150' idref='1'/>
      <child t='167' id='137' V167='21' V283='2' occurMaxTimes='1' minSize='-1' maxSize='-1' groupType='3' repHandlerStruct='' inheritsFrom='' V281='13' V1='4' name='Attributes'>
        <structNode t='150' idref='1'/>
        <child t='167' id='138' V167='21' V283='2' occurMinTimes='1' occurMaxTimes='1' minSize='-1' maxSize='-1' dataType='13' elemType='1' repHandlerStruct='' visible='true' inheritsFrom='' V281='13' V1='4' name='id'>
          <structNode t='150' idref='1'/>
        </child>
        <child t='167' id='139' V167='21' V283='2' occurMaxTimes='1' minSize='-1' maxSize='-1' dataType='2' elemType='1' repHandlerStruct='' visible='true' inheritsFrom='' V281='13' V1='4' name='extCode'>
          <structNode t='150' idref='1'/>
        </child>
      </child>
    </child>
    <child t='167' id='140' V167='21' V283='2' occurMaxTimes='1' minSize='-1' maxSize='-1' dataType='2' repHandlerStruct='' visible='true' inheritsFrom='' V281='13' V1='4' name='propertyOwnVORef' description='original type: class com.idit.policy.common.reference.vo.TPropertyOwnVO'>
      <structNode t='150' idref='1'/>
      <child t='167' id='141' V167='21' V283='2' occurMaxTimes='1' minSize='-1' maxSize='-1' groupType='3' repHandlerStruct='' inheritsFrom='' V281='13' V1='4' name='Attributes'>
        <structNode t='150' idref='1'/>
        <child t='167' id='142' V167='21' V283='2' occurMinTimes='1' occurMaxTimes='1' minSize='-1' maxSize='-1' dataType='13' elemType='1' repHandlerStruct='' visible='true' inheritsFrom='' V281='13' V1='4' name='id'>
          <structNode t='150' idref='1'/>
        </child>
        <child t='167' id='143' V167='21' V283='2' occurMaxTimes='1' minSize='-1' maxSize='-1' dataType='2' elemType='1' repHandlerStruct='' visible='true' inheritsFrom='' V281='13' V1='4' name='extCode'>
          <structNode t='150' idref='1'/>
        </child>
      </child>
    </child>
    <child t='167' id='144' V167='21' V283='2' occurMaxTimes='1' minSize='-1' maxSize='-1' dataType='1' repHandlerStruct='' visible='true' inheritsFrom='' V281='13' V1='4' name='futureRateFlag'>
      <structNode t='150' idref='1'/>
    </child>
    <child t='167' id='145' V167='21' inheritsFromIncarnation='8' inheritsFromTimestamp='0x19077fc6832' inheritsInThisStruct='true' V283='2' occurMaxTimes='1' minSize='-1' maxSize='-1' inheritsFromCopyRule='20' groupType='3' repHandlerStruct='' visible='true' inheritsFrom='Structures/CI_QA_all_interfaces_20240703/Types/interfaces/PastInsuranceIVO.xml' V281='13' V1='4' name='pastInsuranceVO' description='Details zur vorherigen Versicherung des VermögenswertsAsset previous insurance detailsAsset previous insurance details'>
      <structNode t='150' idref='1'/>
      <savedDerivedCopy t='167' id='146' V167='21' needInheritInit='true' inheritsInThisStruct='true' V283='2' occurMaxTimes='1' minSize='-1' maxSize='-1' inheritsFromCopyRule='20' dataType='2' repHandlerStruct='' visible='true' inheritsFrom='Structures/CI_QA_all_interfaces_20240703/Types/interfaces/PastInsuranceIVO.xml' V281='13' V1='4' name='pastInsuranceVO' description='Details zur vorherigen Versicherung des VermögenswertsAsset previous insurance detailsAsset previous insurance details'>
      </savedDerivedCopy>
      <savedOrigCopyAtInheritsFrom t='167' id='147' V167='21' V283='2' occurMaxTimes='1' minSize='-1' maxSize='-1' groupType='3' repHandlerStruct='' visible='true' inheritsFrom='' namespaceIndex='1' V281='13' V1='4' name='PastInsuranceIVO'>
      </savedOrigCopyAtInheritsFrom>
    </child>
    <child t='167' id='148' V167='21' V283='2' occurMaxTimes='1' minSize='-1' maxSize='-1' dataType='21' repHandlerStruct='' visible='true' inheritsFrom='' V281='13' V1='4' name='combustiblePercentage' description='Prozentsatz brennbarer MaterialienPercentage of combustible materialsPercentage of combustible materials'>
      <structNode t='150' idref='1'/>
    </child>
    <child t='167' id='149' V167='21' V283='2' occurMaxTimes='1' minSize='-1' maxSize='-1' dataType='13' repHandlerStruct='' visible='true' inheritsFrom='' V281='13' V1='4' name='childrenLivingInProp'>
      <structNode t='150' idref='1'/>
    </child>
    <child t='167' id='150' V167='21' V283='2' occurMaxTimes='1' minSize='-1' maxSize='-1' dataType='13' repHandlerStruct='' visible='true' inheritsFrom='' V281='13' V1='4' name='inPropertySince'>
      <structNode t='150' idref='1'/>
    </child>
    <child t='167' id='151' V167='21' V283='2' occurMaxTimes='1' minSize='-1' maxSize='-1' groupType='1' repHandlerStruct='' visible='true' inheritsFrom='' V281='13' V1='4' name='assetItemVOsList'>
      <structNode t='150' idref='1'/>
      <child t='167' id='152' V167='21' inheritsFromIncarnation='8' inheritsFromTimestamp='0x19077fc67e8' inheritsInThisStruct='true' V283='2' occurMaxTimes='-1' minSize='-1' maxSize='-1' inheritsFromCopyRule='20' groupType='3' repHandlerStruct='' visible='true' inheritsFrom='Structures/CI_QA_all_interfaces_20240703/Types/interfaces/AssetItemIVO.xml' V281='13' V1='4' name='assetItemVOs' description='Liste der Asset-ElementeList of asset itemsList of asset items' checksumValid='true' checksum='16nZ/Zje+hw6JNClGts/nWpXG+I='>
        <structNode t='150' idref='1'/>
        <savedDerivedCopy t='167' id='153' V167='21' needInheritInit='true' inheritsInThisStruct='true' V283='2' occurMaxTimes='-1' minSize='-1' maxSize='-1' inheritsFromCopyRule='20' dataType='2' repHandlerStruct='' visible='true' inheritsFrom='Structures/CI_QA_all_interfaces_20240703/Types/interfaces/AssetItemIVO.xml' V281='13' V1='4' name='assetItemVOs' description='Liste der Asset-ElementeList of asset itemsList of asset items'>
        </savedDerivedCopy>
        <savedOrigCopyAtInheritsFrom t='167' id='154' V167='21' V283='2' occurMaxTimes='1' minSize='-1' maxSize='-1' groupType='3' repHandlerStruct='' visible='true' inheritsFrom='' namespaceIndex='1' V281='13' V1='4' name='AssetItemIVO'>
        </savedOrigCopyAtInheritsFrom>
      </child>
    </child>
    <child t='167' id='155' V167='21' V283='2' occurMaxTimes='1' minSize='-1' maxSize='-1' dataType='2' repHandlerStruct='' visible='true' inheritsFrom='' V281='13' V1='4' name='electricalStandardsFlagVORef' description='Kennzeichnen Sie, ob die Eigenschaft dem elektrischen Standard entsprichtFlag whether property meets electrical standardFlag whe...'>
      <structNode t='150' idref='1'/>
      <longDesc>Kennzeichnen Sie, ob die Eigenschaft dem elektrischen Standard entsprichtFlag whether property meets electrical standardFlag whether property meets electrical standardoriginal type: class com.idit.reference.common.vo.TYesNoVO</longDesc>
      <child t='167' id='156' V167='21' V283='2' occurMaxTimes='1' minSize='-1' maxSize='-1' groupType='3' repHandlerStruct='' inheritsFrom='' V281='13' V1='4' name='Attributes'>
        <structNode t='150' idref='1'/>
        <child t='167' id='157' V167='21' V283='2' occurMinTimes='1' occurMaxTimes='1' minSize='-1' maxSize='-1' dataType='13' elemType='1' repHandlerStruct='' visible='true' inheritsFrom='' V281='13' V1='4' name='id'>
          <structNode t='150' idref='1'/>
        </child>
        <child t='167' id='158' V167='21' V283='2' occurMaxTimes='1' minSize='-1' maxSize='-1' dataType='2' elemType='1' repHandlerStruct='' visible='true' inheritsFrom='' V281='13' V1='4' name='extCode'>
          <structNode t='150' idref='1'/>
        </child>
      </child>
    </child>
    <child t='167' id='159' V167='21' V283='2' occurMaxTimes='1' minSize='-1' maxSize='-1' dataType='2' repHandlerStruct='' visible='true' inheritsFrom='' V281='13' V1='4' name='sprinklerTypeRef' description='dynamic table type and id: class com.idit.reference.server.ejb3.vo.TDynamicReferenceDataVO and dynamic tabled id is:20912'>
      <structNode t='150' idref='1'/>
      <child t='167' id='160' V167='21' V283='2' occurMaxTimes='1' minSize='-1' maxSize='-1' groupType='3' repHandlerStruct='' inheritsFrom='' V281='13' V1='4' name='Attributes'>
        <structNode t='150' idref='1'/>
        <child t='167' id='161' V167='21' V283='2' occurMinTimes='1' occurMaxTimes='1' minSize='-1' maxSize='-1' dataType='13' elemType='1' repHandlerStruct='' visible='true' inheritsFrom='' V281='13' V1='4' name='id'>
          <structNode t='150' idref='1'/>
        </child>
        <child t='167' id='162' V167='21' V283='2' occurMaxTimes='1' minSize='-1' maxSize='-1' dataType='2' elemType='1' repHandlerStruct='' visible='true' inheritsFrom='' V281='13' V1='4' name='extCode'>
          <structNode t='150' idref='1'/>
        </child>
      </child>
    </child>
    <child t='167' id='163' V167='21' V283='2' occurMaxTimes='1' minSize='-1' maxSize='-1' dataType='2' repHandlerStruct='' visible='true' inheritsFrom='' V281='13' V1='4' name='buildingTypeVORef' description='Gebäudetyp - 1 Seite nebeneinander, 2 Seite nebeneinander usw. - Fremdschlüssel T_BUILDING_TYPEType of building - 1 side adjacen...'>
      <structNode t='150' idref='1'/>
      <longDesc>Gebäudetyp - 1 Seite nebeneinander, 2 Seite nebeneinander usw. - Fremdschlüssel T_BUILDING_TYPEType of building - 1 side adjacent, 2 side adjacent, etc - foreign key T_BUILDING_TYPEType of building - 1 side adjacent, 2 side adjacent, etc - foreign key T_BUILDING_TYPEoriginal type: class com.idit.product.common.reference.vo.TBuildingTypeVO</longDesc>
      <child t='167' id='164' V167='21' V283='2' occurMaxTimes='1' minSize='-1' maxSize='-1' groupType='3' repHandlerStruct='' inheritsFrom='' V281='13' V1='4' name='Attributes'>
        <structNode t='150' idref='1'/>
        <child t='167' id='165' V167='21' V283='2' occurMinTimes='1' occurMaxTimes='1' minSize='-1' maxSize='-1' dataType='13' elemType='1' repHandlerStruct='' visible='true' inheritsFrom='' V281='13' V1='4' name='id'>
          <structNode t='150' idref='1'/>
        </child>
        <child t='167' id='166' V167='21' V283='2' occurMaxTimes='1' minSize='-1' maxSize='-1' dataType='2' elemType='1' repHandlerStruct='' visible='true' inheritsFrom='' V281='13' V1='4' name='extCode'>
          <structNode t='150' idref='1'/>
        </child>
      </child>
    </child>
    <child t='167' id='167' V167='21' V283='2' occurMaxTimes='1' minSize='-1' maxSize='-1' dataType='2' repHandlerStruct='' visible='true' inheritsFrom='' V281='13' V1='4' name='blgListedStatusVORef' description='original type: class com.idit.policy.common.reference.vo.TBlgListedStatusVO'>
      <structNode t='150' idref='1'/>
      <child t='167' id='168' V167='21' V283='2' occurMaxTimes='1' minSize='-1' maxSize='-1' groupType='3' repHandlerStruct='' inheritsFrom='' V281='13' V1='4' name='Attributes'>
        <structNode t='150' idref='1'/>
        <child t='167' id='169' V167='21' V283='2' occurMinTimes='1' occurMaxTimes='1' minSize='-1' maxSize='-1' dataType='13' elemType='1' repHandlerStruct='' visible='true' inheritsFrom='' V281='13' V1='4' name='id'>
          <structNode t='150' idref='1'/>
        </child>
        <child t='167' id='170' V167='21' V283='2' occurMaxTimes='1' minSize='-1' maxSize='-1' dataType='2' elemType='1' repHandlerStruct='' visible='true' inheritsFrom='' V281='13' V1='4' name='extCode'>
          <structNode t='150' idref='1'/>
        </child>
      </child>
    </child>
    <child t='167' id='171' V167='21' V283='2' occurMinTimes='1' occurMaxTimes='1' minSize='-1' maxSize='-1' dataType='2' repHandlerStruct='' visible='true' inheritsFrom='' V281='13' V1='4' name='assetTypeVORef' description='Asset-Typ (Eigentum, Fahrzeug, Person usw.) - Fremdschlüssel für T_ASSET_TYPEAsset type (property, vehicle, person, etc.) - fore...'>
      <structNode t='150' idref='1'/>
      <longDesc>Asset-Typ (Eigentum, Fahrzeug, Person usw.) - Fremdschlüssel für T_ASSET_TYPEAsset type (property, vehicle, person, etc.) - foreign key to T_ASSET_TYPEAsset type (property, vehicle, person, etc.) - foreign key to T_ASSET_TYPEoriginal type: class com.idit.reference.common.vo.TAssetTypeVO</longDesc>
      <child t='167' id='172' V167='21' V283='2' occurMaxTimes='1' minSize='-1' maxSize='-1' groupType='3' repHandlerStruct='' inheritsFrom='' V281='13' V1='4' name='Attributes'>
        <structNode t='150' idref='1'/>
        <child t='167' id='173' V167='21' V283='2' occurMinTimes='1' occurMaxTimes='1' minSize='-1' maxSize='-1' dataType='13' elemType='1' repHandlerStruct='' visible='true' inheritsFrom='' V281='13' V1='4' name='id'>
          <structNode t='150' idref='1'/>
        </child>
        <child t='167' id='174' V167='21' V283='2' occurMaxTimes='1' minSize='-1' maxSize='-1' dataType='2' elemType='1' repHandlerStruct='' visible='true' inheritsFrom='' V281='13' V1='4' name='extCode'>
          <structNode t='150' idref='1'/>
        </child>
      </child>
    </child>
    <child t='167' id='175' V167='21' V283='2' occurMaxTimes='1' minSize='-1' maxSize='-1' groupType='1' repHandlerStruct='' visible='true' inheritsFrom='' V281='13' V1='4' name='assetIdentifierIVOsList'>
      <structNode t='150' idref='1'/>
      <child t='167' id='176' V167='21' inheritsFromIncarnation='8' inheritsFromTimestamp='0x19077fc67e7' inheritsInThisStruct='true' V283='2' occurMaxTimes='-1' minSize='-1' maxSize='-1' inheritsFromCopyRule='20' groupType='3' repHandlerStruct='' visible='true' inheritsFrom='Structures/CI_QA_all_interfaces_20240703/Types/interfaces/AssetIdentifierIVO.xml' V281='13' V1='4' name='assetIdentifierIVOs'>
        <structNode t='150' idref='1'/>
        <savedDerivedCopy t='167' id='177' V167='21' needInheritInit='true' inheritsInThisStruct='true' V283='2' occurMaxTimes='-1' minSize='-1' maxSize='-1' inheritsFromCopyRule='20' dataType='2' repHandlerStruct='' visible='true' inheritsFrom='Structures/CI_QA_all_interfaces_20240703/Types/interfaces/AssetIdentifierIVO.xml' V281='13' V1='4' name='assetIdentifierIVOs'>
        </savedDerivedCopy>
        <savedOrigCopyAtInheritsFrom t='167' id='178' V167='21' V283='2' occurMaxTimes='1' minSize='-1' maxSize='-1' groupType='3' repHandlerStruct='' visible='true' inheritsFrom='' namespaceIndex='1' V281='13' V1='4' name='AssetIdentifierIVO'>
        </savedOrigCopyAtInheritsFrom>
      </child>
    </child>
    <child t='167' id='179' V167='21' V283='2' occurMaxTimes='1' minSize='-1' maxSize='-1' dataType='2' repHandlerStruct='' visible='true' inheritsFrom='' V281='13' V1='4' name='constructionTypeVORef' description='Bauart (Holz, Prefarb usw.) - Fremdschlüssel für T_CONSTRUCTION_TYPEConstruction type (wooden, prefarb, etc.) - foreign key to T...'>
      <structNode t='150' idref='1'/>
      <longDesc>Bauart (Holz, Prefarb usw.) - Fremdschlüssel für T_CONSTRUCTION_TYPEConstruction type (wooden, prefarb, etc.) - foreign key to T_CONSTRUCTION_TYPEConstruction type (wooden, prefarb, etc.) - foreign key to T_CONSTRUCTION_TYPEoriginal type: class com.idit.reference.common.vo.TConstructionTypeVO</longDesc>
      <child t='167' id='180' V167='21' V283='2' occurMaxTimes='1' minSize='-1' maxSize='-1' groupType='3' repHandlerStruct='' inheritsFrom='' V281='13' V1='4' name='Attributes'>
        <structNode t='150' idref='1'/>
        <child t='167' id='181' V167='21' V283='2' occurMinTimes='1' occurMaxTimes='1' minSize='-1' maxSize='-1' dataType='13' elemType='1' repHandlerStruct='' visible='true' inheritsFrom='' V281='13' V1='4' name='id'>
          <structNode t='150' idref='1'/>
        </child>
        <child t='167' id='182' V167='21' V283='2' occurMaxTimes='1' minSize='-1' maxSize='-1' dataType='2' elemType='1' repHandlerStruct='' visible='true' inheritsFrom='' V281='13' V1='4' name='extCode'>
          <structNode t='150' idref='1'/>
        </child>
      </child>
    </child>
    <child t='167' id='183' V167='21' V283='2' occurMaxTimes='1' minSize='-1' maxSize='-1' dataType='2' repHandlerStruct='' visible='true' inheritsFrom='' V281='13' V1='4' name='tenantTypeVORef' description='original type: class com.idit.policy.common.reference.vo.TTenantTypeVO'>
      <structNode t='150' idref='1'/>
      <child t='167' id='184' V167='21' V283='2' occurMaxTimes='1' minSize='-1' maxSize='-1' groupType='3' repHandlerStruct='' inheritsFrom='' V281='13' V1='4' name='Attributes'>
        <structNode t='150' idref='1'/>
        <child t='167' id='185' V167='21' V283='2' occurMinTimes='1' occurMaxTimes='1' minSize='-1' maxSize='-1' dataType='13' elemType='1' repHandlerStruct='' visible='true' inheritsFrom='' V281='13' V1='4' name='id'>
          <structNode t='150' idref='1'/>
        </child>
        <child t='167' id='186' V167='21' V283='2' occurMaxTimes='1' minSize='-1' maxSize='-1' dataType='2' elemType='1' repHandlerStruct='' visible='true' inheritsFrom='' V281='13' V1='4' name='extCode'>
          <structNode t='150' idref='1'/>
        </child>
      </child>
    </child>
    <child t='167' id='187' V167='21' V283='2' occurMaxTimes='1' minSize='-1' maxSize='-1' dataType='2' repHandlerStruct='' visible='true' inheritsFrom='' V281='13' V1='4' name='roofingPercentVORef' description='original type: class com.idit.policy.common.reference.vo.TRoofingPercentageVO'>
      <structNode t='150' idref='1'/>
      <child t='167' id='188' V167='21' V283='2' occurMaxTimes='1' minSize='-1' maxSize='-1' groupType='3' repHandlerStruct='' inheritsFrom='' V281='13' V1='4' name='Attributes'>
        <structNode t='150' idref='1'/>
        <child t='167' id='189' V167='21' V283='2' occurMinTimes='1' occurMaxTimes='1' minSize='-1' maxSize='-1' dataType='13' elemType='1' repHandlerStruct='' visible='true' inheritsFrom='' V281='13' V1='4' name='id'>
          <structNode t='150' idref='1'/>
        </child>
        <child t='167' id='190' V167='21' V283='2' occurMaxTimes='1' minSize='-1' maxSize='-1' dataType='2' elemType='1' repHandlerStruct='' visible='true' inheritsFrom='' V281='13' V1='4' name='extCode'>
          <structNode t='150' idref='1'/>
        </child>
      </child>
    </child>
    <child t='167' id='191' V167='21' V283='2' occurMaxTimes='1' minSize='-1' maxSize='-1' dataType='21' repHandlerStruct='' visible='true' inheritsFrom='' V281='13' V1='4' name='amountRate'>
      <structNode t='150' idref='1'/>
    </child>
    <child t='167' id='192' V167='21' V283='2' occurMaxTimes='1' minSize='-1' maxSize='-1' dataType='2' repHandlerStruct='' visible='true' inheritsFrom='' V281='13' V1='4' name='remark' description='BemerkungenRemarksRemarks'>
      <structNode t='150' idref='1'/>
    </child>
    <child t='167' id='193' V167='21' V283='2' occurMaxTimes='1' minSize='-1' maxSize='-1' groupType='1' repHandlerStruct='' visible='true' inheritsFrom='' V281='13' V1='4' name='claimHistoryVOsList'>
      <structNode t='150' idref='1'/>
      <child t='167' id='194' V167='21' inheritsFromIncarnation='8' inheritsFromTimestamp='0x19077fc67e6' inheritsInThisStruct='true' V283='2' occurMaxTimes='-1' minSize='-1' maxSize='-1' inheritsFromCopyRule='20' groupType='3' repHandlerStruct='' visible='true' inheritsFrom='Structures/CI_QA_all_interfaces_20240703/Types/interfaces/AssetClaimHistoryIVO.xml' V281='13' V1='4' name='claimHistoryVOs' description='Liste der Asset-Claims-HistorieList of asset claims historyList of asset claims history' checksumValid='true' checksum='2mplSXO4JmATJJb3gpPnfC0gb5Q='>
        <structNode t='150' idref='1'/>
        <savedDerivedCopy t='167' id='195' V167='21' needInheritInit='true' inheritsInThisStruct='true' V283='2' occurMaxTimes='-1' minSize='-1' maxSize='-1' inheritsFromCopyRule='20' dataType='2' repHandlerStruct='' visible='true' inheritsFrom='Structures/CI_QA_all_interfaces_20240703/Types/interfaces/AssetClaimHistoryIVO.xml' V281='13' V1='4' name='claimHistoryVOs' description='Liste der Asset-Claims-HistorieList of asset claims historyList of asset claims history'>
        </savedDerivedCopy>
        <savedOrigCopyAtInheritsFrom t='167' id='196' V167='21' V283='2' occurMaxTimes='1' minSize='-1' maxSize='-1' groupType='3' repHandlerStruct='' visible='true' inheritsFrom='' namespaceIndex='1' V281='13' V1='4' name='AssetClaimHistoryIVO'>
        </savedOrigCopyAtInheritsFrom>
      </child>
    </child>
    <child t='167' id='197' V167='21' V283='2' occurMaxTimes='1' minSize='-1' maxSize='-1' dataType='2' repHandlerStruct='' visible='true' inheritsFrom='' V281='13' V1='4' name='propertyLocationTypeVORef' description='Verweis auf den Eigenschaftsspeicherorttyp (isoliert, nicht isoliert ...) auf T_PROPERTY_LOCATION_TYPEProperty location type (is...'>
      <structNode t='150' idref='1'/>
      <longDesc>Verweis auf den Eigenschaftsspeicherorttyp (isoliert, nicht isoliert ...) auf T_PROPERTY_LOCATION_TYPEProperty location type (isolated, not isolated...) reference to T_PROPERTY_LOCATION_TYPEProperty location type (isolated, not isolated...) reference to T_PROPERTY_LOCATION_TYPEoriginal type: class com.idit.policy.common.reference.vo.TPropertyLocationTypeVO</longDesc>
      <child t='167' id='198' V167='21' V283='2' occurMaxTimes='1' minSize='-1' maxSize='-1' groupType='3' repHandlerStruct='' inheritsFrom='' V281='13' V1='4' name='Attributes'>
        <structNode t='150' idref='1'/>
        <child t='167' id='199' V167='21' V283='2' occurMinTimes='1' occurMaxTimes='1' minSize='-1' maxSize='-1' dataType='13' elemType='1' repHandlerStruct='' visible='true' inheritsFrom='' V281='13' V1='4' name='id'>
          <structNode t='150' idref='1'/>
        </child>
        <child t='167' id='200' V167='21' V283='2' occurMaxTimes='1' minSize='-1' maxSize='-1' dataType='2' elemType='1' repHandlerStruct='' visible='true' inheritsFrom='' V281='13' V1='4' name='extCode'>
          <structNode t='150' idref='1'/>
        </child>
      </child>
    </child>
    <child t='167' id='201' V167='21' V283='2' occurMaxTimes='1' minSize='-1' maxSize='-1' dataType='2' repHandlerStruct='' visible='true' inheritsFrom='' V281='13' V1='4' name='deductibleLevelVORef' description='Selbstbehalt - Fremdschlüssel für T_DEDUCTIBLE_LEVELProperty deductible level - foreign key to T_DEDUCTIBLE_LEVELProperty deduct...'>
      <structNode t='150' idref='1'/>
      <longDesc>Selbstbehalt - Fremdschlüssel für T_DEDUCTIBLE_LEVELProperty deductible level - foreign key to T_DEDUCTIBLE_LEVELProperty deductible level - foreign key to T_DEDUCTIBLE_LEVELoriginal type: class com.idit.policy.common.reference.vo.TPropertyDeductibleLevelVO</longDesc>
      <child t='167' id='202' V167='21' V283='2' occurMaxTimes='1' minSize='-1' maxSize='-1' groupType='3' repHandlerStruct='' inheritsFrom='' V281='13' V1='4' name='Attributes'>
        <structNode t='150' idref='1'/>
        <child t='167' id='203' V167='21' V283='2' occurMinTimes='1' occurMaxTimes='1' minSize='-1' maxSize='-1' dataType='13' elemType='1' repHandlerStruct='' visible='true' inheritsFrom='' V281='13' V1='4' name='id'>
          <structNode t='150' idref='1'/>
        </child>
        <child t='167' id='204' V167='21' V283='2' occurMaxTimes='1' minSize='-1' maxSize='-1' dataType='2' elemType='1' repHandlerStruct='' visible='true' inheritsFrom='' V281='13' V1='4' name='extCode'>
          <structNode t='150' idref='1'/>
        </child>
      </child>
    </child>
    <child t='167' id='205' V167='21' V283='2' occurMaxTimes='1' minSize='-1' maxSize='-1' groupType='1' repHandlerStruct='' visible='true' inheritsFrom='' V281='13' V1='4' name='assetBeneficiaryVOsList'>
      <structNode t='150' idref='1'/>
      <child t='167' id='206' V167='21' inheritsFromIncarnation='8' inheritsFromTimestamp='0x19077fc67e5' inheritsInThisStruct='true' V283='2' occurMaxTimes='-1' minSize='-1' maxSize='-1' inheritsFromCopyRule='20' groupType='3' repHandlerStruct='' visible='true' inheritsFrom='Structures/CI_QA_all_interfaces_20240703/Types/interfaces/AssetBeneficiaryIVO.xml' V281='13' V1='4' name='assetBeneficiaryVOs' description='Liste der Begünstigten von VermögenswertenList of asset beneficiariesList of asset beneficiaries'>
        <structNode t='150' idref='1'/>
        <savedDerivedCopy t='167' id='207' V167='21' needInheritInit='true' inheritsInThisStruct='true' V283='2' occurMaxTimes='-1' minSize='-1' maxSize='-1' inheritsFromCopyRule='20' dataType='2' repHandlerStruct='' visible='true' inheritsFrom='Structures/CI_QA_all_interfaces_20240703/Types/interfaces/AssetBeneficiaryIVO.xml' V281='13' V1='4' name='assetBeneficiaryVOs' description='Liste der Begünstigten von VermögenswertenList of asset beneficiariesList of asset beneficiaries'>
        </savedDerivedCopy>
        <savedOrigCopyAtInheritsFrom t='167' id='208' V167='21' V283='2' occurMaxTimes='1' minSize='-1' maxSize='-1' groupType='3' repHandlerStruct='' visible='true' inheritsFrom='' namespaceIndex='1' V281='13' V1='4' name='AssetBeneficiaryIVO'>
        </savedOrigCopyAtInheritsFrom>
      </child>
    </child>
    <child t='167' id='209' V167='21' V283='2' occurMaxTimes='1' minSize='-1' maxSize='-1' dataType='2' repHandlerStruct='' visible='true' inheritsFrom='' V281='13' V1='4' name='fireAlarmRemark' description='Bemerkung zum FeueralarmRemark about fire alarmRemark about fire alarm'>
      <structNode t='150' idref='1'/>
    </child>
    <child t='167' id='210' V167='21' V283='2' occurMaxTimes='1' minSize='-1' maxSize='-1' dataType='2' repHandlerStruct='' visible='true' inheritsFrom='' V281='13' V1='4' name='propertyTypeVORef' description='Eigenschaftstyp (öffentlich, privat) - Fremdschlüssel für T_PROPERTY_TYPEProperty Type (public, private) - foreign key to T_PROP...'>
      <structNode t='150' idref='1'/>
      <longDesc>Eigenschaftstyp (öffentlich, privat) - Fremdschlüssel für T_PROPERTY_TYPEProperty Type (public, private) - foreign key to T_PROPERTY_TYPEProperty Type (public, private) - foreign key to T_PROPERTY_TYPEoriginal type: class com.idit.reference.common.vo.TPropertyTypeVO</longDesc>
      <child t='167' id='211' V167='21' V283='2' occurMaxTimes='1' minSize='-1' maxSize='-1' groupType='3' repHandlerStruct='' inheritsFrom='' V281='13' V1='4' name='Attributes'>
        <structNode t='150' idref='1'/>
        <child t='167' id='212' V167='21' V283='2' occurMinTimes='1' occurMaxTimes='1' minSize='-1' maxSize='-1' dataType='13' elemType='1' repHandlerStruct='' visible='true' inheritsFrom='' V281='13' V1='4' name='id'>
          <structNode t='150' idref='1'/>
        </child>
        <child t='167' id='213' V167='21' V283='2' occurMaxTimes='1' minSize='-1' maxSize='-1' dataType='2' elemType='1' repHandlerStruct='' visible='true' inheritsFrom='' V281='13' V1='4' name='extCode'>
          <structNode t='150' idref='1'/>
        </child>
      </child>
    </child>
    <child t='167' id='214' V167='21' V283='2' occurMaxTimes='1' minSize='-1' maxSize='-1' dataType='13' repHandlerStruct='' visible='true' inheritsFrom='' V281='13' V1='4' name='floors' description='Anzahl der EtagenNumber of floorsNumber of floors'>
      <structNode t='150' idref='1'/>
    </child>
    <child t='167' id='215' V167='21' inheritsFromIncarnation='8' inheritsFromTimestamp='0x19077fc67ed' inheritsInThisStruct='true' V283='2' occurMaxTimes='1' minSize='-1' maxSize='-1' inheritsFromCopyRule='20' groupType='3' repHandlerStruct='' visible='true' inheritsFrom='Structures/CI_QA_all_interfaces_20240703/Types/interfaces/AssetPropertyOfficeDetailsIVO.xml' V281='13' V1='4' name='officeDetails' description='BürodetailsOffice detailsOffice details'>
      <structNode t='150' idref='1'/>
      <savedDerivedCopy t='167' id='216' V167='21' needInheritInit='true' inheritsInThisStruct='true' V283='2' occurMaxTimes='1' minSize='-1' maxSize='-1' inheritsFromCopyRule='20' dataType='2' repHandlerStruct='' visible='true' inheritsFrom='Structures/CI_QA_all_interfaces_20240703/Types/interfaces/AssetPropertyOfficeDetailsIVO.xml' V281='13' V1='4' name='officeDetails' description='BürodetailsOffice detailsOffice details'>
      </savedDerivedCopy>
      <savedOrigCopyAtInheritsFrom t='167' id='217' V167='21' V283='2' occurMaxTimes='1' minSize='-1' maxSize='-1' groupType='3' repHandlerStruct='' visible='true' inheritsFrom='' namespaceIndex='1' V281='13' V1='4' name='AssetPropertyOfficeDetailsIVO'>
      </savedOrigCopyAtInheritsFrom>
    </child>
    <child t='167' id='218' V167='21' V283='2' occurMaxTimes='1' minSize='-1' maxSize='-1' dataType='2' repHandlerStruct='' visible='true' inheritsFrom='' V281='13' V1='4' name='propertyOccupationTypeVORef' description='Art der Immobilienbelegung (teilweise, insgesamt)Property occupation type (partial, total)Property occupation type (partial, tot...'>
      <structNode t='150' idref='1'/>
      <longDesc>Art der Immobilienbelegung (teilweise, insgesamt)Property occupation type (partial, total)Property occupation type (partial, total)original type: class com.idit.reference.common.vo.TPropertyOccupationTypeVO</longDesc>
      <child t='167' id='219' V167='21' V283='2' occurMaxTimes='1' minSize='-1' maxSize='-1' groupType='3' repHandlerStruct='' inheritsFrom='' V281='13' V1='4' name='Attributes'>
        <structNode t='150' idref='1'/>
        <child t='167' id='220' V167='21' V283='2' occurMinTimes='1' occurMaxTimes='1' minSize='-1' maxSize='-1' dataType='13' elemType='1' repHandlerStruct='' visible='true' inheritsFrom='' V281='13' V1='4' name='id'>
          <structNode t='150' idref='1'/>
        </child>
        <child t='167' id='221' V167='21' V283='2' occurMaxTimes='1' minSize='-1' maxSize='-1' dataType='2' elemType='1' repHandlerStruct='' visible='true' inheritsFrom='' V281='13' V1='4' name='extCode'>
          <structNode t='150' idref='1'/>
        </child>
      </child>
    </child>
    <child t='167' id='222' V167='21' inheritsFromIncarnation='8' inheritsFromTimestamp='0x19077fc67fc' inheritsInThisStruct='true' V283='2' occurMaxTimes='1' minSize='-1' maxSize='-1' inheritsFromCopyRule='20' groupType='3' repHandlerStruct='' visible='true' inheritsFrom='Structures/CI_QA_all_interfaces_20240703/Types/interfaces/BusinessInterruptionIVO.xml' V281='13' V1='4' name='businessInterruptionVO' description='Details zur BetriebsunterbrechungBusiness Interruption detailsBusiness Interruption details' checksumValid='true' checksum='kUm6z8L6/04yZ1pX1TfSGjjABX8='>
      <structNode t='150' idref='1'/>
      <savedDerivedCopy t='167' id='223' V167='21' needInheritInit='true' inheritsInThisStruct='true' V283='2' occurMaxTimes='1' minSize='-1' maxSize='-1' inheritsFromCopyRule='20' dataType='2' repHandlerStruct='' visible='true' inheritsFrom='Structures/CI_QA_all_interfaces_20240703/Types/interfaces/BusinessInterruptionIVO.xml' V281='13' V1='4' name='businessInterruptionVO' description='Details zur BetriebsunterbrechungBusiness Interruption detailsBusiness Interruption details'>
      </savedDerivedCopy>
      <savedOrigCopyAtInheritsFrom t='167' id='224' V167='21' V283='2' occurMaxTimes='1' minSize='-1' maxSize='-1' groupType='3' repHandlerStruct='' visible='true' inheritsFrom='' namespaceIndex='1' V281='13' V1='4' name='BusinessInterruptionIVO'>
      </savedOrigCopyAtInheritsFrom>
    </child>
    <child t='167' id='225' V167='21' V283='2' occurMaxTimes='1' minSize='-1' maxSize='-1' dataType='13' repHandlerStruct='' visible='true' inheritsFrom='' V281='13' V1='4' name='buildingYear' description='BaujahrBuilding YearBuilding Year'>
      <structNode t='150' idref='1'/>
    </child>
    <child t='167' id='226' V167='21' V283='2' occurMaxTimes='1' minSize='-1' maxSize='-1' dataType='2' repHandlerStruct='' visible='true' inheritsFrom='' V281='13' V1='4' name='smokeDetectorsRef' description='original type: class com.idit.reference.common.vo.TYesNoVO'>
      <structNode t='150' idref='1'/>
      <child t='167' id='227' V167='21' V283='2' occurMaxTimes='1' minSize='-1' maxSize='-1' groupType='3' repHandlerStruct='' inheritsFrom='' V281='13' V1='4' name='Attributes'>
        <structNode t='150' idref='1'/>
        <child t='167' id='228' V167='21' V283='2' occurMinTimes='1' occurMaxTimes='1' minSize='-1' maxSize='-1' dataType='13' elemType='1' repHandlerStruct='' visible='true' inheritsFrom='' V281='13' V1='4' name='id'>
          <structNode t='150' idref='1'/>
        </child>
        <child t='167' id='229' V167='21' V283='2' occurMaxTimes='1' minSize='-1' maxSize='-1' dataType='2' elemType='1' repHandlerStruct='' visible='true' inheritsFrom='' V281='13' V1='4' name='extCode'>
          <structNode t='150' idref='1'/>
        </child>
      </child>
    </child>
    <child t='167' id='230' V167='21' V283='2' occurMinTimes='1' occurMaxTimes='1' minSize='-1' maxSize='-1' dataType='13' repHandlerStruct='' visible='true' inheritsFrom='' V281='13' V1='4' name='mortgageFlag' description='Markieren Sie, ob eine Hypothek vorhanden ist - Fremdschlüssel für die Tabelle T_YES_NO, und legen Sie den Wert "0" fest.Flag wh...'>
      <structNode t='150' idref='1'/>
      <longDesc>Markieren Sie, ob eine Hypothek vorhanden ist - Fremdschlüssel für die Tabelle T_YES_NO, und legen Sie den Wert "0" fest.Flag whether mortgage exist - foreign key to T_YES_NO table, fix value "0".Flag whether mortgage exist - foreign key to T_YES_NO table, fix value "0".</longDesc>
    </child>
    <child t='167' id='231' V167='21' inheritsFromIncarnation='8' inheritsFromTimestamp='0x19077fc6836' inheritsInThisStruct='true' V283='2' occurMaxTimes='1' minSize='-1' maxSize='-1' inheritsFromCopyRule='20' groupType='3' repHandlerStruct='' visible='true' inheritsFrom='Structures/CI_QA_all_interfaces_20240703/Types/interfaces/PolicyAmountIVO.xml' V281='13' V1='4' name='marketValueAmountVO' checksumValid='true' checksum='fDxa40l9rEmD2V2Jt5Q306Dc7ZI='>
      <structNode t='150' idref='1'/>
      <savedDerivedCopy t='167' id='232' V167='21' needInheritInit='true' inheritsInThisStruct='true' V283='2' occurMaxTimes='1' minSize='-1' maxSize='-1' inheritsFromCopyRule='20' dataType='2' repHandlerStruct='' visible='true' inheritsFrom='Structures/CI_QA_all_interfaces_20240703/Types/interfaces/PolicyAmountIVO.xml' V281='13' V1='4' name='marketValueAmountVO'>
      </savedDerivedCopy>
      <savedOrigCopyAtInheritsFrom t='167' id='233' V167='21' V283='2' occurMaxTimes='1' minSize='-1' maxSize='-1' groupType='3' repHandlerStruct='' visible='true' inheritsFrom='' namespaceIndex='1' V281='13' V1='4' name='PolicyAmountIVO'>
      </savedOrigCopyAtInheritsFrom>
    </child>
    <child t='167' id='234' V167='21' inheritsFromIncarnation='8' inheritsFromTimestamp='0x19077fc6836' inheritsInThisStruct='true' V283='2' occurMaxTimes='1' minSize='-1' maxSize='-1' inheritsFromCopyRule='20' groupType='3' repHandlerStruct='' visible='true' inheritsFrom='Structures/CI_QA_all_interfaces_20240703/Types/interfaces/PolicyAmountIVO.xml' V281='13' V1='4' name='lowValueContAmountVO' checksumValid='true' checksum='dxQdJAEQt7cSk4xPs5ydglx7XME='>
      <structNode t='150' idref='1'/>
      <savedDerivedCopy t='167' id='235' V167='21' needInheritInit='true' inheritsInThisStruct='true' V283='2' occurMaxTimes='1' minSize='-1' maxSize='-1' inheritsFromCopyRule='20' dataType='2' repHandlerStruct='' visible='true' inheritsFrom='Structures/CI_QA_all_interfaces_20240703/Types/interfaces/PolicyAmountIVO.xml' V281='13' V1='4' name='lowValueContAmountVO'>
      </savedDerivedCopy>
      <savedOrigCopyAtInheritsFrom t='167' id='236' V167='21' V283='2' occurMaxTimes='1' minSize='-1' maxSize='-1' groupType='3' repHandlerStruct='' visible='true' inheritsFrom='' namespaceIndex='1' V281='13' V1='4' name='PolicyAmountIVO'>
      </savedOrigCopyAtInheritsFrom>
    </child>
    <child t='167' id='237' V167='21' V283='2' occurMaxTimes='1' minSize='-1' maxSize='-1' dataType='30' repHandlerStruct='' visible='true' inheritsFrom='' V281='13' V1='4' name='futureRateDate'>
      <structNode t='150' idref='1'/>
    </child>
    <child t='167' id='238' V167='21' V283='2' occurMaxTimes='1' minSize='-1' maxSize='-1' dataType='2' repHandlerStruct='' visible='true' inheritsFrom='' V281='13' V1='4' name='businessLocationRef' description='dynamic table type and id: class com.idit.reference.server.ejb3.vo.TDynamicReferenceDataVO and dynamic tabled id is:20917'>
      <structNode t='150' idref='1'/>
      <child t='167' id='239' V167='21' V283='2' occurMaxTimes='1' minSize='-1' maxSize='-1' groupType='3' repHandlerStruct='' inheritsFrom='' V281='13' V1='4' name='Attributes'>
        <structNode t='150' idref='1'/>
        <child t='167' id='240' V167='21' V283='2' occurMinTimes='1' occurMaxTimes='1' minSize='-1' maxSize='-1' dataType='13' elemType='1' repHandlerStruct='' visible='true' inheritsFrom='' V281='13' V1='4' name='id'>
          <structNode t='150' idref='1'/>
        </child>
        <child t='167' id='241' V167='21' V283='2' occurMaxTimes='1' minSize='-1' maxSize='-1' dataType='2' elemType='1' repHandlerStruct='' visible='true' inheritsFrom='' V281='13' V1='4' name='extCode'>
          <structNode t='150' idref='1'/>
        </child>
      </child>
    </child>
    <child t='167' id='242' V167='21' V283='2' occurMaxTimes='1' minSize='-1' maxSize='-1' dataType='2' repHandlerStruct='' visible='true' inheritsFrom='' V281='13' V1='4' name='neighbouringOccupancyRef' description='dynamic table type and id: class com.idit.reference.server.ejb3.vo.TDynamicReferenceDataVO and dynamic tabled id is:20914'>
      <structNode t='150' idref='1'/>
      <child t='167' id='243' V167='21' V283='2' occurMaxTimes='1' minSize='-1' maxSize='-1' groupType='3' repHandlerStruct='' inheritsFrom='' V281='13' V1='4' name='Attributes'>
        <structNode t='150' idref='1'/>
        <child t='167' id='244' V167='21' V283='2' occurMinTimes='1' occurMaxTimes='1' minSize='-1' maxSize='-1' dataType='13' elemType='1' repHandlerStruct='' visible='true' inheritsFrom='' V281='13' V1='4' name='id'>
          <structNode t='150' idref='1'/>
        </child>
        <child t='167' id='245' V167='21' V283='2' occurMaxTimes='1' minSize='-1' maxSize='-1' dataType='2' elemType='1' repHandlerStruct='' visible='true' inheritsFrom='' V281='13' V1='4' name='extCode'>
          <structNode t='150' idref='1'/>
        </child>
      </child>
    </child>
    <child t='167' id='246' V167='21' V283='2' occurMaxTimes='1' minSize='-1' maxSize='-1' dataType='2' repHandlerStruct='' visible='true' inheritsFrom='' V281='13' V1='4' name='amountIndexVORef' description='original type: class com.idit.reference.common.vo.TIndexVO'>
      <structNode t='150' idref='1'/>
      <child t='167' id='247' V167='21' V283='2' occurMaxTimes='1' minSize='-1' maxSize='-1' groupType='3' repHandlerStruct='' inheritsFrom='' V281='13' V1='4' name='Attributes'>
        <structNode t='150' idref='1'/>
        <child t='167' id='248' V167='21' V283='2' occurMinTimes='1' occurMaxTimes='1' minSize='-1' maxSize='-1' dataType='13' elemType='1' repHandlerStruct='' visible='true' inheritsFrom='' V281='13' V1='4' name='id'>
          <structNode t='150' idref='1'/>
        </child>
        <child t='167' id='249' V167='21' V283='2' occurMaxTimes='1' minSize='-1' maxSize='-1' dataType='2' elemType='1' repHandlerStruct='' visible='true' inheritsFrom='' V281='13' V1='4' name='extCode'>
          <structNode t='150' idref='1'/>
        </child>
      </child>
    </child>
    <child t='167' id='250' V167='21' V283='2' occurMaxTimes='1' minSize='-1' maxSize='-1' dataType='30' repHandlerStruct='' visible='true' inheritsFrom='' V281='13' V1='4' name='datePrice' description='Date Price'>
      <structNode t='150' idref='1'/>
    </child>
    <child t='167' id='251' V167='21' V283='2' occurMaxTimes='1' minSize='-1' maxSize='-1' dataType='2' repHandlerStruct='' visible='true' inheritsFrom='' V281='13' V1='4' name='storageStandardsFlagVORef' description='Kennzeichnen Sie, ob die Eigenschaft den Speicherstandards entsprichtFlag whether property meets storage standardsFlag whether p...'>
      <structNode t='150' idref='1'/>
      <longDesc>Kennzeichnen Sie, ob die Eigenschaft den Speicherstandards entsprichtFlag whether property meets storage standardsFlag whether property meets storage standardsoriginal type: class com.idit.reference.common.vo.TYesNoVO</longDesc>
      <child t='167' id='252' V167='21' V283='2' occurMaxTimes='1' minSize='-1' maxSize='-1' groupType='3' repHandlerStruct='' inheritsFrom='' V281='13' V1='4' name='Attributes'>
        <structNode t='150' idref='1'/>
        <child t='167' id='253' V167='21' V283='2' occurMinTimes='1' occurMaxTimes='1' minSize='-1' maxSize='-1' dataType='13' elemType='1' repHandlerStruct='' visible='true' inheritsFrom='' V281='13' V1='4' name='id'>
          <structNode t='150' idref='1'/>
        </child>
        <child t='167' id='254' V167='21' V283='2' occurMaxTimes='1' minSize='-1' maxSize='-1' dataType='2' elemType='1' repHandlerStruct='' visible='true' inheritsFrom='' V281='13' V1='4' name='extCode'>
          <structNode t='150' idref='1'/>
        </child>
      </child>
    </child>
    <child t='167' id='255' V167='21' V283='2' occurMaxTimes='1' minSize='-1' maxSize='-1' dataType='2' repHandlerStruct='' visible='true' inheritsFrom='' V281='13' V1='4' name='generalHighValueItemsVORef' description='original type: class com.idit.reference.common.vo.TYesNoVO'>
      <structNode t='150' idref='1'/>
      <child t='167' id='256' V167='21' V283='2' occurMaxTimes='1' minSize='-1' maxSize='-1' groupType='3' repHandlerStruct='' inheritsFrom='' V281='13' V1='4' name='Attributes'>
        <structNode t='150' idref='1'/>
        <child t='167' id='257' V167='21' V283='2' occurMinTimes='1' occurMaxTimes='1' minSize='-1' maxSize='-1' dataType='13' elemType='1' repHandlerStruct='' visible='true' inheritsFrom='' V281='13' V1='4' name='id'>
          <structNode t='150' idref='1'/>
        </child>
        <child t='167' id='258' V167='21' V283='2' occurMaxTimes='1' minSize='-1' maxSize='-1' dataType='2' elemType='1' repHandlerStruct='' visible='true' inheritsFrom='' V281='13' V1='4' name='extCode'>
          <structNode t='150' idref='1'/>
        </child>
      </child>
    </child>
    <child t='167' id='259' V167='21' V283='2' occurMaxTimes='1' minSize='-1' maxSize='-1' groupType='1' repHandlerStruct='' visible='true' inheritsFrom='' V281='13' V1='4' name='insuredCompanyFirePropertiesList'>
      <structNode t='150' idref='1'/>
      <child t='167' id='260' V167='21' inheritsFromIncarnation='9' inheritsFromTimestamp='0x19077fc682b' inheritsInThisStruct='true' V283='2' occurMaxTimes='-1' minSize='-1' maxSize='-1' inheritsFromCopyRule='20' groupType='3' repHandlerStruct='' visible='true' inheritsFrom='Structures/CI_QA_all_interfaces_20240703/Types/interfaces/InsuredCompanyFirePropertiesIVO.xml' V281='13' V1='4' name='insuredCompanyFireProperties' description='Angaben zur Feuerversicherung des UnternehmensCompany fire insurance detailsCompany fire insurance details'>
        <structNode t='150' idref='1'/>
        <savedDerivedCopy t='167' id='261' V167='21' needInheritInit='true' inheritsInThisStruct='true' V283='2' occurMaxTimes='-1' minSize='-1' maxSize='-1' inheritsFromCopyRule='20' dataType='2' repHandlerStruct='' visible='true' inheritsFrom='Structures/CI_QA_all_interfaces_20240703/Types/interfaces/InsuredCompanyFirePropertiesIVO.xml' V281='13' V1='4' name='insuredCompanyFireProperties' description='Angaben zur Feuerversicherung des UnternehmensCompany fire insurance detailsCompany fire insurance details'>
        </savedDerivedCopy>
        <savedOrigCopyAtInheritsFrom t='167' id='262' V167='21' V283='2' occurMaxTimes='1' minSize='-1' maxSize='-1' groupType='3' repHandlerStruct='' visible='true' inheritsFrom='' namespaceIndex='1' V281='13' V1='4' name='InsuredCompanyFirePropertiesIVO'>
        </savedOrigCopyAtInheritsFrom>
      </child>
    </child>
    <child t='167' id='263' V167='21' inheritsFromIncarnation='8' inheritsFromTimestamp='0x19077fc6836' inheritsInThisStruct='true' V283='2' occurMaxTimes='1' minSize='-1' maxSize='-1' inheritsFromCopyRule='20' groupType='3' repHandlerStruct='' visible='true' inheritsFrom='Structures/CI_QA_all_interfaces_20240703/Types/interfaces/PolicyAmountIVO.xml' V281='13' V1='4' name='rebuildingAmountVO' checksumValid='true' checksum='CmjJMs5A9Pevlf56bxn2/xriLmI='>
      <structNode t='150' idref='1'/>
      <savedDerivedCopy t='167' id='264' V167='21' needInheritInit='true' inheritsInThisStruct='true' V283='2' occurMaxTimes='1' minSize='-1' maxSize='-1' inheritsFromCopyRule='20' dataType='2' repHandlerStruct='' visible='true' inheritsFrom='Structures/CI_QA_all_interfaces_20240703/Types/interfaces/PolicyAmountIVO.xml' V281='13' V1='4' name='rebuildingAmountVO'>
      </savedDerivedCopy>
      <savedOrigCopyAtInheritsFrom t='167' id='265' V167='21' V283='2' occurMaxTimes='1' minSize='-1' maxSize='-1' groupType='3' repHandlerStruct='' visible='true' inheritsFrom='' namespaceIndex='1' V281='13' V1='4' name='PolicyAmountIVO'>
      </savedOrigCopyAtInheritsFrom>
    </child>
    <child t='167' id='266' V167='21' V283='2' occurMaxTimes='1' minSize='-1' maxSize='-1' dataType='2' repHandlerStruct='' visible='true' inheritsFrom='' V281='13' V1='4' name='occupancySMERef' description='dynamic table type and id: class com.idit.reference.server.ejb3.vo.TDynamicReferenceDataVO and dynamic tabled id is:20910'>
      <structNode t='150' idref='1'/>
      <child t='167' id='267' V167='21' V283='2' occurMaxTimes='1' minSize='-1' maxSize='-1' groupType='3' repHandlerStruct='' inheritsFrom='' V281='13' V1='4' name='Attributes'>
        <structNode t='150' idref='1'/>
        <child t='167' id='268' V167='21' V283='2' occurMinTimes='1' occurMaxTimes='1' minSize='-1' maxSize='-1' dataType='13' elemType='1' repHandlerStruct='' visible='true' inheritsFrom='' V281='13' V1='4' name='id'>
          <structNode t='150' idref='1'/>
        </child>
        <child t='167' id='269' V167='21' V283='2' occurMaxTimes='1' minSize='-1' maxSize='-1' dataType='2' elemType='1' repHandlerStruct='' visible='true' inheritsFrom='' V281='13' V1='4' name='extCode'>
          <structNode t='150' idref='1'/>
        </child>
      </child>
    </child>
    <child t='167' id='270' V167='21' V283='2' occurMaxTimes='1' minSize='-1' maxSize='-1' dataType='2' repHandlerStruct='' visible='true' inheritsFrom='' V281='13' V1='4' name='remarks' description='BemerkungenRemarksRemarks'>
      <structNode t='150' idref='1'/>
    </child>
    <child t='167' id='271' V167='21' V283='2' occurMaxTimes='1' minSize='-1' maxSize='-1' dataType='2' repHandlerStruct='' visible='true' inheritsFrom='' V281='13' V1='4' name='woodPlasticStandardsFlagVORef' description='Kennzeichnen Sie, ob die Immobilie den Standards für Holzkunststoffe entsprichtFlag whether property meets wood plastic material...'>
      <structNode t='150' idref='1'/>
      <longDesc>Kennzeichnen Sie, ob die Immobilie den Standards für Holzkunststoffe entsprichtFlag whether property meets wood plastic materials standardsFlag whether property meets wood plastic materials standardsoriginal type: class com.idit.reference.common.vo.TYesNoVO</longDesc>
      <child t='167' id='272' V167='21' V283='2' occurMaxTimes='1' minSize='-1' maxSize='-1' groupType='3' repHandlerStruct='' inheritsFrom='' V281='13' V1='4' name='Attributes'>
        <structNode t='150' idref='1'/>
        <child t='167' id='273' V167='21' V283='2' occurMinTimes='1' occurMaxTimes='1' minSize='-1' maxSize='-1' dataType='13' elemType='1' repHandlerStruct='' visible='true' inheritsFrom='' V281='13' V1='4' name='id'>
          <structNode t='150' idref='1'/>
        </child>
        <child t='167' id='274' V167='21' V283='2' occurMaxTimes='1' minSize='-1' maxSize='-1' dataType='2' elemType='1' repHandlerStruct='' visible='true' inheritsFrom='' V281='13' V1='4' name='extCode'>
          <structNode t='150' idref='1'/>
        </child>
      </child>
    </child>
  </rootElem>
  <defaultRep t='172' id='275' V172='6' autoFixNamespaceMismatch='true' V170='10' V692='1' V690='1' ignoreExcluded='true' fixInvalidCharacters='true' V1='4' name='XML'>
    <namespaceContainers t='220' ref='Namespace Containers/CI_QA_all_interfaces_20240703.xml'/>
  </defaultRep>
  <namespaceList t='161' id='276' V161='1' namespaceUri='___osdtDummy___' V1='4'>
  </namespaceList>
  <namespaceList t='161' id='277' V161='1' namespaceUri='http://www.idit.co.il/schemas/all/interfaces' namespacePrefix='interfaces' V1='4'>
  </namespaceList>
  <child t='162' id='278' V1='4' name='Representations'>
    <child t='172' idref='275'/>
  </child>
  <child t='165' id='279' V1='4' name='Document Bindings'>
    <child t='166' id='280' V166='5' docType='1' V1='4' name='/interfaces:PropertyIVO'>
      <elemNode t='167' idref='2'/>
    </child>
  </child>
</root>
