<?xml version="1.0" encoding="UTF-8"?>
<root t='150' id='1' V150='13' creationTimestamp='0x19077fc6874' V1='4' name='TProductIVO' incarnation='26'>
  <rootElem t='167' id='2' V167='21' V283='2' occurMaxTimes='1' minSize='-1' maxSize='-1' groupType='3' repHandlerStruct='' visible='true' inheritsFrom='' namespaceIndex='1' V281='13' V1='4' name='TProductIVO'>
    <structNode t='150' idref='1'/>
    <child t='167' id='3' V167='21' V283='2' occurMaxTimes='1' minSize='-1' maxSize='-1' groupType='3' repHandlerStruct='' inheritsFrom='' V281='13' V1='4' name='Attributes'>
      <structNode t='150' idref='1'/>
      <child t='167' id='4' V167='21' V283='2' occurMaxTimes='1' minSize='-1' maxSize='-1' dataType='13' elemType='1' repHandlerStruct='' visible='true' inheritsFrom='' V281='13' V1='4' name='id'>
        <structNode t='150' idref='1'/>
      </child>
      <child t='167' id='5' V167='21' V283='2' occurMaxTimes='1' minSize='-1' maxSize='-1' dataType='1' elemType='1' repHandlerStruct='' visible='true' inheritsFrom='' V281='13' V1='4' name='main'>
        <structNode t='150' idref='1'/>
      </child>
      <child t='167' id='6' V167='21' V283='2' occurMaxTimes='1' minSize='-1' maxSize='-1' dataType='13' elemType='1' repHandlerStruct='' visible='true' inheritsFrom='' V281='13' V1='4' name='system_id'>
        <structNode t='150' idref='1'/>
      </child>
      <child t='167' id='7' V167='21' V283='2' occurMaxTimes='1' minSize='-1' maxSize='-1' dataType='13' elemType='1' repHandlerStruct='' visible='true' inheritsFrom='' V281='13' V1='4' name='updateVersion'>
        <structNode t='150' idref='1'/>
      </child>
    </child>
    <child t='167' id='8' V167='21' V283='2' occurMaxTimes='1' minSize='-1' maxSize='-1' dataType='2' repHandlerStruct='' visible='true' inheritsFrom='' V281='13' V1='4' name='renewalPeriodVORef' description='original type: class com.idit.reference.common.vo.TRecurrentPeriodVO'>
      <structNode t='150' idref='1'/>
      <child t='167' id='9' V167='21' V283='2' occurMaxTimes='1' minSize='-1' maxSize='-1' groupType='3' repHandlerStruct='' inheritsFrom='' V281='13' V1='4' name='Attributes'>
        <structNode t='150' idref='1'/>
        <child t='167' id='10' V167='21' V283='2' occurMinTimes='1' occurMaxTimes='1' minSize='-1' maxSize='-1' dataType='13' elemType='1' repHandlerStruct='' visible='true' inheritsFrom='' V281='13' V1='4' name='id'>
          <structNode t='150' idref='1'/>
        </child>
        <child t='167' id='11' V167='21' V283='2' occurMaxTimes='1' minSize='-1' maxSize='-1' dataType='2' elemType='1' repHandlerStruct='' visible='true' inheritsFrom='' V281='13' V1='4' name='extCode'>
          <structNode t='150' idref='1'/>
        </child>
      </child>
    </child>
    <child t='167' id='12' V167='21' V283='2' occurMaxTimes='1' minSize='-1' maxSize='-1' dataType='13' repHandlerStruct='' visible='true' inheritsFrom='' V281='13' V1='4' name='surrenderWaitingYears'>
      <structNode t='150' idref='1'/>
    </child>
    <child t='167' id='13' V167='21' V283='2' occurMaxTimes='1' minSize='-1' maxSize='-1' dataType='13' repHandlerStruct='' visible='true' inheritsFrom='' V281='13' V1='4' name='prolongationWaitingYears'>
      <structNode t='150' idref='1'/>
    </child>
    <child t='167' id='14' V167='21' inheritsFromIncarnation='8' inheritsFromTimestamp='0x19077fc6883' inheritsInThisStruct='true' V283='2' occurMaxTimes='1' minSize='-1' maxSize='-1' inheritsFromCopyRule='20' groupType='3' repHandlerStruct='' visible='true' inheritsFrom='Structures/CI_QA_all_interfaces_20240703/Types/interfaces/ValueIVO.xml' V281='13' V1='4' name='medicalExaminationRequiredRuleIVO'>
      <structNode t='150' idref='1'/>
      <savedDerivedCopy t='167' id='15' V167='21' needInheritInit='true' inheritsInThisStruct='true' V283='2' occurMaxTimes='1' minSize='-1' maxSize='-1' inheritsFromCopyRule='20' dataType='2' repHandlerStruct='' visible='true' inheritsFrom='Structures/CI_QA_all_interfaces_20240703/Types/interfaces/ValueIVO.xml' V281='13' V1='4' name='medicalExaminationRequiredRuleIVO'>
      </savedDerivedCopy>
      <savedOrigCopyAtInheritsFrom t='167' id='16' V167='21' V283='2' occurMaxTimes='1' minSize='-1' maxSize='-1' groupType='3' repHandlerStruct='' visible='true' inheritsFrom='' namespaceIndex='1' V281='13' V1='4' name='ValueIVO'>
      </savedOrigCopyAtInheritsFrom>
    </child>
    <child t='167' id='17' V167='21' V283='2' occurMaxTimes='1' minSize='-1' maxSize='-1' dataType='2' repHandlerStruct='' visible='true' inheritsFrom='' V281='13' V1='4' name='section'>
      <structNode t='150' idref='1'/>
    </child>
    <child t='167' id='18' V167='21' V283='2' occurMaxTimes='1' minSize='-1' maxSize='-1' dataType='13' repHandlerStruct='' visible='true' inheritsFrom='' V281='13' V1='4' name='maxContractsForEmployeeDiscount'>
      <structNode t='150' idref='1'/>
    </child>
    <child t='167' id='19' V167='21' V283='2' occurMaxTimes='1' minSize='-1' maxSize='-1' groupType='1' repHandlerStruct='' visible='true' inheritsFrom='' V281='13' V1='4' name='salesChannelChangesVOsList'>
      <structNode t='150' idref='1'/>
      <child t='167' id='20' V167='21' inheritsFromIncarnation='8' inheritsFromTimestamp='0x19077fc6880' inheritsInThisStruct='true' V283='2' occurMaxTimes='-1' minSize='-1' maxSize='-1' inheritsFromCopyRule='20' groupType='3' repHandlerStruct='' visible='true' inheritsFrom='Structures/CI_QA_all_interfaces_20240703/Types/interfaces/TSalesChannelChangesIVO.xml' V281='13' V1='4' name='salesChannelChangesVOs'>
        <structNode t='150' idref='1'/>
        <savedDerivedCopy t='167' id='21' V167='21' needInheritInit='true' inheritsInThisStruct='true' V283='2' occurMaxTimes='-1' minSize='-1' maxSize='-1' inheritsFromCopyRule='20' dataType='2' repHandlerStruct='' visible='true' inheritsFrom='Structures/CI_QA_all_interfaces_20240703/Types/interfaces/TSalesChannelChangesIVO.xml' V281='13' V1='4' name='salesChannelChangesVOs'>
        </savedDerivedCopy>
        <savedOrigCopyAtInheritsFrom t='167' id='22' V167='21' V283='2' occurMaxTimes='1' minSize='-1' maxSize='-1' groupType='3' repHandlerStruct='' visible='true' inheritsFrom='' namespaceIndex='1' V281='13' V1='4' name='TSalesChannelChangesIVO'>
        </savedOrigCopyAtInheritsFrom>
      </child>
    </child>
    <child t='167' id='23' V167='21' inheritsFromIncarnation='8' inheritsFromTimestamp='0x19077fc6873' inheritsInThisStruct='true' V283='2' occurMaxTimes='1' minSize='-1' maxSize='-1' inheritsFromCopyRule='20' groupType='3' repHandlerStruct='' visible='true' inheritsFrom='Structures/CI_QA_all_interfaces_20240703/Types/interfaces/TProductAttnIVO.xml' V281='13' V1='4' name='productAttnIVO'>
      <structNode t='150' idref='1'/>
      <savedDerivedCopy t='167' id='24' V167='21' needInheritInit='true' inheritsInThisStruct='true' V283='2' occurMaxTimes='1' minSize='-1' maxSize='-1' inheritsFromCopyRule='20' dataType='2' repHandlerStruct='' visible='true' inheritsFrom='Structures/CI_QA_all_interfaces_20240703/Types/interfaces/TProductAttnIVO.xml' V281='13' V1='4' name='productAttnIVO'>
      </savedDerivedCopy>
      <savedOrigCopyAtInheritsFrom t='167' id='25' V167='21' V283='2' occurMaxTimes='1' minSize='-1' maxSize='-1' groupType='3' repHandlerStruct='' visible='true' inheritsFrom='' namespaceIndex='1' V281='13' V1='4' name='TProductAttnIVO'>
      </savedOrigCopyAtInheritsFrom>
    </child>
    <child t='167' id='26' V167='21' V283='2' occurMaxTimes='1' minSize='-1' maxSize='-1' dataType='1' repHandlerStruct='' visible='true' inheritsFrom='' V281='13' V1='4' name='forCollective'>
      <structNode t='150' idref='1'/>
    </child>
    <child t='167' id='27' V167='21' V283='2' occurMaxTimes='1' minSize='-1' maxSize='-1' dataType='1' repHandlerStruct='' visible='true' inheritsFrom='' V281='13' V1='4' name='allowChangePolicyEndDateFlag'>
      <structNode t='150' idref='1'/>
    </child>
    <child t='167' id='28' V167='21' V283='2' occurMaxTimes='1' minSize='-1' maxSize='-1' dataType='1' repHandlerStruct='' visible='true' inheritsFrom='' V281='13' V1='4' name='isCustomerAgreementForExtraPremiumIndex'>
      <structNode t='150' idref='1'/>
    </child>
    <child t='167' id='29' V167='21' V283='2' occurMaxTimes='1' minSize='-1' maxSize='-1' groupType='1' repHandlerStruct='' visible='true' inheritsFrom='' V281='13' V1='4' name='productDriverTypeIVOsList'>
      <structNode t='150' idref='1'/>
      <child t='167' id='30' V167='21' inheritsFromIncarnation='8' inheritsFromTimestamp='0x19077fc6874' inheritsInThisStruct='true' V283='2' occurMaxTimes='-1' minSize='-1' maxSize='-1' inheritsFromCopyRule='20' groupType='3' repHandlerStruct='' visible='true' inheritsFrom='Structures/CI_QA_all_interfaces_20240703/Types/interfaces/TProductDriverTypeIVO.xml' V281='13' V1='4' name='productDriverTypeIVOs'>
        <structNode t='150' idref='1'/>
        <savedDerivedCopy t='167' id='31' V167='21' needInheritInit='true' inheritsInThisStruct='true' V283='2' occurMaxTimes='-1' minSize='-1' maxSize='-1' inheritsFromCopyRule='20' dataType='2' repHandlerStruct='' visible='true' inheritsFrom='Structures/CI_QA_all_interfaces_20240703/Types/interfaces/TProductDriverTypeIVO.xml' V281='13' V1='4' name='productDriverTypeIVOs'>
        </savedDerivedCopy>
        <savedOrigCopyAtInheritsFrom t='167' id='32' V167='21' V283='2' occurMaxTimes='1' minSize='-1' maxSize='-1' groupType='3' repHandlerStruct='' visible='true' inheritsFrom='' namespaceIndex='1' V281='13' V1='4' name='TProductDriverTypeIVO'>
        </savedOrigCopyAtInheritsFrom>
      </child>
    </child>
    <child t='167' id='33' V167='21' V283='2' occurMaxTimes='1' minSize='-1' maxSize='-1' dataType='1' repHandlerStruct='' visible='true' inheritsFrom='' V281='13' V1='4' name='isForPaidUp'>
      <structNode t='150' idref='1'/>
    </child>
    <child t='167' id='34' V167='21' V283='2' occurMaxTimes='1' minSize='-1' maxSize='-1' groupType='1' repHandlerStruct='' visible='true' inheritsFrom='' V281='13' V1='4' name='prodAgrmntLineGroupIVOsList'>
      <structNode t='150' idref='1'/>
      <child t='167' id='35' V167='21' inheritsFromIncarnation='8' inheritsFromTimestamp='0x19077fc6875' inheritsInThisStruct='true' V283='2' occurMaxTimes='-1' minSize='-1' maxSize='-1' inheritsFromCopyRule='20' groupType='3' repHandlerStruct='' visible='true' inheritsFrom='Structures/CI_QA_all_interfaces_20240703/Types/interfaces/TProductLineGroupIVO.xml' V281='13' V1='4' name='prodAgrmntLineGroupIVOs'>
        <structNode t='150' idref='1'/>
        <savedDerivedCopy t='167' id='36' V167='21' needInheritInit='true' inheritsInThisStruct='true' V283='2' occurMaxTimes='-1' minSize='-1' maxSize='-1' inheritsFromCopyRule='20' dataType='2' repHandlerStruct='' visible='true' inheritsFrom='Structures/CI_QA_all_interfaces_20240703/Types/interfaces/TProductLineGroupIVO.xml' V281='13' V1='4' name='prodAgrmntLineGroupIVOs'>
        </savedDerivedCopy>
        <savedOrigCopyAtInheritsFrom t='167' id='37' V167='21' V283='2' occurMaxTimes='1' minSize='-1' maxSize='-1' groupType='3' repHandlerStruct='' visible='true' inheritsFrom='' namespaceIndex='1' V281='13' V1='4' name='TProductLineGroupIVO'>
        </savedOrigCopyAtInheritsFrom>
      </child>
    </child>
    <child t='167' id='38' V167='21' V283='2' occurMaxTimes='1' minSize='-1' maxSize='-1' dataType='1' repHandlerStruct='' visible='true' inheritsFrom='' V281='13' V1='4' name='isUpdatePolicyDatesByFirstCoverDates'>
      <structNode t='150' idref='1'/>
    </child>
    <child t='167' id='39' V167='21' V283='2' occurMaxTimes='1' minSize='-1' maxSize='-1' dataType='2' repHandlerStruct='' visible='true' inheritsFrom='' V281='13' V1='4' name='premiumIndexFreePeriodRef' description='original type: class com.idit.reference.common.vo.TPeriodVO'>
      <structNode t='150' idref='1'/>
      <child t='167' id='40' V167='21' V283='2' occurMaxTimes='1' minSize='-1' maxSize='-1' groupType='3' repHandlerStruct='' inheritsFrom='' V281='13' V1='4' name='Attributes'>
        <structNode t='150' idref='1'/>
        <child t='167' id='41' V167='21' V283='2' occurMinTimes='1' occurMaxTimes='1' minSize='-1' maxSize='-1' dataType='13' elemType='1' repHandlerStruct='' visible='true' inheritsFrom='' V281='13' V1='4' name='id'>
          <structNode t='150' idref='1'/>
        </child>
        <child t='167' id='42' V167='21' V283='2' occurMaxTimes='1' minSize='-1' maxSize='-1' dataType='2' elemType='1' repHandlerStruct='' visible='true' inheritsFrom='' V281='13' V1='4' name='extCode'>
          <structNode t='150' idref='1'/>
        </child>
      </child>
    </child>
    <child t='167' id='43' V167='21' V283='2' occurMaxTimes='1' minSize='-1' maxSize='-1' dataType='1' repHandlerStruct='' visible='true' inheritsFrom='' V281='13' V1='4' name='allowCommissionOverride'>
      <structNode t='150' idref='1'/>
    </child>
    <child t='167' id='44' V167='21' V283='2' occurMaxTimes='1' minSize='-1' maxSize='-1' dataType='1' repHandlerStruct='' visible='true' inheritsFrom='' V281='13' V1='4' name='bulkCommissionCalculation'>
      <structNode t='150' idref='1'/>
    </child>
    <child t='167' id='45' V167='21' V283='2' occurMaxTimes='1' minSize='-1' maxSize='-1' dataType='2' repHandlerStruct='' visible='true' inheritsFrom='' V281='13' V1='4' name='earningWeightCoeffVORef' description='original type: class com.idit.reference.common.vo.TProductCoefficientTypeVO'>
      <structNode t='150' idref='1'/>
      <child t='167' id='46' V167='21' V283='2' occurMaxTimes='1' minSize='-1' maxSize='-1' groupType='3' repHandlerStruct='' inheritsFrom='' V281='13' V1='4' name='Attributes'>
        <structNode t='150' idref='1'/>
        <child t='167' id='47' V167='21' V283='2' occurMinTimes='1' occurMaxTimes='1' minSize='-1' maxSize='-1' dataType='13' elemType='1' repHandlerStruct='' visible='true' inheritsFrom='' V281='13' V1='4' name='id'>
          <structNode t='150' idref='1'/>
        </child>
        <child t='167' id='48' V167='21' V283='2' occurMaxTimes='1' minSize='-1' maxSize='-1' dataType='2' elemType='1' repHandlerStruct='' visible='true' inheritsFrom='' V281='13' V1='4' name='extCode'>
          <structNode t='150' idref='1'/>
        </child>
      </child>
    </child>
    <child t='167' id='49' V167='21' V283='2' occurMaxTimes='1' minSize='-1' maxSize='-1' dataType='13' repHandlerStruct='' visible='true' inheritsFrom='' V281='13' V1='4' name='collectionDateRenewalDelayPoint'>
      <structNode t='150' idref='1'/>
    </child>
    <child t='167' id='50' V167='21' V283='2' occurMaxTimes='1' minSize='-1' maxSize='-1' dataType='13' repHandlerStruct='' visible='true' inheritsFrom='' V281='13' V1='4' name='contactLabel'>
      <structNode t='150' idref='1'/>
    </child>
    <child t='167' id='51' V167='21' V283='2' occurMaxTimes='1' minSize='-1' maxSize='-1' groupType='1' repHandlerStruct='' visible='true' inheritsFrom='' V281='13' V1='4' name='productDiscountTypeIVOsList'>
      <structNode t='150' idref='1'/>
      <child t='167' id='52' V167='21' inheritsFromIncarnation='12' inheritsFromTimestamp='0x19077fc6874' inheritsInThisStruct='true' V283='2' occurMaxTimes='-1' minSize='-1' maxSize='-1' inheritsFromCopyRule='20' groupType='3' repHandlerStruct='' visible='true' inheritsFrom='Structures/CI_QA_all_interfaces_20240703/Types/interfaces/TProductDiscountTypeIVO.xml' V281='13' V1='4' name='productDiscountTypeIVOs' checksumValid='true' checksum='6eblyFVPH8iPwYSR1g17UpWOJcQ='>
        <structNode t='150' idref='1'/>
        <savedDerivedCopy t='167' id='53' V167='21' needInheritInit='true' inheritsInThisStruct='true' V283='2' occurMaxTimes='-1' minSize='-1' maxSize='-1' inheritsFromCopyRule='20' dataType='2' repHandlerStruct='' visible='true' inheritsFrom='Structures/CI_QA_all_interfaces_20240703/Types/interfaces/TProductDiscountTypeIVO.xml' V281='13' V1='4' name='productDiscountTypeIVOs'>
        </savedDerivedCopy>
        <savedOrigCopyAtInheritsFrom t='167' id='54' V167='21' V283='2' occurMaxTimes='1' minSize='-1' maxSize='-1' groupType='3' repHandlerStruct='' visible='true' inheritsFrom='' namespaceIndex='1' V281='13' V1='4' name='TProductDiscountTypeIVO'>
        </savedOrigCopyAtInheritsFrom>
      </child>
    </child>
    <child t='167' id='55' V167='21' V283='2' occurMaxTimes='1' minSize='-1' maxSize='-1' groupType='1' repHandlerStruct='' visible='true' inheritsFrom='' V281='13' V1='4' name='productAffinityIVOsList'>
      <structNode t='150' idref='1'/>
      <child t='167' id='56' V167='21' inheritsFromIncarnation='8' inheritsFromTimestamp='0x19077fc6873' inheritsInThisStruct='true' V283='2' occurMaxTimes='-1' minSize='-1' maxSize='-1' inheritsFromCopyRule='20' groupType='3' repHandlerStruct='' visible='true' inheritsFrom='Structures/CI_QA_all_interfaces_20240703/Types/interfaces/TProductAffinityIVO.xml' V281='13' V1='4' name='productAffinityIVOs'>
        <structNode t='150' idref='1'/>
        <savedDerivedCopy t='167' id='57' V167='21' needInheritInit='true' inheritsInThisStruct='true' V283='2' occurMaxTimes='-1' minSize='-1' maxSize='-1' inheritsFromCopyRule='20' dataType='2' repHandlerStruct='' visible='true' inheritsFrom='Structures/CI_QA_all_interfaces_20240703/Types/interfaces/TProductAffinityIVO.xml' V281='13' V1='4' name='productAffinityIVOs'>
        </savedDerivedCopy>
        <savedOrigCopyAtInheritsFrom t='167' id='58' V167='21' V283='2' occurMaxTimes='1' minSize='-1' maxSize='-1' groupType='3' repHandlerStruct='' visible='true' inheritsFrom='' namespaceIndex='1' V281='13' V1='4' name='TProductAffinityIVO'>
        </savedOrigCopyAtInheritsFrom>
      </child>
    </child>
    <child t='167' id='59' V167='21' V283='2' occurMaxTimes='1' minSize='-1' maxSize='-1' groupType='1' repHandlerStruct='' visible='true' inheritsFrom='' V281='13' V1='4' name='productInsuranceTypeIVOsList'>
      <structNode t='150' idref='1'/>
      <child t='167' id='60' V167='21' inheritsFromIncarnation='8' inheritsFromTimestamp='0x19077fc6875' inheritsInThisStruct='true' V283='2' occurMaxTimes='-1' minSize='-1' maxSize='-1' inheritsFromCopyRule='20' groupType='3' repHandlerStruct='' visible='true' inheritsFrom='Structures/CI_QA_all_interfaces_20240703/Types/interfaces/TProductInsuranceTypeIVO.xml' V281='13' V1='4' name='productInsuranceTypeIVOs'>
        <structNode t='150' idref='1'/>
        <savedDerivedCopy t='167' id='61' V167='21' needInheritInit='true' inheritsInThisStruct='true' V283='2' occurMaxTimes='-1' minSize='-1' maxSize='-1' inheritsFromCopyRule='20' dataType='2' repHandlerStruct='' visible='true' inheritsFrom='Structures/CI_QA_all_interfaces_20240703/Types/interfaces/TProductInsuranceTypeIVO.xml' V281='13' V1='4' name='productInsuranceTypeIVOs'>
        </savedDerivedCopy>
        <savedOrigCopyAtInheritsFrom t='167' id='62' V167='21' V283='2' occurMaxTimes='1' minSize='-1' maxSize='-1' groupType='3' repHandlerStruct='' visible='true' inheritsFrom='' namespaceIndex='1' V281='13' V1='4' name='TProductInsuranceTypeIVO'>
        </savedOrigCopyAtInheritsFrom>
      </child>
    </child>
    <child t='167' id='63' V167='21' V283='2' occurMaxTimes='1' minSize='-1' maxSize='-1' dataType='2' repHandlerStruct='' visible='true' inheritsFrom='' V281='13' V1='4' name='renewedPolicyStatusCodeRef' description='original type: class com.idit.reference.common.vo.TStatusCodeVO'>
      <structNode t='150' idref='1'/>
      <child t='167' id='64' V167='21' V283='2' occurMaxTimes='1' minSize='-1' maxSize='-1' groupType='3' repHandlerStruct='' inheritsFrom='' V281='13' V1='4' name='Attributes'>
        <structNode t='150' idref='1'/>
        <child t='167' id='65' V167='21' V283='2' occurMinTimes='1' occurMaxTimes='1' minSize='-1' maxSize='-1' dataType='13' elemType='1' repHandlerStruct='' visible='true' inheritsFrom='' V281='13' V1='4' name='id'>
          <structNode t='150' idref='1'/>
        </child>
        <child t='167' id='66' V167='21' V283='2' occurMaxTimes='1' minSize='-1' maxSize='-1' dataType='2' elemType='1' repHandlerStruct='' visible='true' inheritsFrom='' V281='13' V1='4' name='extCode'>
          <structNode t='150' idref='1'/>
        </child>
      </child>
    </child>
    <child t='167' id='67' V167='21' V283='2' occurMaxTimes='1' minSize='-1' maxSize='-1' dataType='2' repHandlerStruct='' visible='true' inheritsFrom='' V281='13' V1='4' name='maximumCommissionValueTypeRef' description='original type: class com.idit.reference.common.tot_manager.vo.TValueTypeVO'>
      <structNode t='150' idref='1'/>
      <child t='167' id='68' V167='21' V283='2' occurMaxTimes='1' minSize='-1' maxSize='-1' groupType='3' repHandlerStruct='' inheritsFrom='' V281='13' V1='4' name='Attributes'>
        <structNode t='150' idref='1'/>
        <child t='167' id='69' V167='21' V283='2' occurMinTimes='1' occurMaxTimes='1' minSize='-1' maxSize='-1' dataType='13' elemType='1' repHandlerStruct='' visible='true' inheritsFrom='' V281='13' V1='4' name='id'>
          <structNode t='150' idref='1'/>
        </child>
        <child t='167' id='70' V167='21' V283='2' occurMaxTimes='1' minSize='-1' maxSize='-1' dataType='2' elemType='1' repHandlerStruct='' visible='true' inheritsFrom='' V281='13' V1='4' name='extCode'>
          <structNode t='150' idref='1'/>
        </child>
      </child>
    </child>
    <child t='167' id='71' V167='21' V283='2' occurMaxTimes='1' minSize='-1' maxSize='-1' groupType='1' repHandlerStruct='' visible='true' inheritsFrom='' V281='13' V1='4' name='productVersionIVOsList'>
      <structNode t='150' idref='1'/>
      <child t='167' id='72' V167='21' inheritsFromIncarnation='16' inheritsFromTimestamp='0x19077fc687c' inheritsInThisStruct='true' V283='2' occurMaxTimes='-1' minSize='-1' maxSize='-1' inheritsFromCopyRule='20' groupType='3' repHandlerStruct='' visible='true' inheritsFrom='Structures/CI_QA_all_interfaces_20240703/Types/interfaces/TProductVersionIVO.xml' V281='13' V1='4' name='productVersionIVOs' checksumValid='true' checksum='Aa3xRkySwYzmzzPzDjA6U6yRW1s='>
        <structNode t='150' idref='1'/>
        <savedDerivedCopy t='167' id='73' V167='21' needInheritInit='true' inheritsInThisStruct='true' V283='2' occurMaxTimes='-1' minSize='-1' maxSize='-1' inheritsFromCopyRule='20' dataType='2' repHandlerStruct='' visible='true' inheritsFrom='Structures/CI_QA_all_interfaces_20240703/Types/interfaces/TProductVersionIVO.xml' V281='13' V1='4' name='productVersionIVOs'>
        </savedDerivedCopy>
        <savedOrigCopyAtInheritsFrom t='167' id='74' V167='21' V283='2' occurMaxTimes='1' minSize='-1' maxSize='-1' groupType='3' repHandlerStruct='' visible='true' inheritsFrom='' namespaceIndex='1' V281='13' V1='4' name='TProductVersionIVO'>
        </savedOrigCopyAtInheritsFrom>
      </child>
    </child>
    <child t='167' id='75' V167='21' V283='2' occurMaxTimes='1' minSize='-1' maxSize='-1' dataType='1' repHandlerStruct='' visible='true' inheritsFrom='' V281='13' V1='4' name='multiplePayersFlag'>
      <structNode t='150' idref='1'/>
    </child>
    <child t='167' id='76' V167='21' V283='2' occurMaxTimes='1' minSize='-1' maxSize='-1' dataType='1' repHandlerStruct='' visible='true' inheritsFrom='' V281='13' V1='4' name='isForSurrendering'>
      <structNode t='150' idref='1'/>
    </child>
    <child t='167' id='77' V167='21' V283='2' occurMaxTimes='1' minSize='-1' maxSize='-1' dataType='1' repHandlerStruct='' visible='true' inheritsFrom='' V281='13' V1='4' name='retainTarifOnRenewal'>
      <structNode t='150' idref='1'/>
    </child>
    <child t='167' id='78' V167='21' V283='2' occurMaxTimes='1' minSize='-1' maxSize='-1' dataType='1' repHandlerStruct='' visible='true' inheritsFrom='' V281='13' V1='4' name='allowPremiumToCollectFlag'>
      <structNode t='150' idref='1'/>
    </child>
    <child t='167' id='79' V167='21' V283='2' occurMaxTimes='1' minSize='-1' maxSize='-1' dataType='2' repHandlerStruct='' visible='true' inheritsFrom='' V281='13' V1='4' name='earnedPremiumTypeVORef' description='dynamic table type and id: class com.idit.reference.server.ejb3.vo.TDynamicReferenceDataVO and dynamic tabled id is:19371'>
      <structNode t='150' idref='1'/>
      <child t='167' id='80' V167='21' V283='2' occurMaxTimes='1' minSize='-1' maxSize='-1' groupType='3' repHandlerStruct='' inheritsFrom='' V281='13' V1='4' name='Attributes'>
        <structNode t='150' idref='1'/>
        <child t='167' id='81' V167='21' V283='2' occurMinTimes='1' occurMaxTimes='1' minSize='-1' maxSize='-1' dataType='13' elemType='1' repHandlerStruct='' visible='true' inheritsFrom='' V281='13' V1='4' name='id'>
          <structNode t='150' idref='1'/>
        </child>
        <child t='167' id='82' V167='21' V283='2' occurMaxTimes='1' minSize='-1' maxSize='-1' dataType='2' elemType='1' repHandlerStruct='' visible='true' inheritsFrom='' V281='13' V1='4' name='extCode'>
          <structNode t='150' idref='1'/>
        </child>
      </child>
    </child>
    <child t='167' id='83' V167='21' V283='2' occurMaxTimes='1' minSize='-1' maxSize='-1' dataType='1' repHandlerStruct='' visible='true' inheritsFrom='' V281='13' V1='4' name='automaticCompensationFlag'>
      <structNode t='150' idref='1'/>
    </child>
    <child t='167' id='84' V167='21' V283='2' occurMaxTimes='1' minSize='-1' maxSize='-1' dataType='2' repHandlerStruct='' visible='true' inheritsFrom='' V281='13' V1='4' name='desc'>
      <structNode t='150' idref='1'/>
    </child>
    <child t='167' id='85' V167='21' V283='2' occurMaxTimes='1' minSize='-1' maxSize='-1' dataType='1' repHandlerStruct='' visible='true' inheritsFrom='' V281='13' V1='4' name='isAdvancedPaymentTerms'>
      <structNode t='150' idref='1'/>
    </child>
    <child t='167' id='86' V167='21' V283='2' occurMaxTimes='1' minSize='-1' maxSize='-1' dataType='2' repHandlerStruct='' visible='true' inheritsFrom='' V281='13' V1='4' name='brandCompanyName'>
      <structNode t='150' idref='1'/>
    </child>
    <child t='167' id='87' V167='21' V283='2' occurMaxTimes='1' minSize='-1' maxSize='-1' dataType='13' repHandlerStruct='' visible='true' inheritsFrom='' V281='13' V1='4' name='quoteSecurityActionId'>
      <structNode t='150' idref='1'/>
    </child>
    <child t='167' id='88' V167='21' V283='2' occurMaxTimes='1' minSize='-1' maxSize='-1' dataType='1' repHandlerStruct='' visible='true' inheritsFrom='' V281='13' V1='4' name='isForRenewalFlag'>
      <structNode t='150' idref='1'/>
    </child>
    <child t='167' id='89' V167='21' V283='2' occurMaxTimes='1' minSize='-1' maxSize='-1' dataType='1' repHandlerStruct='' visible='true' inheritsFrom='' V281='13' V1='4' name='retainTarifOnChangeStartDate'>
      <structNode t='150' idref='1'/>
    </child>
    <child t='167' id='90' V167='21' V283='2' occurMaxTimes='1' minSize='-1' maxSize='-1' dataType='1' repHandlerStruct='' visible='true' inheritsFrom='' V281='13' V1='4' name='allowCombineInvoiceFlag'>
      <structNode t='150' idref='1'/>
    </child>
    <child t='167' id='91' V167='21' V283='2' occurMaxTimes='1' minSize='-1' maxSize='-1' dataType='13' repHandlerStruct='' visible='true' inheritsFrom='' V281='13' V1='4' name='paidUpWaitingYears'>
      <structNode t='150' idref='1'/>
    </child>
    <child t='167' id='92' V167='21' V283='2' occurMaxTimes='1' minSize='-1' maxSize='-1' dataType='1' repHandlerStruct='' visible='true' inheritsFrom='' V281='13' V1='4' name='isEndowmentProduct'>
      <structNode t='150' idref='1'/>
    </child>
    <child t='167' id='93' V167='21' V283='2' occurMaxTimes='1' minSize='-1' maxSize='-1' groupType='1' repHandlerStruct='' visible='true' inheritsFrom='' V281='13' V1='4' name='productFundIVOsList'>
      <structNode t='150' idref='1'/>
      <child t='167' id='94' V167='21' inheritsFromIncarnation='8' inheritsFromTimestamp='0x19077fc6874' inheritsInThisStruct='true' V283='2' occurMaxTimes='-1' minSize='-1' maxSize='-1' inheritsFromCopyRule='20' groupType='3' repHandlerStruct='' visible='true' inheritsFrom='Structures/CI_QA_all_interfaces_20240703/Types/interfaces/TProductFundIVO.xml' V281='13' V1='4' name='productFundIVOs'>
        <structNode t='150' idref='1'/>
        <savedDerivedCopy t='167' id='95' V167='21' needInheritInit='true' inheritsInThisStruct='true' V283='2' occurMaxTimes='-1' minSize='-1' maxSize='-1' inheritsFromCopyRule='20' dataType='2' repHandlerStruct='' visible='true' inheritsFrom='Structures/CI_QA_all_interfaces_20240703/Types/interfaces/TProductFundIVO.xml' V281='13' V1='4' name='productFundIVOs'>
        </savedDerivedCopy>
        <savedOrigCopyAtInheritsFrom t='167' id='96' V167='21' V283='2' occurMaxTimes='1' minSize='-1' maxSize='-1' groupType='3' repHandlerStruct='' visible='true' inheritsFrom='' namespaceIndex='1' V281='13' V1='4' name='TProductFundIVO'>
        </savedOrigCopyAtInheritsFrom>
      </child>
    </child>
    <child t='167' id='97' V167='21' V283='2' occurMaxTimes='1' minSize='-1' maxSize='-1' dataType='2' repHandlerStruct='' visible='true' inheritsFrom='' V281='13' V1='4' name='collectionDateDelayPointVORef' description='original type: class com.idit.reference.common.accounting.vo.TCollectionDateDelayPointVO'>
      <structNode t='150' idref='1'/>
      <child t='167' id='98' V167='21' V283='2' occurMaxTimes='1' minSize='-1' maxSize='-1' groupType='3' repHandlerStruct='' inheritsFrom='' V281='13' V1='4' name='Attributes'>
        <structNode t='150' idref='1'/>
        <child t='167' id='99' V167='21' V283='2' occurMinTimes='1' occurMaxTimes='1' minSize='-1' maxSize='-1' dataType='13' elemType='1' repHandlerStruct='' visible='true' inheritsFrom='' V281='13' V1='4' name='id'>
          <structNode t='150' idref='1'/>
        </child>
        <child t='167' id='100' V167='21' V283='2' occurMaxTimes='1' minSize='-1' maxSize='-1' dataType='2' elemType='1' repHandlerStruct='' visible='true' inheritsFrom='' V281='13' V1='4' name='extCode'>
          <structNode t='150' idref='1'/>
        </child>
      </child>
    </child>
    <child t='167' id='101' V167='21' inheritsFromIncarnation='8' inheritsFromTimestamp='0x19077fc687b' inheritsInThisStruct='true' V283='2' occurMaxTimes='1' minSize='-1' maxSize='-1' inheritsFromCopyRule='20' groupType='3' repHandlerStruct='' visible='true' inheritsFrom='Structures/CI_QA_all_interfaces_20240703/Types/interfaces/TProductQuestionnaireIVO.xml' V281='13' V1='4' name='productQuestionnaireIVO' checksumValid='true' checksum='SJ5rH5cdOp66h4VEIoUm3seqbmE='>
      <structNode t='150' idref='1'/>
      <savedDerivedCopy t='167' id='102' V167='21' needInheritInit='true' inheritsInThisStruct='true' V283='2' occurMaxTimes='1' minSize='-1' maxSize='-1' inheritsFromCopyRule='20' dataType='2' repHandlerStruct='' visible='true' inheritsFrom='Structures/CI_QA_all_interfaces_20240703/Types/interfaces/TProductQuestionnaireIVO.xml' V281='13' V1='4' name='productQuestionnaireIVO'>
      </savedDerivedCopy>
      <savedOrigCopyAtInheritsFrom t='167' id='103' V167='21' V283='2' occurMaxTimes='1' minSize='-1' maxSize='-1' groupType='3' repHandlerStruct='' visible='true' inheritsFrom='' namespaceIndex='1' V281='13' V1='4' name='TProductQuestionnaireIVO'>
      </savedOrigCopyAtInheritsFrom>
    </child>
    <child t='167' id='104' V167='21' V283='2' occurMaxTimes='1' minSize='-1' maxSize='-1' dataType='1' repHandlerStruct='' visible='true' inheritsFrom='' V281='13' V1='4' name='enabled'>
      <structNode t='150' idref='1'/>
    </child>
    <child t='167' id='105' V167='21' V283='2' occurMaxTimes='1' minSize='-1' maxSize='-1' groupType='1' repHandlerStruct='' visible='true' inheritsFrom='' V281='13' V1='4' name='productCurrencyIVOsList'>
      <structNode t='150' idref='1'/>
      <child t='167' id='106' V167='21' inheritsFromIncarnation='8' inheritsFromTimestamp='0x19077fc6874' inheritsInThisStruct='true' V283='2' occurMaxTimes='-1' minSize='-1' maxSize='-1' inheritsFromCopyRule='20' groupType='3' repHandlerStruct='' visible='true' inheritsFrom='Structures/CI_QA_all_interfaces_20240703/Types/interfaces/TProductCurrencyIVO.xml' V281='13' V1='4' name='productCurrencyIVOs'>
        <structNode t='150' idref='1'/>
        <savedDerivedCopy t='167' id='107' V167='21' needInheritInit='true' inheritsInThisStruct='true' V283='2' occurMaxTimes='-1' minSize='-1' maxSize='-1' inheritsFromCopyRule='20' dataType='2' repHandlerStruct='' visible='true' inheritsFrom='Structures/CI_QA_all_interfaces_20240703/Types/interfaces/TProductCurrencyIVO.xml' V281='13' V1='4' name='productCurrencyIVOs'>
        </savedDerivedCopy>
        <savedOrigCopyAtInheritsFrom t='167' id='108' V167='21' V283='2' occurMaxTimes='1' minSize='-1' maxSize='-1' groupType='3' repHandlerStruct='' visible='true' inheritsFrom='' namespaceIndex='1' V281='13' V1='4' name='TProductCurrencyIVO'>
        </savedOrigCopyAtInheritsFrom>
      </child>
    </child>
    <child t='167' id='109' V167='21' V283='2' occurMaxTimes='1' minSize='-1' maxSize='-1' groupType='1' repHandlerStruct='' visible='true' inheritsFrom='' V281='13' V1='4' name='productLodgerTypeIVOsList'>
      <structNode t='150' idref='1'/>
      <child t='167' id='110' V167='21' inheritsFromIncarnation='8' inheritsFromTimestamp='0x19077fc687b' inheritsInThisStruct='true' V283='2' occurMaxTimes='-1' minSize='-1' maxSize='-1' inheritsFromCopyRule='20' groupType='3' repHandlerStruct='' visible='true' inheritsFrom='Structures/CI_QA_all_interfaces_20240703/Types/interfaces/TProductLodgerTypeIVO.xml' V281='13' V1='4' name='productLodgerTypeIVOs'>
        <structNode t='150' idref='1'/>
        <savedDerivedCopy t='167' id='111' V167='21' needInheritInit='true' inheritsInThisStruct='true' V283='2' occurMaxTimes='-1' minSize='-1' maxSize='-1' inheritsFromCopyRule='20' dataType='2' repHandlerStruct='' visible='true' inheritsFrom='Structures/CI_QA_all_interfaces_20240703/Types/interfaces/TProductLodgerTypeIVO.xml' V281='13' V1='4' name='productLodgerTypeIVOs'>
        </savedDerivedCopy>
        <savedOrigCopyAtInheritsFrom t='167' id='112' V167='21' V283='2' occurMaxTimes='1' minSize='-1' maxSize='-1' groupType='3' repHandlerStruct='' visible='true' inheritsFrom='' namespaceIndex='1' V281='13' V1='4' name='TProductLodgerTypeIVO'>
        </savedOrigCopyAtInheritsFrom>
      </child>
    </child>
    <child t='167' id='113' V167='21' V283='2' occurMaxTimes='1' minSize='-1' maxSize='-1' dataType='13' repHandlerStruct='' visible='true' inheritsFrom='' V281='13' V1='4' name='privilegeActionId'>
      <structNode t='150' idref='1'/>
    </child>
    <child t='167' id='114' V167='21' V283='2' occurMaxTimes='1' minSize='-1' maxSize='-1' dataType='1' repHandlerStruct='' visible='true' inheritsFrom='' V281='13' V1='4' name='allowClaimInjuredPersonFlag'>
      <structNode t='150' idref='1'/>
    </child>
    <child t='167' id='115' V167='21' V283='2' occurMaxTimes='1' minSize='-1' maxSize='-1' dataType='21' repHandlerStruct='' visible='true' inheritsFrom='' V281='13' V1='4' name='maximumCommissionValue'>
      <structNode t='150' idref='1'/>
    </child>
    <child t='167' id='116' V167='21' V283='2' occurMaxTimes='1' minSize='-1' maxSize='-1' dataType='2' repHandlerStruct='' visible='true' inheritsFrom='' V281='13' V1='4' name='productCategoryVORef' description='original type: class com.idit.reference.common.vo.TProductCategoryVO'>
      <structNode t='150' idref='1'/>
      <child t='167' id='117' V167='21' V283='2' occurMaxTimes='1' minSize='-1' maxSize='-1' groupType='3' repHandlerStruct='' inheritsFrom='' V281='13' V1='4' name='Attributes'>
        <structNode t='150' idref='1'/>
        <child t='167' id='118' V167='21' V283='2' occurMinTimes='1' occurMaxTimes='1' minSize='-1' maxSize='-1' dataType='13' elemType='1' repHandlerStruct='' visible='true' inheritsFrom='' V281='13' V1='4' name='id'>
          <structNode t='150' idref='1'/>
        </child>
        <child t='167' id='119' V167='21' V283='2' occurMaxTimes='1' minSize='-1' maxSize='-1' dataType='2' elemType='1' repHandlerStruct='' visible='true' inheritsFrom='' V281='13' V1='4' name='extCode'>
          <structNode t='150' idref='1'/>
        </child>
      </child>
    </child>
    <child t='167' id='120' V167='21' V283='2' occurMaxTimes='1' minSize='-1' maxSize='-1' dataType='1' repHandlerStruct='' visible='true' inheritsFrom='' V281='13' V1='4' name='isExtraPremiumIndexApplicable'>
      <structNode t='150' idref='1'/>
    </child>
    <child t='167' id='121' V167='21' V283='2' occurMaxTimes='1' minSize='-1' maxSize='-1' groupType='1' repHandlerStruct='' visible='true' inheritsFrom='' V281='13' V1='4' name='productPromotionIVOsList'>
      <structNode t='150' idref='1'/>
      <child t='167' id='122' V167='21' inheritsFromIncarnation='9' inheritsFromTimestamp='0x19077fc687b' inheritsInThisStruct='true' V283='2' occurMaxTimes='-1' minSize='-1' maxSize='-1' inheritsFromCopyRule='20' groupType='3' repHandlerStruct='' visible='true' inheritsFrom='Structures/CI_QA_all_interfaces_20240703/Types/interfaces/TProductPromotionIVO.xml' V281='13' V1='4' name='productPromotionIVOs' checksumValid='true' checksum='P9eHAw3yS+DJGsWijF+UUCGr8FU='>
        <structNode t='150' idref='1'/>
        <savedDerivedCopy t='167' id='123' V167='21' needInheritInit='true' inheritsInThisStruct='true' V283='2' occurMaxTimes='-1' minSize='-1' maxSize='-1' inheritsFromCopyRule='20' dataType='2' repHandlerStruct='' visible='true' inheritsFrom='Structures/CI_QA_all_interfaces_20240703/Types/interfaces/TProductPromotionIVO.xml' V281='13' V1='4' name='productPromotionIVOs'>
        </savedDerivedCopy>
        <savedOrigCopyAtInheritsFrom t='167' id='124' V167='21' V283='2' occurMaxTimes='1' minSize='-1' maxSize='-1' groupType='3' repHandlerStruct='' visible='true' inheritsFrom='' namespaceIndex='1' V281='13' V1='4' name='TProductPromotionIVO'>
        </savedOrigCopyAtInheritsFrom>
      </child>
    </child>
    <child t='167' id='125' V167='21' V283='2' occurMaxTimes='1' minSize='-1' maxSize='-1' dataType='13' repHandlerStruct='' visible='true' inheritsFrom='' V281='13' V1='4' name='defaultEffectiveDate'>
      <structNode t='150' idref='1'/>
    </child>
    <child t='167' id='126' V167='21' V283='2' occurMaxTimes='1' minSize='-1' maxSize='-1' dataType='2' repHandlerStruct='' visible='true' inheritsFrom='' V281='13' V1='4' name='productTypeVORef' description='original type: class com.idit.reference.common.vo.TProductTypeVO'>
      <structNode t='150' idref='1'/>
      <child t='167' id='127' V167='21' V283='2' occurMaxTimes='1' minSize='-1' maxSize='-1' groupType='3' repHandlerStruct='' inheritsFrom='' V281='13' V1='4' name='Attributes'>
        <structNode t='150' idref='1'/>
        <child t='167' id='128' V167='21' V283='2' occurMinTimes='1' occurMaxTimes='1' minSize='-1' maxSize='-1' dataType='13' elemType='1' repHandlerStruct='' visible='true' inheritsFrom='' V281='13' V1='4' name='id'>
          <structNode t='150' idref='1'/>
        </child>
        <child t='167' id='129' V167='21' V283='2' occurMaxTimes='1' minSize='-1' maxSize='-1' dataType='2' elemType='1' repHandlerStruct='' visible='true' inheritsFrom='' V281='13' V1='4' name='extCode'>
          <structNode t='150' idref='1'/>
        </child>
      </child>
    </child>
    <child t='167' id='130' V167='21' V283='2' occurMaxTimes='1' minSize='-1' maxSize='-1' groupType='1' repHandlerStruct='' visible='true' inheritsFrom='' V281='13' V1='4' name='productPaymentTermsIVOsList'>
      <structNode t='150' idref='1'/>
      <child t='167' id='131' V167='21' inheritsFromIncarnation='9' inheritsFromTimestamp='0x19077fc687b' inheritsInThisStruct='true' V283='2' occurMaxTimes='-1' minSize='-1' maxSize='-1' inheritsFromCopyRule='20' groupType='3' repHandlerStruct='' visible='true' inheritsFrom='Structures/CI_QA_all_interfaces_20240703/Types/interfaces/TProductPaymentTermsIVO.xml' V281='13' V1='4' name='productPaymentTermsIVOs'>
        <structNode t='150' idref='1'/>
        <savedDerivedCopy t='167' id='132' V167='21' needInheritInit='true' inheritsInThisStruct='true' V283='2' occurMaxTimes='-1' minSize='-1' maxSize='-1' inheritsFromCopyRule='20' dataType='2' repHandlerStruct='' visible='true' inheritsFrom='Structures/CI_QA_all_interfaces_20240703/Types/interfaces/TProductPaymentTermsIVO.xml' V281='13' V1='4' name='productPaymentTermsIVOs'>
        </savedDerivedCopy>
        <savedOrigCopyAtInheritsFrom t='167' id='133' V167='21' V283='2' occurMaxTimes='1' minSize='-1' maxSize='-1' groupType='3' repHandlerStruct='' visible='true' inheritsFrom='' namespaceIndex='1' V281='13' V1='4' name='TProductPaymentTermsIVO'>
        </savedOrigCopyAtInheritsFrom>
      </child>
    </child>
    <child t='167' id='134' V167='21' V283='2' occurMaxTimes='1' minSize='-1' maxSize='-1' dataType='1' repHandlerStruct='' visible='true' inheritsFrom='' V281='13' V1='4' name='isForProlongation'>
      <structNode t='150' idref='1'/>
    </child>
    <child t='167' id='135' V167='21' V283='2' occurMaxTimes='1' minSize='-1' maxSize='-1' dataType='13' repHandlerStruct='' visible='true' inheritsFrom='' V281='13' V1='4' name='collectionDateDelayPoint'>
      <structNode t='150' idref='1'/>
    </child>
    <child t='167' id='136' V167='21' V283='2' occurMaxTimes='1' minSize='-1' maxSize='-1' dataType='13' repHandlerStruct='' visible='true' inheritsFrom='' V281='13' V1='4' name='discountCalculationMethod'>
      <structNode t='150' idref='1'/>
    </child>
    <child t='167' id='137' V167='21' V283='2' occurMaxTimes='1' minSize='-1' maxSize='-1' dataType='13' repHandlerStruct='' visible='true' inheritsFrom='' V281='13' V1='4' name='brandCompanyId'>
      <structNode t='150' idref='1'/>
    </child>
    <child t='167' id='138' V167='21' V283='2' occurMaxTimes='1' minSize='-1' maxSize='-1' dataType='1' repHandlerStruct='' visible='true' inheritsFrom='' V281='13' V1='4' name='defaultEffectiveDateFlag'>
      <structNode t='150' idref='1'/>
    </child>
    <child t='167' id='139' V167='21' V283='2' occurMaxTimes='1' minSize='-1' maxSize='-1' dataType='1' repHandlerStruct='' visible='true' inheritsFrom='' V281='13' V1='4' name='nullifyManualPremiumOnRenewalFlag'>
      <structNode t='150' idref='1'/>
    </child>
    <child t='167' id='140' V167='21' V283='2' occurMaxTimes='1' minSize='-1' maxSize='-1' groupType='1' repHandlerStruct='' visible='true' inheritsFrom='' V281='13' V1='4' name='productBuildingTypeIVOsList'>
      <structNode t='150' idref='1'/>
      <child t='167' id='141' V167='21' inheritsFromIncarnation='8' inheritsFromTimestamp='0x19077fc6873' inheritsInThisStruct='true' V283='2' occurMaxTimes='-1' minSize='-1' maxSize='-1' inheritsFromCopyRule='20' groupType='3' repHandlerStruct='' visible='true' inheritsFrom='Structures/CI_QA_all_interfaces_20240703/Types/interfaces/TProductBuildingTypeIVO.xml' V281='13' V1='4' name='productBuildingTypeIVOs'>
        <structNode t='150' idref='1'/>
        <savedDerivedCopy t='167' id='142' V167='21' needInheritInit='true' inheritsInThisStruct='true' V283='2' occurMaxTimes='-1' minSize='-1' maxSize='-1' inheritsFromCopyRule='20' dataType='2' repHandlerStruct='' visible='true' inheritsFrom='Structures/CI_QA_all_interfaces_20240703/Types/interfaces/TProductBuildingTypeIVO.xml' V281='13' V1='4' name='productBuildingTypeIVOs'>
        </savedDerivedCopy>
        <savedOrigCopyAtInheritsFrom t='167' id='143' V167='21' V283='2' occurMaxTimes='1' minSize='-1' maxSize='-1' groupType='3' repHandlerStruct='' visible='true' inheritsFrom='' namespaceIndex='1' V281='13' V1='4' name='TProductBuildingTypeIVO'>
        </savedOrigCopyAtInheritsFrom>
      </child>
    </child>
    <child t='167' id='144' V167='21' V283='2' occurMaxTimes='1' minSize='-1' maxSize='-1' groupType='1' repHandlerStruct='' visible='true' inheritsFrom='' V281='13' V1='4' name='productPeriodIVOsList'>
      <structNode t='150' idref='1'/>
      <child t='167' id='145' V167='21' inheritsFromIncarnation='8' inheritsFromTimestamp='0x19077fc687b' inheritsInThisStruct='true' V283='2' occurMaxTimes='-1' minSize='-1' maxSize='-1' inheritsFromCopyRule='20' groupType='3' repHandlerStruct='' visible='true' inheritsFrom='Structures/CI_QA_all_interfaces_20240703/Types/interfaces/TProductPeriodIVO.xml' V281='13' V1='4' name='productPeriodIVOs'>
        <structNode t='150' idref='1'/>
        <savedDerivedCopy t='167' id='146' V167='21' needInheritInit='true' inheritsInThisStruct='true' V283='2' occurMaxTimes='-1' minSize='-1' maxSize='-1' inheritsFromCopyRule='20' dataType='2' repHandlerStruct='' visible='true' inheritsFrom='Structures/CI_QA_all_interfaces_20240703/Types/interfaces/TProductPeriodIVO.xml' V281='13' V1='4' name='productPeriodIVOs'>
        </savedDerivedCopy>
        <savedOrigCopyAtInheritsFrom t='167' id='147' V167='21' V283='2' occurMaxTimes='1' minSize='-1' maxSize='-1' groupType='3' repHandlerStruct='' visible='true' inheritsFrom='' namespaceIndex='1' V281='13' V1='4' name='TProductPeriodIVO'>
        </savedOrigCopyAtInheritsFrom>
      </child>
    </child>
    <child t='167' id='148' V167='21' V283='2' occurMaxTimes='1' minSize='-1' maxSize='-1' dataType='1' repHandlerStruct='' visible='true' inheritsFrom='' V281='13' V1='4' name='bulkCommRiCalc'>
      <structNode t='150' idref='1'/>
    </child>
    <child t='167' id='149' V167='21' V283='2' occurMaxTimes='1' minSize='-1' maxSize='-1' dataType='13' repHandlerStruct='' visible='true' inheritsFrom='' V281='13' V1='4' name='claimSecurityActionId'>
      <structNode t='150' idref='1'/>
    </child>
    <child t='167' id='150' V167='21' V283='2' occurMaxTimes='1' minSize='-1' maxSize='-1' groupType='1' repHandlerStruct='' visible='true' inheritsFrom='' V281='13' V1='4' name='productVehicleUsageIVOsList'>
      <structNode t='150' idref='1'/>
      <child t='167' id='151' V167='21' inheritsFromIncarnation='8' inheritsFromTimestamp='0x19077fc687c' inheritsInThisStruct='true' V283='2' occurMaxTimes='-1' minSize='-1' maxSize='-1' inheritsFromCopyRule='20' groupType='3' repHandlerStruct='' visible='true' inheritsFrom='Structures/CI_QA_all_interfaces_20240703/Types/interfaces/TProductVehicleUsageIVO.xml' V281='13' V1='4' name='productVehicleUsageIVOs'>
        <structNode t='150' idref='1'/>
        <savedDerivedCopy t='167' id='152' V167='21' needInheritInit='true' inheritsInThisStruct='true' V283='2' occurMaxTimes='-1' minSize='-1' maxSize='-1' inheritsFromCopyRule='20' dataType='2' repHandlerStruct='' visible='true' inheritsFrom='Structures/CI_QA_all_interfaces_20240703/Types/interfaces/TProductVehicleUsageIVO.xml' V281='13' V1='4' name='productVehicleUsageIVOs'>
        </savedDerivedCopy>
        <savedOrigCopyAtInheritsFrom t='167' id='153' V167='21' V283='2' occurMaxTimes='1' minSize='-1' maxSize='-1' groupType='3' repHandlerStruct='' visible='true' inheritsFrom='' namespaceIndex='1' V281='13' V1='4' name='TProductVehicleUsageIVO'>
        </savedOrigCopyAtInheritsFrom>
      </child>
    </child>
    <child t='167' id='154' V167='21' V283='2' occurMaxTimes='1' minSize='-1' maxSize='-1' dataType='13' repHandlerStruct='' visible='true' inheritsFrom='' V281='13' V1='4' name='policySecurityActionId'>
      <structNode t='150' idref='1'/>
    </child>
    <child t='167' id='155' V167='21' V283='2' occurMaxTimes='1' minSize='-1' maxSize='-1' dataType='1' repHandlerStruct='' visible='true' inheritsFrom='' V281='13' V1='4' name='applyNewVersionForNewCoverFlag'>
      <structNode t='150' idref='1'/>
    </child>
  </rootElem>
  <defaultRep t='172' id='156' V172='6' autoFixNamespaceMismatch='true' V170='10' V692='1' V690='1' ignoreExcluded='true' fixInvalidCharacters='true' V1='4' name='XML'>
    <namespaceContainers t='220' ref='Namespace Containers/CI_QA_all_interfaces_20240703.xml'/>
  </defaultRep>
  <namespaceList t='161' id='157' V161='1' namespaceUri='___osdtDummy___' V1='4'>
  </namespaceList>
  <namespaceList t='161' id='158' V161='1' namespaceUri='http://www.idit.co.il/schemas/all/interfaces' namespacePrefix='interfaces' V1='4'>
  </namespaceList>
  <child t='162' id='159' V1='4' name='Representations'>
    <child t='172' idref='156'/>
  </child>
  <child t='165' id='160' V1='4' name='Document Bindings'>
    <child t='166' id='161' V166='5' docType='1' V1='4' name='/interfaces:TProductIVO'>
      <elemNode t='167' idref='2'/>
    </child>
  </child>
</root>
