<?xml version="1.0" encoding="UTF-8"?>
<root t='150' id='1' V150='13' creationTimestamp='0x190c0a23208' V1='4' name='policyHeaderRecord' incarnation='1150'>
  <rootElem t='167' id='1039' V167='21' V283='2' occurMaxTimes='1' minSize='-1' maxSize='-1' groupType='1' repHandlerStruct='' visible='true' inheritsFrom='' V281='13' V1='4' name='row'>
    <structNode t='150' idref='1'/>
    <child t='167' id='1040' V167='21' V283='2' occurMaxTimes='1' minSize='-1' maxSize='-1' dataType='13' repHandlerStruct='' visible='true' inheritsFrom='' V281='13' V1='4' name='POLICY'>
      <structNode t='150' idref='1'/>
    </child>
    <child t='167' id='1041' V167='21' V283='2' occurMaxTimes='1' minSize='-1' maxSize='-1' dataType='12' repHandlerStruct='' visible='true' inheritsFrom='' V281='13' V1='4' name='VERTRAG'>
      <structNode t='150' idref='1'/>
    </child>
    <child t='167' id='1042' V167='21' V283='2' occurMaxTimes='1' minSize='-1' maxSize='-1' dataType='13' repHandlerStruct='' visible='true' inheritsFrom='' V281='13' V1='4' name='activePolicyId'>
      <structNode t='150' idref='1'/>
    </child>
    <child t='167' id='1043' V167='21' V283='2' occurMaxTimes='1' minSize='-1' maxSize='-1' dataType='1' repHandlerStruct='' visible='true' inheritsFrom='' V281='13' V1='4' name='consolidatedBillingFlag'>
      <structNode t='150' idref='1'/>
    </child>
    <child t='167' id='1044' V167='21' V283='2' occurMaxTimes='1' minSize='-1' maxSize='-1' dataType='1' repHandlerStruct='' visible='true' inheritsFrom='' V281='13' V1='4' name='bundlePolicy'>
      <structNode t='150' idref='1'/>
    </child>
    <child t='167' id='1045' V167='21' V283='2' occurMaxTimes='1' minSize='-1' maxSize='-1' dataType='13' repHandlerStruct='' visible='true' inheritsFrom='' V281='13' V1='4' name='bundlePolicyHeaderId'>
      <structNode t='150' idref='1'/>
    </child>
    <child t='167' id='1046' V167='21' V283='2' occurMaxTimes='1' minSize='-1' maxSize='-1' dataType='13' repHandlerStruct='' visible='true' inheritsFrom='' V281='13' V1='4' name='cropGroupRefID'>
      <structNode t='150' idref='1'/>
    </child>
    <child t='167' id='1047' V167='21' V283='2' occurMaxTimes='1' minSize='-1' maxSize='-1' dataType='2' repHandlerStruct='' visible='true' inheritsFrom='' V281='13' V1='4' name='cropGroupRefDesc'>
      <structNode t='150' idref='1'/>
    </child>
    <child t='167' id='1048' V167='21' V283='2' occurMaxTimes='1' minSize='-1' maxSize='-1' dataType='13' repHandlerStruct='' visible='true' inheritsFrom='' V281='13' V1='4' name='currencyVORefID'>
      <structNode t='150' idref='1'/>
    </child>
    <child t='167' id='1049' V167='21' V283='2' occurMaxTimes='1' minSize='-1' maxSize='-1' dataType='2' repHandlerStruct='' visible='true' inheritsFrom='' V281='13' V1='4' name='currencyVORefDesc'>
      <structNode t='150' idref='1'/>
    </child>
    <child t='167' id='1050' V167='21' V283='2' occurMaxTimes='1' minSize='-1' maxSize='-1' dataType='2' repHandlerStruct='' visible='true' inheritsFrom='' V281='13' V1='4' name='externalHeaderNumber'>
      <structNode t='150' idref='1'/>
    </child>
    <child t='167' id='1051' V167='21' V283='2' occurMaxTimes='1' minSize='-1' maxSize='-1' dataType='1' repHandlerStruct='' visible='true' inheritsFrom='' V281='13' V1='4' name='isHealthUmbrellaPolicy'>
      <structNode t='150' idref='1'/>
    </child>
    <child t='167' id='1052' V167='21' V283='2' occurMaxTimes='1' minSize='-1' maxSize='-1' dataType='1' repHandlerStruct='' visible='true' inheritsFrom='' V281='13' V1='4' name='isMasterPolicy'>
      <structNode t='150' idref='1'/>
    </child>
    <child t='167' id='1053' V167='21' V283='2' occurMaxTimes='1' minSize='-1' maxSize='-1' dataType='30' repHandlerStruct='' visible='true' inheritsFrom='' V281='13' V1='4' name='mainRenewalDate'>
      <structNode t='150' idref='1'/>
    </child>
    <child t='167' id='1054' V167='21' V283='2' occurMaxTimes='1' minSize='-1' maxSize='-1' dataType='1' repHandlerStruct='' visible='true' inheritsFrom='' V281='13' V1='4' name='multiplePayersFlag'>
      <structNode t='150' idref='1'/>
    </child>
    <child t='167' id='1055' V167='21' V283='2' occurMaxTimes='1' minSize='-1' maxSize='-1' dataType='1' repHandlerStruct='' visible='true' inheritsFrom='' V281='13' V1='4' name='paidByAgentFlag'>
      <structNode t='150' idref='1'/>
    </child>
    <child t='167' id='1056' V167='21' V283='2' occurMaxTimes='1' minSize='-1' maxSize='-1' dataType='30' repHandlerStruct='' visible='true' inheritsFrom='' V281='13' V1='4' name='policyEndDate'>
      <structNode t='150' idref='1'/>
    </child>
    <child t='167' id='1057' V167='21' V283='2' occurMaxTimes='1' minSize='-1' maxSize='-1' dataType='30' repHandlerStruct='' visible='true' inheritsFrom='' V281='13' V1='4' name='policyProposalDate'>
      <structNode t='150' idref='1'/>
    </child>
    <child t='167' id='1058' V167='21' V283='2' occurMaxTimes='1' minSize='-1' maxSize='-1' dataType='30' repHandlerStruct='' visible='true' inheritsFrom='' V281='13' V1='4' name='policyStartDate'>
      <structNode t='150' idref='1'/>
    </child>
    <child t='167' id='1059' V167='21' V283='2' occurMaxTimes='1' minSize='-1' maxSize='-1' dataType='13' repHandlerStruct='' visible='true' inheritsFrom='' V281='13' V1='4' name='processingStatusVORefID'>
      <structNode t='150' idref='1'/>
    </child>
    <child t='167' id='1060' V167='21' V283='2' occurMaxTimes='1' minSize='-1' maxSize='-1' dataType='2' repHandlerStruct='' visible='true' inheritsFrom='' V281='13' V1='4' name='processingStatusVORefDesc'>
      <structNode t='150' idref='1'/>
    </child>
    <child t='167' id='1061' V167='21' V283='2' occurMaxTimes='1' minSize='-1' maxSize='-1' dataType='13' repHandlerStruct='' visible='true' inheritsFrom='' V281='13' V1='4' name='productVersionVORefID'>
      <structNode t='150' idref='1'/>
    </child>
    <child t='167' id='1062' V167='21' V283='2' occurMaxTimes='1' minSize='-1' maxSize='-1' dataType='2' repHandlerStruct='' visible='true' inheritsFrom='' V281='13' V1='4' name='productVersionVORefDesc'>
      <structNode t='150' idref='1'/>
    </child>
    <child t='167' id='1063' V167='21' V283='2' occurMaxTimes='1' minSize='-1' maxSize='-1' dataType='13' repHandlerStruct='' visible='true' inheritsFrom='' V281='13' V1='4' name='productVORefID'>
      <structNode t='150' idref='1'/>
    </child>
    <child t='167' id='1064' V167='21' V283='2' occurMaxTimes='1' minSize='-1' maxSize='-1' dataType='2' repHandlerStruct='' visible='true' inheritsFrom='' V281='13' V1='4' name='productVORefDesc'>
      <structNode t='150' idref='1'/>
    </child>
    <child t='167' id='1065' V167='21' V283='2' occurMaxTimes='1' minSize='-1' maxSize='-1' dataType='13' repHandlerStruct='' visible='true' inheritsFrom='' V281='13' V1='4' name='sales1'>
      <structNode t='150' idref='1'/>
    </child>
    <child t='167' id='1066' V167='21' V283='2' occurMaxTimes='1' minSize='-1' maxSize='-1' dataType='30' repHandlerStruct='' visible='true' inheritsFrom='' V281='13' V1='4' name='sales1Date'>
      <structNode t='150' idref='1'/>
    </child>
    <child t='167' id='1067' V167='21' V283='2' occurMaxTimes='1' minSize='-1' maxSize='-1' dataType='13' repHandlerStruct='' visible='true' inheritsFrom='' V281='13' V1='4' name='statusCodeVORefID'>
      <structNode t='150' idref='1'/>
    </child>
    <child t='167' id='1068' V167='21' V283='2' occurMaxTimes='1' minSize='-1' maxSize='-1' dataType='2' repHandlerStruct='' visible='true' inheritsFrom='' V281='13' V1='4' name='statusCodeVORefDesc'>
      <structNode t='150' idref='1'/>
    </child>
    <child t='167' id='1069' V167='21' V283='2' occurMaxTimes='1' minSize='-1' maxSize='-1' dataType='30' repHandlerStruct='' visible='true' inheritsFrom='' V281='13' V1='4' name='statusCollDate'>
      <structNode t='150' idref='1'/>
    </child>
    <child t='167' id='1070' V167='21' V283='2' occurMaxTimes='1' minSize='-1' maxSize='-1' dataType='30' repHandlerStruct='' visible='true' inheritsFrom='' V281='13' V1='4' name='statusDate'>
      <structNode t='150' idref='1'/>
    </child>
    <child t='167' id='1071' V167='21' V283='2' occurMaxTimes='1' minSize='-1' maxSize='-1' dataType='1' repHandlerStruct='' visible='true' inheritsFrom='' V281='13' V1='4' name='trackCoverBalancePerEndors'>
      <structNode t='150' idref='1'/>
    </child>
    <child t='167' id='1072' V167='21' V283='2' occurMaxTimes='1' minSize='-1' maxSize='-1' dataType='1' repHandlerStruct='' visible='true' inheritsFrom='' V281='13' V1='4' name='updateTotFlag'>
      <structNode t='150' idref='1'/>
    </child>
    <child t='167' id='1073' V167='21' V283='2' occurMaxTimes='1' minSize='-1' maxSize='-1' dataType='30' repHandlerStruct='' visible='true' inheritsFrom='' V281='13' V1='4' name='cancelFrom'>
      <structNode t='150' idref='1'/>
    </child>
    <child t='167' id='1074' V167='21' V283='2' occurMaxTimes='1' minSize='-1' maxSize='-1' dataType='13' repHandlerStruct='' visible='true' inheritsFrom='' V281='13' V1='4' name='nextPolicyNumInBundle'>
      <structNode t='150' idref='1'/>
    </child>
    <child t='167' id='1075' V167='21' V283='2' occurMaxTimes='1' minSize='-1' maxSize='-1' dataType='13' repHandlerStruct='' visible='true' inheritsFrom='' V281='13' V1='4' name='nextProposalNumInBundle'>
      <structNode t='150' idref='1'/>
    </child>
    <child t='167' id='1076' V167='21' V283='2' occurMaxTimes='1' minSize='-1' maxSize='-1' dataType='1' repHandlerStruct='' visible='true' inheritsFrom='' V281='13' V1='4' name='isAnnualPayer'>
      <structNode t='150' idref='1'/>
    </child>
    <child t='167' id='1077' V167='21' V283='2' occurMaxTimes='1' minSize='-1' maxSize='-1' dataType='13' repHandlerStruct='' visible='true' inheritsFrom='' V281='13' V1='4' name='predecessor'>
      <structNode t='150' idref='1'/>
    </child>
    <child t='167' id='1078' V167='21' V283='2' occurMaxTimes='1' minSize='-1' maxSize='-1' dataType='13' repHandlerStruct='' visible='true' inheritsFrom='' V281='13' V1='4' name='successor'>
      <structNode t='150' idref='1'/>
    </child>
  </rootElem>
  <defaultRep t='178' id='1079' V178='1' V170='10' V698='1' V690='1' padOutput='true' ignoreExcluded='true' fixInvalidCharacters='true' V1='4' name='Map'>
  </defaultRep>
  <child t='162' id='5' V1='4' name='Representations'>
    <child t='178' idref='1079'/>
  </child>
  <child t='165' id='6' V1='4' name='Document Bindings'>
  </child>
</root>
