<?xml version="1.0" encoding="UTF-8"?>
<root t='150' id='1' V150='13' creationTimestamp='0x19078f939c9' V1='4' name='TProductLineOptionIVO' incarnation='37'>
  <rootElem t='167' id='2' V167='21' V283='2' occurMaxTimes='1' minSize='-1' maxSize='-1' groupType='3' repHandlerStruct='' visible='true' inheritsFrom='' namespaceIndex='1' V281='13' V1='4' name='TProductLineOptionIVO'>
    <structNode t='150' idref='1'/>
    <child t='167' id='3' V167='21' V283='2' occurMaxTimes='1' minSize='-1' maxSize='-1' groupType='3' repHandlerStruct='' inheritsFrom='' V281='13' V1='4' name='Attributes'>
      <structNode t='150' idref='1'/>
      <child t='167' id='4' V167='21' V283='2' occurMaxTimes='1' minSize='-1' maxSize='-1' dataType='13' elemType='1' repHandlerStruct='' visible='true' inheritsFrom='' V281='13' V1='4' name='id'>
        <structNode t='150' idref='1'/>
      </child>
      <child t='167' id='5' V167='21' V283='2' occurMaxTimes='1' minSize='-1' maxSize='-1' dataType='1' elemType='1' repHandlerStruct='' visible='true' inheritsFrom='' V281='13' V1='4' name='main'>
        <structNode t='150' idref='1'/>
      </child>
      <child t='167' id='6' V167='21' V283='2' occurMaxTimes='1' minSize='-1' maxSize='-1' dataType='13' elemType='1' repHandlerStruct='' visible='true' inheritsFrom='' V281='13' V1='4' name='system_id'>
        <structNode t='150' idref='1'/>
      </child>
      <child t='167' id='7' V167='21' V283='2' occurMaxTimes='1' minSize='-1' maxSize='-1' dataType='13' elemType='1' repHandlerStruct='' visible='true' inheritsFrom='' V281='13' V1='4' name='updateVersion'>
        <structNode t='150' idref='1'/>
      </child>
    </child>
    <child t='167' id='8' V167='21' inheritsFromIncarnation='8' inheritsFromTimestamp='0x19078f939d1' inheritsInThisStruct='true' V283='2' occurMaxTimes='1' minSize='-1' maxSize='-1' inheritsFromCopyRule='20' groupType='3' repHandlerStruct='' visible='true' inheritsFrom='Structures/CI_QA_all_interfaces_20240703_mod/Types/interfaces/ValueIVO.xml' V281='13' V1='4' name='checkClaimantSurAmountRuleIVO'>
      <structNode t='150' idref='1'/>
      <savedDerivedCopy t='167' id='9' V167='21' needInheritInit='true' inheritsInThisStruct='true' V283='2' occurMaxTimes='1' minSize='-1' maxSize='-1' inheritsFromCopyRule='20' dataType='2' repHandlerStruct='' visible='true' inheritsFrom='Structures/CI_QA_all_interfaces_20240703_mod/Types/interfaces/ValueIVO.xml' V281='13' V1='4' name='checkClaimantSurAmountRuleIVO'>
      </savedDerivedCopy>
      <savedOrigCopyAtInheritsFrom t='167' id='10' V167='21' V283='2' occurMaxTimes='1' minSize='-1' maxSize='-1' groupType='3' repHandlerStruct='' visible='true' inheritsFrom='' namespaceIndex='1' V281='13' V1='4' name='ValueIVO'>
      </savedOrigCopyAtInheritsFrom>
    </child>
    <child t='167' id='11' V167='21' V283='2' occurMaxTimes='1' minSize='-1' maxSize='-1' dataType='2' repHandlerStruct='' visible='true' inheritsFrom='' V281='13' V1='4' name='premiumAttrTypeVORef' description='original type: class com.idit.reference.common.vo.TPremiumAttrTypeVO'>
      <structNode t='150' idref='1'/>
      <child t='167' id='12' V167='21' V283='2' occurMaxTimes='1' minSize='-1' maxSize='-1' groupType='3' repHandlerStruct='' inheritsFrom='' V281='13' V1='4' name='Attributes'>
        <structNode t='150' idref='1'/>
        <child t='167' id='13' V167='21' V283='2' occurMinTimes='1' occurMaxTimes='1' minSize='-1' maxSize='-1' dataType='13' elemType='1' repHandlerStruct='' visible='true' inheritsFrom='' V281='13' V1='4' name='id'>
          <structNode t='150' idref='1'/>
        </child>
        <child t='167' id='14' V167='21' V283='2' occurMaxTimes='1' minSize='-1' maxSize='-1' dataType='2' elemType='1' repHandlerStruct='' visible='true' inheritsFrom='' V281='13' V1='4' name='extCode'>
          <structNode t='150' idref='1'/>
        </child>
      </child>
    </child>
    <child t='167' id='15' V167='21' V283='2' occurMaxTimes='1' minSize='-1' maxSize='-1' dataType='2' repHandlerStruct='' visible='true' inheritsFrom='' V281='13' V1='4' name='aggregatedSurAmtTypeVORef' description='original type: class com.idit.reference.common.vo.TInsuranceAmountTypeVO'>
      <structNode t='150' idref='1'/>
      <child t='167' id='16' V167='21' V283='2' occurMaxTimes='1' minSize='-1' maxSize='-1' groupType='3' repHandlerStruct='' inheritsFrom='' V281='13' V1='4' name='Attributes'>
        <structNode t='150' idref='1'/>
        <child t='167' id='17' V167='21' V283='2' occurMinTimes='1' occurMaxTimes='1' minSize='-1' maxSize='-1' dataType='13' elemType='1' repHandlerStruct='' visible='true' inheritsFrom='' V281='13' V1='4' name='id'>
          <structNode t='150' idref='1'/>
        </child>
        <child t='167' id='18' V167='21' V283='2' occurMaxTimes='1' minSize='-1' maxSize='-1' dataType='2' elemType='1' repHandlerStruct='' visible='true' inheritsFrom='' V281='13' V1='4' name='extCode'>
          <structNode t='150' idref='1'/>
        </child>
      </child>
    </child>
    <child t='167' id='19' V167='21' V283='2' occurMaxTimes='1' minSize='-1' maxSize='-1' dataType='2' repHandlerStruct='' visible='true' inheritsFrom='' V281='13' V1='4' name='insAmntIndexMethodVORef' description='original type: class com.idit.reference.common.vo.TIndexationMethodVO'>
      <structNode t='150' idref='1'/>
      <child t='167' id='20' V167='21' V283='2' occurMaxTimes='1' minSize='-1' maxSize='-1' groupType='3' repHandlerStruct='' inheritsFrom='' V281='13' V1='4' name='Attributes'>
        <structNode t='150' idref='1'/>
        <child t='167' id='21' V167='21' V283='2' occurMinTimes='1' occurMaxTimes='1' minSize='-1' maxSize='-1' dataType='13' elemType='1' repHandlerStruct='' visible='true' inheritsFrom='' V281='13' V1='4' name='id'>
          <structNode t='150' idref='1'/>
        </child>
        <child t='167' id='22' V167='21' V283='2' occurMaxTimes='1' minSize='-1' maxSize='-1' dataType='2' elemType='1' repHandlerStruct='' visible='true' inheritsFrom='' V281='13' V1='4' name='extCode'>
          <structNode t='150' idref='1'/>
        </child>
      </child>
    </child>
    <child t='167' id='23' V167='21' V283='2' occurMaxTimes='1' minSize='-1' maxSize='-1' dataType='2' repHandlerStruct='' visible='true' inheritsFrom='' V281='13' V1='4' name='additionalText'>
      <structNode t='150' idref='1'/>
    </child>
    <child t='167' id='24' V167='21' V283='2' occurMaxTimes='1' minSize='-1' maxSize='-1' groupType='1' repHandlerStruct='' visible='true' inheritsFrom='' V281='13' V1='4' name='productLineOptionSumIVOsList'>
      <structNode t='150' idref='1'/>
      <child t='167' id='25' V167='21' inheritsFromIncarnation='8' inheritsFromTimestamp='0x19078f939c9' inheritsInThisStruct='true' V283='2' occurMaxTimes='-1' minSize='-1' maxSize='-1' inheritsFromCopyRule='20' groupType='3' repHandlerStruct='' visible='true' inheritsFrom='Structures/CI_QA_all_interfaces_20240703_mod/Types/interfaces/TProductLineOptionSumIVO.xml' V281='13' V1='4' name='productLineOptionSumIVOs'>
        <structNode t='150' idref='1'/>
        <savedDerivedCopy t='167' id='26' V167='21' needInheritInit='true' inheritsInThisStruct='true' V283='2' occurMaxTimes='-1' minSize='-1' maxSize='-1' inheritsFromCopyRule='20' dataType='2' repHandlerStruct='' visible='true' inheritsFrom='Structures/CI_QA_all_interfaces_20240703_mod/Types/interfaces/TProductLineOptionSumIVO.xml' V281='13' V1='4' name='productLineOptionSumIVOs'>
        </savedDerivedCopy>
        <savedOrigCopyAtInheritsFrom t='167' id='27' V167='21' V283='2' occurMaxTimes='1' minSize='-1' maxSize='-1' groupType='3' repHandlerStruct='' visible='true' inheritsFrom='' namespaceIndex='1' V281='13' V1='4' name='TProductLineOptionSumIVO'>
        </savedOrigCopyAtInheritsFrom>
      </child>
    </child>
    <child t='167' id='28' V167='21' V283='2' occurMaxTimes='1' minSize='-1' maxSize='-1' dataType='2' repHandlerStruct='' visible='true' inheritsFrom='' V281='13' V1='4' name='insAmntIndexTypeVORef' description='original type: class com.idit.reference.common.vo.TIndexTypeVO'>
      <structNode t='150' idref='1'/>
      <child t='167' id='29' V167='21' V283='2' occurMaxTimes='1' minSize='-1' maxSize='-1' groupType='3' repHandlerStruct='' inheritsFrom='' V281='13' V1='4' name='Attributes'>
        <structNode t='150' idref='1'/>
        <child t='167' id='30' V167='21' V283='2' occurMinTimes='1' occurMaxTimes='1' minSize='-1' maxSize='-1' dataType='13' elemType='1' repHandlerStruct='' visible='true' inheritsFrom='' V281='13' V1='4' name='id'>
          <structNode t='150' idref='1'/>
        </child>
        <child t='167' id='31' V167='21' V283='2' occurMaxTimes='1' minSize='-1' maxSize='-1' dataType='2' elemType='1' repHandlerStruct='' visible='true' inheritsFrom='' V281='13' V1='4' name='extCode'>
          <structNode t='150' idref='1'/>
        </child>
      </child>
    </child>
    <child t='167' id='32' V167='21' inheritsFromIncarnation='8' inheritsFromTimestamp='0x19078f939d1' inheritsInThisStruct='true' V283='2' occurMaxTimes='1' minSize='-1' maxSize='-1' inheritsFromCopyRule='20' groupType='3' repHandlerStruct='' visible='true' inheritsFrom='Structures/CI_QA_all_interfaces_20240703_mod/Types/interfaces/ValueIVO.xml' V281='13' V1='4' name='applicableCrtRuleIVO'>
      <structNode t='150' idref='1'/>
      <savedDerivedCopy t='167' id='33' V167='21' needInheritInit='true' inheritsInThisStruct='true' V283='2' occurMaxTimes='1' minSize='-1' maxSize='-1' inheritsFromCopyRule='20' dataType='2' repHandlerStruct='' visible='true' inheritsFrom='Structures/CI_QA_all_interfaces_20240703_mod/Types/interfaces/ValueIVO.xml' V281='13' V1='4' name='applicableCrtRuleIVO'>
      </savedDerivedCopy>
      <savedOrigCopyAtInheritsFrom t='167' id='34' V167='21' V283='2' occurMaxTimes='1' minSize='-1' maxSize='-1' groupType='3' repHandlerStruct='' visible='true' inheritsFrom='' namespaceIndex='1' V281='13' V1='4' name='ValueIVO'>
      </savedOrigCopyAtInheritsFrom>
    </child>
    <child t='167' id='35' V167='21' inheritsFromIncarnation='8' inheritsFromTimestamp='0x19078f939d1' inheritsInThisStruct='true' V283='2' occurMaxTimes='1' minSize='-1' maxSize='-1' inheritsFromCopyRule='20' groupType='3' repHandlerStruct='' visible='true' inheritsFrom='Structures/CI_QA_all_interfaces_20240703_mod/Types/interfaces/ValueIVO.xml' V281='13' V1='4' name='periodSumInsRuleIVO'>
      <structNode t='150' idref='1'/>
      <savedDerivedCopy t='167' id='36' V167='21' needInheritInit='true' inheritsInThisStruct='true' V283='2' occurMaxTimes='1' minSize='-1' maxSize='-1' inheritsFromCopyRule='20' dataType='2' repHandlerStruct='' visible='true' inheritsFrom='Structures/CI_QA_all_interfaces_20240703_mod/Types/interfaces/ValueIVO.xml' V281='13' V1='4' name='periodSumInsRuleIVO'>
      </savedDerivedCopy>
      <savedOrigCopyAtInheritsFrom t='167' id='37' V167='21' V283='2' occurMaxTimes='1' minSize='-1' maxSize='-1' groupType='3' repHandlerStruct='' visible='true' inheritsFrom='' namespaceIndex='1' V281='13' V1='4' name='ValueIVO'>
      </savedOrigCopyAtInheritsFrom>
    </child>
    <child t='167' id='38' V167='21' inheritsFromIncarnation='8' inheritsFromTimestamp='0x19078f939d1' inheritsInThisStruct='true' V283='2' occurMaxTimes='1' minSize='-1' maxSize='-1' inheritsFromCopyRule='20' groupType='3' repHandlerStruct='' visible='true' inheritsFrom='Structures/CI_QA_all_interfaces_20240703_mod/Types/interfaces/ValueIVO.xml' V281='13' V1='4' name='minExcessRuleIVO'>
      <structNode t='150' idref='1'/>
      <savedDerivedCopy t='167' id='39' V167='21' needInheritInit='true' inheritsInThisStruct='true' V283='2' occurMaxTimes='1' minSize='-1' maxSize='-1' inheritsFromCopyRule='20' dataType='2' repHandlerStruct='' visible='true' inheritsFrom='Structures/CI_QA_all_interfaces_20240703_mod/Types/interfaces/ValueIVO.xml' V281='13' V1='4' name='minExcessRuleIVO'>
      </savedDerivedCopy>
      <savedOrigCopyAtInheritsFrom t='167' id='40' V167='21' V283='2' occurMaxTimes='1' minSize='-1' maxSize='-1' groupType='3' repHandlerStruct='' visible='true' inheritsFrom='' namespaceIndex='1' V281='13' V1='4' name='ValueIVO'>
      </savedOrigCopyAtInheritsFrom>
    </child>
    <child t='167' id='41' V167='21' V283='2' occurMaxTimes='1' minSize='-1' maxSize='-1' dataType='1' repHandlerStruct='' visible='true' inheritsFrom='' V281='13' V1='4' name='forCollective'>
      <structNode t='150' idref='1'/>
    </child>
    <child t='167' id='42' V167='21' inheritsFromIncarnation='8' inheritsFromTimestamp='0x19078f939d1' inheritsInThisStruct='true' V283='2' occurMaxTimes='1' minSize='-1' maxSize='-1' inheritsFromCopyRule='20' groupType='3' repHandlerStruct='' visible='true' inheritsFrom='Structures/CI_QA_all_interfaces_20240703_mod/Types/interfaces/ValueIVO.xml' V281='13' V1='4' name='insuranceAmountRuleIVO'>
      <structNode t='150' idref='1'/>
      <savedDerivedCopy t='167' id='43' V167='21' needInheritInit='true' inheritsInThisStruct='true' V283='2' occurMaxTimes='1' minSize='-1' maxSize='-1' inheritsFromCopyRule='20' dataType='2' repHandlerStruct='' visible='true' inheritsFrom='Structures/CI_QA_all_interfaces_20240703_mod/Types/interfaces/ValueIVO.xml' V281='13' V1='4' name='insuranceAmountRuleIVO'>
      </savedDerivedCopy>
      <savedOrigCopyAtInheritsFrom t='167' id='44' V167='21' V283='2' occurMaxTimes='1' minSize='-1' maxSize='-1' groupType='3' repHandlerStruct='' visible='true' inheritsFrom='' namespaceIndex='1' V281='13' V1='4' name='ValueIVO'>
      </savedOrigCopyAtInheritsFrom>
    </child>
    <child t='167' id='45' V167='21' inheritsFromIncarnation='8' inheritsFromTimestamp='0x19078f939d1' inheritsInThisStruct='true' V283='2' occurMaxTimes='1' minSize='-1' maxSize='-1' inheritsFromCopyRule='20' groupType='3' repHandlerStruct='' visible='true' inheritsFrom='Structures/CI_QA_all_interfaces_20240703_mod/Types/interfaces/ValueIVO.xml' V281='13' V1='4' name='checkSureAmountRuleIVO'>
      <structNode t='150' idref='1'/>
      <savedDerivedCopy t='167' id='46' V167='21' needInheritInit='true' inheritsInThisStruct='true' V283='2' occurMaxTimes='1' minSize='-1' maxSize='-1' inheritsFromCopyRule='20' dataType='2' repHandlerStruct='' visible='true' inheritsFrom='Structures/CI_QA_all_interfaces_20240703_mod/Types/interfaces/ValueIVO.xml' V281='13' V1='4' name='checkSureAmountRuleIVO'>
      </savedDerivedCopy>
      <savedOrigCopyAtInheritsFrom t='167' id='47' V167='21' V283='2' occurMaxTimes='1' minSize='-1' maxSize='-1' groupType='3' repHandlerStruct='' visible='true' inheritsFrom='' namespaceIndex='1' V281='13' V1='4' name='ValueIVO'>
      </savedOrigCopyAtInheritsFrom>
    </child>
    <child t='167' id='48' V167='21' V283='2' occurMaxTimes='1' minSize='-1' maxSize='-1' groupType='1' repHandlerStruct='' visible='true' inheritsFrom='' V281='13' V1='4' name='packagePriceIVOsList'>
      <structNode t='150' idref='1'/>
      <child t='167' id='49' V167='21' inheritsFromIncarnation='10' inheritsFromTimestamp='0x19078f939c6' inheritsInThisStruct='true' V283='2' occurMaxTimes='-1' minSize='-1' maxSize='-1' inheritsFromCopyRule='20' groupType='3' repHandlerStruct='' visible='true' inheritsFrom='Structures/CI_QA_all_interfaces_20240703_mod/Types/interfaces/TPackagePriceIVO.xml' V281='13' V1='4' name='packagePriceIVOs' checksumValid='true' checksum='8ltw/5UHT2u4FWLor+25MjT/pHk='>
        <structNode t='150' idref='1'/>
        <savedDerivedCopy t='167' id='50' V167='21' needInheritInit='true' inheritsInThisStruct='true' V283='2' occurMaxTimes='-1' minSize='-1' maxSize='-1' inheritsFromCopyRule='20' dataType='2' repHandlerStruct='' visible='true' inheritsFrom='Structures/CI_QA_all_interfaces_20240703_mod/Types/interfaces/TPackagePriceIVO.xml' V281='13' V1='4' name='packagePriceIVOs'>
        </savedDerivedCopy>
        <savedOrigCopyAtInheritsFrom t='167' id='51' V167='21' V283='2' occurMaxTimes='1' minSize='-1' maxSize='-1' groupType='3' repHandlerStruct='' visible='true' inheritsFrom='' namespaceIndex='1' V281='13' V1='4' name='TPackagePriceIVO'>
        </savedOrigCopyAtInheritsFrom>
      </child>
    </child>
    <child t='167' id='52' V167='21' V283='2' occurMaxTimes='1' minSize='-1' maxSize='-1' dataType='30' repHandlerStruct='' visible='true' inheritsFrom='' V281='13' V1='4' name='insAmntBaseIndexDate'>
      <structNode t='150' idref='1'/>
    </child>
    <child t='167' id='53' V167='21' V283='2' occurMaxTimes='1' minSize='-1' maxSize='-1' dataType='2' repHandlerStruct='' visible='true' inheritsFrom='' V281='13' V1='4' name='excAmntIndexTypeVORef' description='original type: class com.idit.reference.common.vo.TIndexTypeVO'>
      <structNode t='150' idref='1'/>
      <child t='167' id='54' V167='21' V283='2' occurMaxTimes='1' minSize='-1' maxSize='-1' groupType='3' repHandlerStruct='' inheritsFrom='' V281='13' V1='4' name='Attributes'>
        <structNode t='150' idref='1'/>
        <child t='167' id='55' V167='21' V283='2' occurMinTimes='1' occurMaxTimes='1' minSize='-1' maxSize='-1' dataType='13' elemType='1' repHandlerStruct='' visible='true' inheritsFrom='' V281='13' V1='4' name='id'>
          <structNode t='150' idref='1'/>
        </child>
        <child t='167' id='56' V167='21' V283='2' occurMaxTimes='1' minSize='-1' maxSize='-1' dataType='2' elemType='1' repHandlerStruct='' visible='true' inheritsFrom='' V281='13' V1='4' name='extCode'>
          <structNode t='150' idref='1'/>
        </child>
      </child>
    </child>
    <child t='167' id='57' V167='21' V283='2' occurMaxTimes='1' minSize='-1' maxSize='-1' dataType='2' repHandlerStruct='' visible='true' inheritsFrom='' V281='13' V1='4' name='entryTypeVORef' description='original type: class com.idit.reference.common.accounting.vo.TEntryTypeVO'>
      <structNode t='150' idref='1'/>
      <child t='167' id='58' V167='21' V283='2' occurMaxTimes='1' minSize='-1' maxSize='-1' groupType='3' repHandlerStruct='' inheritsFrom='' V281='13' V1='4' name='Attributes'>
        <structNode t='150' idref='1'/>
        <child t='167' id='59' V167='21' V283='2' occurMinTimes='1' occurMaxTimes='1' minSize='-1' maxSize='-1' dataType='13' elemType='1' repHandlerStruct='' visible='true' inheritsFrom='' V281='13' V1='4' name='id'>
          <structNode t='150' idref='1'/>
        </child>
        <child t='167' id='60' V167='21' V283='2' occurMaxTimes='1' minSize='-1' maxSize='-1' dataType='2' elemType='1' repHandlerStruct='' visible='true' inheritsFrom='' V281='13' V1='4' name='extCode'>
          <structNode t='150' idref='1'/>
        </child>
      </child>
    </child>
    <child t='167' id='61' V167='21' inheritsFromIncarnation='8' inheritsFromTimestamp='0x19078f939d1' inheritsInThisStruct='true' V283='2' occurMaxTimes='1' minSize='-1' maxSize='-1' inheritsFromCopyRule='20' groupType='3' repHandlerStruct='' visible='true' inheritsFrom='Structures/CI_QA_all_interfaces_20240703_mod/Types/interfaces/ValueIVO.xml' V281='13' V1='4' name='additionalQuestionnaireRuleIVO'>
      <structNode t='150' idref='1'/>
      <savedDerivedCopy t='167' id='62' V167='21' needInheritInit='true' inheritsInThisStruct='true' V283='2' occurMaxTimes='1' minSize='-1' maxSize='-1' inheritsFromCopyRule='20' dataType='2' repHandlerStruct='' visible='true' inheritsFrom='Structures/CI_QA_all_interfaces_20240703_mod/Types/interfaces/ValueIVO.xml' V281='13' V1='4' name='additionalQuestionnaireRuleIVO'>
      </savedDerivedCopy>
      <savedOrigCopyAtInheritsFrom t='167' id='63' V167='21' V283='2' occurMaxTimes='1' minSize='-1' maxSize='-1' groupType='3' repHandlerStruct='' visible='true' inheritsFrom='' namespaceIndex='1' V281='13' V1='4' name='ValueIVO'>
      </savedOrigCopyAtInheritsFrom>
    </child>
    <child t='167' id='64' V167='21' inheritsFromIncarnation='8' inheritsFromTimestamp='0x19078f939d1' inheritsInThisStruct='true' V283='2' occurMaxTimes='1' minSize='-1' maxSize='-1' inheritsFromCopyRule='20' groupType='3' repHandlerStruct='' visible='true' inheritsFrom='Structures/CI_QA_all_interfaces_20240703_mod/Types/interfaces/ValueIVO.xml' V281='13' V1='4' name='maxAllowanceRuleIVO'>
      <structNode t='150' idref='1'/>
      <savedDerivedCopy t='167' id='65' V167='21' needInheritInit='true' inheritsInThisStruct='true' V283='2' occurMaxTimes='1' minSize='-1' maxSize='-1' inheritsFromCopyRule='20' dataType='2' repHandlerStruct='' visible='true' inheritsFrom='Structures/CI_QA_all_interfaces_20240703_mod/Types/interfaces/ValueIVO.xml' V281='13' V1='4' name='maxAllowanceRuleIVO'>
      </savedDerivedCopy>
      <savedOrigCopyAtInheritsFrom t='167' id='66' V167='21' V283='2' occurMaxTimes='1' minSize='-1' maxSize='-1' groupType='3' repHandlerStruct='' visible='true' inheritsFrom='' namespaceIndex='1' V281='13' V1='4' name='ValueIVO'>
      </savedOrigCopyAtInheritsFrom>
    </child>
    <child t='167' id='67' V167='21' V283='2' occurMaxTimes='1' minSize='-1' maxSize='-1' dataType='1' repHandlerStruct='' visible='true' inheritsFrom='' V281='13' V1='4' name='addBespokePremium'>
      <structNode t='150' idref='1'/>
    </child>
    <child t='167' id='68' V167='21' V283='2' occurMaxTimes='1' minSize='-1' maxSize='-1' groupType='1' repHandlerStruct='' visible='true' inheritsFrom='' V281='13' V1='4' name='deductibleMethodIVOsList'>
      <structNode t='150' idref='1'/>
      <child t='167' id='69' V167='21' inheritsFromIncarnation='16' inheritsFromTimestamp='0x19078f939c5' inheritsInThisStruct='true' V283='2' occurMaxTimes='-1' minSize='-1' maxSize='-1' inheritsFromCopyRule='20' groupType='3' repHandlerStruct='' visible='true' inheritsFrom='Structures/CI_QA_all_interfaces_20240703_mod/Types/interfaces/TOptionDeductibleMethodIVO.xml' V281='13' V1='4' name='deductibleMethodIVOs' checksumValid='true' checksum='iWK/REuTL2W2yxT2wGEtHP7oXAk='>
        <structNode t='150' idref='1'/>
        <savedDerivedCopy t='167' id='70' V167='21' needInheritInit='true' inheritsInThisStruct='true' V283='2' occurMaxTimes='-1' minSize='-1' maxSize='-1' inheritsFromCopyRule='20' dataType='2' repHandlerStruct='' visible='true' inheritsFrom='Structures/CI_QA_all_interfaces_20240703_mod/Types/interfaces/TOptionDeductibleMethodIVO.xml' V281='13' V1='4' name='deductibleMethodIVOs'>
        </savedDerivedCopy>
        <savedOrigCopyAtInheritsFrom t='167' id='71' V167='21' V283='2' occurMaxTimes='1' minSize='-1' maxSize='-1' groupType='3' repHandlerStruct='' visible='true' inheritsFrom='' namespaceIndex='1' V281='13' V1='4' name='TOptionDeductibleMethodIVO'>
        </savedOrigCopyAtInheritsFrom>
      </child>
    </child>
    <child t='167' id='72' V167='21' V283='2' occurMaxTimes='1' minSize='-1' maxSize='-1' dataType='1' repHandlerStruct='' visible='true' inheritsFrom='' V281='13' V1='4' name='defaultFlag'>
      <structNode t='150' idref='1'/>
    </child>
    <child t='167' id='73' V167='21' V283='2' occurMaxTimes='1' minSize='-1' maxSize='-1' dataType='13' repHandlerStruct='' visible='true' inheritsFrom='' V281='13' V1='4' name='optionNumber'>
      <structNode t='150' idref='1'/>
    </child>
    <child t='167' id='74' V167='21' V283='2' occurMaxTimes='1' minSize='-1' maxSize='-1' dataType='1' repHandlerStruct='' visible='true' inheritsFrom='' V281='13' V1='4' name='addBespokeInsuranceAmout'>
      <structNode t='150' idref='1'/>
    </child>
    <child t='167' id='75' V167='21' V283='2' occurMaxTimes='1' minSize='-1' maxSize='-1' dataType='13' repHandlerStruct='' visible='true' inheritsFrom='' V281='13' V1='4' name='maxExtendedReportingMonths'>
      <structNode t='150' idref='1'/>
    </child>
    <child t='167' id='76' V167='21' inheritsFromIncarnation='8' inheritsFromTimestamp='0x19078f939d1' inheritsInThisStruct='true' V283='2' occurMaxTimes='1' minSize='-1' maxSize='-1' inheritsFromCopyRule='20' groupType='3' repHandlerStruct='' visible='true' inheritsFrom='Structures/CI_QA_all_interfaces_20240703_mod/Types/interfaces/ValueIVO.xml' V281='13' V1='4' name='aggregatedSurAmountRuleIVO'>
      <structNode t='150' idref='1'/>
      <savedDerivedCopy t='167' id='77' V167='21' needInheritInit='true' inheritsInThisStruct='true' V283='2' occurMaxTimes='1' minSize='-1' maxSize='-1' inheritsFromCopyRule='20' dataType='2' repHandlerStruct='' visible='true' inheritsFrom='Structures/CI_QA_all_interfaces_20240703_mod/Types/interfaces/ValueIVO.xml' V281='13' V1='4' name='aggregatedSurAmountRuleIVO'>
      </savedDerivedCopy>
      <savedOrigCopyAtInheritsFrom t='167' id='78' V167='21' V283='2' occurMaxTimes='1' minSize='-1' maxSize='-1' groupType='3' repHandlerStruct='' visible='true' inheritsFrom='' namespaceIndex='1' V281='13' V1='4' name='ValueIVO'>
      </savedOrigCopyAtInheritsFrom>
    </child>
    <child t='167' id='79' V167='21' V283='2' occurMaxTimes='1' minSize='-1' maxSize='-1' dataType='1' repHandlerStruct='' visible='true' inheritsFrom='' V281='13' V1='4' name='renewalFlag'>
      <structNode t='150' idref='1'/>
    </child>
    <child t='167' id='80' V167='21' inheritsFromIncarnation='8' inheritsFromTimestamp='0x19078f939d1' inheritsInThisStruct='true' V283='2' occurMaxTimes='1' minSize='-1' maxSize='-1' inheritsFromCopyRule='20' groupType='3' repHandlerStruct='' visible='true' inheritsFrom='Structures/CI_QA_all_interfaces_20240703_mod/Types/interfaces/ValueIVO.xml' V281='13' V1='4' name='minimumDeductibleRuleIVO'>
      <structNode t='150' idref='1'/>
      <savedDerivedCopy t='167' id='81' V167='21' needInheritInit='true' inheritsInThisStruct='true' V283='2' occurMaxTimes='1' minSize='-1' maxSize='-1' inheritsFromCopyRule='20' dataType='2' repHandlerStruct='' visible='true' inheritsFrom='Structures/CI_QA_all_interfaces_20240703_mod/Types/interfaces/ValueIVO.xml' V281='13' V1='4' name='minimumDeductibleRuleIVO'>
      </savedDerivedCopy>
      <savedOrigCopyAtInheritsFrom t='167' id='82' V167='21' V283='2' occurMaxTimes='1' minSize='-1' maxSize='-1' groupType='3' repHandlerStruct='' visible='true' inheritsFrom='' namespaceIndex='1' V281='13' V1='4' name='ValueIVO'>
      </savedOrigCopyAtInheritsFrom>
    </child>
    <child t='167' id='83' V167='21' V283='2' occurMaxTimes='1' minSize='-1' maxSize='-1' dataType='2' repHandlerStruct='' visible='true' inheritsFrom='' V281='13' V1='4' name='premiumIndexMethodVORef' description='original type: class com.idit.reference.common.vo.TIndexationMethodVO'>
      <structNode t='150' idref='1'/>
      <child t='167' id='84' V167='21' V283='2' occurMaxTimes='1' minSize='-1' maxSize='-1' groupType='3' repHandlerStruct='' inheritsFrom='' V281='13' V1='4' name='Attributes'>
        <structNode t='150' idref='1'/>
        <child t='167' id='85' V167='21' V283='2' occurMinTimes='1' occurMaxTimes='1' minSize='-1' maxSize='-1' dataType='13' elemType='1' repHandlerStruct='' visible='true' inheritsFrom='' V281='13' V1='4' name='id'>
          <structNode t='150' idref='1'/>
        </child>
        <child t='167' id='86' V167='21' V283='2' occurMaxTimes='1' minSize='-1' maxSize='-1' dataType='2' elemType='1' repHandlerStruct='' visible='true' inheritsFrom='' V281='13' V1='4' name='extCode'>
          <structNode t='150' idref='1'/>
        </child>
      </child>
    </child>
    <child t='167' id='87' V167='21' V283='2' occurMaxTimes='1' minSize='-1' maxSize='-1' dataType='1' repHandlerStruct='' visible='true' inheritsFrom='' V281='13' V1='4' name='isBasicCover'>
      <structNode t='150' idref='1'/>
    </child>
    <child t='167' id='88' V167='21' inheritsFromIncarnation='8' inheritsFromTimestamp='0x19078f939d1' inheritsInThisStruct='true' V283='2' occurMaxTimes='1' minSize='-1' maxSize='-1' inheritsFromCopyRule='20' groupType='3' repHandlerStruct='' visible='true' inheritsFrom='Structures/CI_QA_all_interfaces_20240703_mod/Types/interfaces/ValueIVO.xml' V281='13' V1='4' name='maxExcessRuleIVO'>
      <structNode t='150' idref='1'/>
      <savedDerivedCopy t='167' id='89' V167='21' needInheritInit='true' inheritsInThisStruct='true' V283='2' occurMaxTimes='1' minSize='-1' maxSize='-1' inheritsFromCopyRule='20' dataType='2' repHandlerStruct='' visible='true' inheritsFrom='Structures/CI_QA_all_interfaces_20240703_mod/Types/interfaces/ValueIVO.xml' V281='13' V1='4' name='maxExcessRuleIVO'>
      </savedDerivedCopy>
      <savedOrigCopyAtInheritsFrom t='167' id='90' V167='21' V283='2' occurMaxTimes='1' minSize='-1' maxSize='-1' groupType='3' repHandlerStruct='' visible='true' inheritsFrom='' namespaceIndex='1' V281='13' V1='4' name='ValueIVO'>
      </savedOrigCopyAtInheritsFrom>
    </child>
    <child t='167' id='91' V167='21' V283='2' occurMaxTimes='1' minSize='-1' maxSize='-1' dataType='2' repHandlerStruct='' visible='true' inheritsFrom='' V281='13' V1='4' name='perClmntSurAmtAttrTypeVORef' description='original type: class com.idit.reference.common.vo.TInsuranceAmountAttrTypeVO'>
      <structNode t='150' idref='1'/>
      <child t='167' id='92' V167='21' V283='2' occurMaxTimes='1' minSize='-1' maxSize='-1' groupType='3' repHandlerStruct='' inheritsFrom='' V281='13' V1='4' name='Attributes'>
        <structNode t='150' idref='1'/>
        <child t='167' id='93' V167='21' V283='2' occurMinTimes='1' occurMaxTimes='1' minSize='-1' maxSize='-1' dataType='13' elemType='1' repHandlerStruct='' visible='true' inheritsFrom='' V281='13' V1='4' name='id'>
          <structNode t='150' idref='1'/>
        </child>
        <child t='167' id='94' V167='21' V283='2' occurMaxTimes='1' minSize='-1' maxSize='-1' dataType='2' elemType='1' repHandlerStruct='' visible='true' inheritsFrom='' V281='13' V1='4' name='extCode'>
          <structNode t='150' idref='1'/>
        </child>
      </child>
    </child>
    <child t='167' id='95' V167='21' V283='2' occurMaxTimes='1' minSize='-1' maxSize='-1' dataType='2' repHandlerStruct='' visible='true' inheritsFrom='' V281='13' V1='4' name='perilInsAmntIndTypeVORef' description='original type: class com.idit.reference.common.vo.TIndexTypeVO'>
      <structNode t='150' idref='1'/>
      <child t='167' id='96' V167='21' V283='2' occurMaxTimes='1' minSize='-1' maxSize='-1' groupType='3' repHandlerStruct='' inheritsFrom='' V281='13' V1='4' name='Attributes'>
        <structNode t='150' idref='1'/>
        <child t='167' id='97' V167='21' V283='2' occurMinTimes='1' occurMaxTimes='1' minSize='-1' maxSize='-1' dataType='13' elemType='1' repHandlerStruct='' visible='true' inheritsFrom='' V281='13' V1='4' name='id'>
          <structNode t='150' idref='1'/>
        </child>
        <child t='167' id='98' V167='21' V283='2' occurMaxTimes='1' minSize='-1' maxSize='-1' dataType='2' elemType='1' repHandlerStruct='' visible='true' inheritsFrom='' V281='13' V1='4' name='extCode'>
          <structNode t='150' idref='1'/>
        </child>
      </child>
    </child>
    <child t='167' id='99' V167='21' V283='2' occurMaxTimes='1' minSize='-1' maxSize='-1' dataType='13' repHandlerStruct='' visible='true' inheritsFrom='' V281='13' V1='4' name='minPeriodDays'>
      <structNode t='150' idref='1'/>
    </child>
    <child t='167' id='100' V167='21' V283='2' occurMaxTimes='1' minSize='-1' maxSize='-1' dataType='2' repHandlerStruct='' visible='true' inheritsFrom='' V281='13' V1='4' name='perClaimantSurAmtTypeVORef' description='original type: class com.idit.reference.common.vo.TInsuranceAmountTypeVO'>
      <structNode t='150' idref='1'/>
      <child t='167' id='101' V167='21' V283='2' occurMaxTimes='1' minSize='-1' maxSize='-1' groupType='3' repHandlerStruct='' inheritsFrom='' V281='13' V1='4' name='Attributes'>
        <structNode t='150' idref='1'/>
        <child t='167' id='102' V167='21' V283='2' occurMinTimes='1' occurMaxTimes='1' minSize='-1' maxSize='-1' dataType='13' elemType='1' repHandlerStruct='' visible='true' inheritsFrom='' V281='13' V1='4' name='id'>
          <structNode t='150' idref='1'/>
        </child>
        <child t='167' id='103' V167='21' V283='2' occurMaxTimes='1' minSize='-1' maxSize='-1' dataType='2' elemType='1' repHandlerStruct='' visible='true' inheritsFrom='' V281='13' V1='4' name='extCode'>
          <structNode t='150' idref='1'/>
        </child>
      </child>
    </child>
    <child t='167' id='104' V167='21' inheritsFromIncarnation='8' inheritsFromTimestamp='0x19078f939bc' inheritsInThisStruct='true' V283='2' occurMaxTimes='1' minSize='-1' maxSize='-1' inheritsFromCopyRule='20' groupType='3' repHandlerStruct='' visible='true' inheritsFrom='Structures/CI_QA_all_interfaces_20240703_mod/Types/interfaces/TAmountIVO.xml' V281='13' V1='4' name='maxClaimAmountIVO' checksumValid='true' checksum='TWb5oBKDVozcDki/la67LWpOLU8='>
      <structNode t='150' idref='1'/>
      <savedDerivedCopy t='167' id='105' V167='21' needInheritInit='true' inheritsInThisStruct='true' V283='2' occurMaxTimes='1' minSize='-1' maxSize='-1' inheritsFromCopyRule='20' dataType='2' repHandlerStruct='' visible='true' inheritsFrom='Structures/CI_QA_all_interfaces_20240703_mod/Types/interfaces/TAmountIVO.xml' V281='13' V1='4' name='maxClaimAmountIVO'>
      </savedDerivedCopy>
      <savedOrigCopyAtInheritsFrom t='167' id='106' V167='21' V283='2' occurMaxTimes='1' minSize='-1' maxSize='-1' groupType='3' repHandlerStruct='' visible='true' inheritsFrom='' namespaceIndex='1' V281='13' V1='4' name='TAmountIVO'>
      </savedOrigCopyAtInheritsFrom>
    </child>
    <child t='167' id='107' V167='21' V283='2' occurMaxTimes='1' minSize='-1' maxSize='-1' dataType='13' repHandlerStruct='' visible='true' inheritsFrom='' V281='13' V1='4' name='productLineOptionTypeId'>
      <structNode t='150' idref='1'/>
    </child>
    <child t='167' id='108' V167='21' V283='2' occurMaxTimes='1' minSize='-1' maxSize='-1' dataType='13' repHandlerStruct='' visible='true' inheritsFrom='' V281='13' V1='4' name='originalLineOptionTypeId'>
      <structNode t='150' idref='1'/>
    </child>
    <child t='167' id='109' V167='21' V283='2' occurMaxTimes='1' minSize='-1' maxSize='-1' dataType='13' repHandlerStruct='' visible='true' inheritsFrom='' V281='13' V1='4' name='maxPeriodDays'>
      <structNode t='150' idref='1'/>
    </child>
    <child t='167' id='110' V167='21' V283='2' occurMaxTimes='1' minSize='-1' maxSize='-1' dataType='13' repHandlerStruct='' visible='true' inheritsFrom='' V281='13' V1='4' name='defaultPriorActStartMonths'>
      <structNode t='150' idref='1'/>
    </child>
    <child t='167' id='111' V167='21' V283='2' occurMaxTimes='1' minSize='-1' maxSize='-1' dataType='1' repHandlerStruct='' visible='true' inheritsFrom='' V281='13' V1='4' name='isClaimMadeCover'>
      <structNode t='150' idref='1'/>
    </child>
    <child t='167' id='112' V167='21' V283='2' occurMaxTimes='1' minSize='-1' maxSize='-1' groupType='1' repHandlerStruct='' visible='true' inheritsFrom='' V281='13' V1='4' name='premiumCalculationStepIVOsList'>
      <structNode t='150' idref='1'/>
      <child t='167' id='113' V167='21' inheritsFromIncarnation='10' inheritsFromTimestamp='0x19078f939bd' inheritsInThisStruct='true' V283='2' occurMaxTimes='-1' minSize='-1' maxSize='-1' inheritsFromCopyRule='20' groupType='3' repHandlerStruct='' visible='true' inheritsFrom='Structures/CI_QA_all_interfaces_20240703_mod/Types/interfaces/TCalculationStepIVO.xml' V281='13' V1='4' name='premiumCalculationStepIVOs' checksumValid='true' checksum='h1pA/GF85OqTI97wgkzPqdc5QxI='>
        <structNode t='150' idref='1'/>
        <savedDerivedCopy t='167' id='114' V167='21' needInheritInit='true' inheritsInThisStruct='true' V283='2' occurMaxTimes='-1' minSize='-1' maxSize='-1' inheritsFromCopyRule='20' dataType='2' repHandlerStruct='' visible='true' inheritsFrom='Structures/CI_QA_all_interfaces_20240703_mod/Types/interfaces/TCalculationStepIVO.xml' V281='13' V1='4' name='premiumCalculationStepIVOs'>
        </savedDerivedCopy>
        <savedOrigCopyAtInheritsFrom t='167' id='115' V167='21' V283='2' occurMaxTimes='1' minSize='-1' maxSize='-1' groupType='3' repHandlerStruct='' visible='true' inheritsFrom='' namespaceIndex='1' V281='13' V1='4' name='TCalculationStepIVO'>
        </savedOrigCopyAtInheritsFrom>
      </child>
    </child>
    <child t='167' id='116' V167='21' V283='2' occurMaxTimes='1' minSize='-1' maxSize='-1' dataType='2' repHandlerStruct='' visible='true' inheritsFrom='' V281='13' V1='4' name='desc'>
      <structNode t='150' idref='1'/>
    </child>
    <child t='167' id='117' V167='21' inheritsFromIncarnation='8' inheritsFromTimestamp='0x19078f939d1' inheritsInThisStruct='true' V283='2' occurMaxTimes='1' minSize='-1' maxSize='-1' inheritsFromCopyRule='20' groupType='3' repHandlerStruct='' visible='true' inheritsFrom='Structures/CI_QA_all_interfaces_20240703_mod/Types/interfaces/ValueIVO.xml' V281='13' V1='4' name='checkAggregatedSurAmountRuleIVO'>
      <structNode t='150' idref='1'/>
      <savedDerivedCopy t='167' id='118' V167='21' needInheritInit='true' inheritsInThisStruct='true' V283='2' occurMaxTimes='1' minSize='-1' maxSize='-1' inheritsFromCopyRule='20' dataType='2' repHandlerStruct='' visible='true' inheritsFrom='Structures/CI_QA_all_interfaces_20240703_mod/Types/interfaces/ValueIVO.xml' V281='13' V1='4' name='checkAggregatedSurAmountRuleIVO'>
      </savedDerivedCopy>
      <savedOrigCopyAtInheritsFrom t='167' id='119' V167='21' V283='2' occurMaxTimes='1' minSize='-1' maxSize='-1' groupType='3' repHandlerStruct='' visible='true' inheritsFrom='' namespaceIndex='1' V281='13' V1='4' name='ValueIVO'>
      </savedOrigCopyAtInheritsFrom>
    </child>
    <child t='167' id='120' V167='21' V283='2' occurMaxTimes='1' minSize='-1' maxSize='-1' dataType='2' repHandlerStruct='' visible='true' inheritsFrom='' V281='13' V1='4' name='surAmtDisplayMaskUnitRef' description='original type: class com.idit.reference.common.vo.TMaskUnitVO'>
      <structNode t='150' idref='1'/>
      <child t='167' id='121' V167='21' V283='2' occurMaxTimes='1' minSize='-1' maxSize='-1' groupType='3' repHandlerStruct='' inheritsFrom='' V281='13' V1='4' name='Attributes'>
        <structNode t='150' idref='1'/>
        <child t='167' id='122' V167='21' V283='2' occurMinTimes='1' occurMaxTimes='1' minSize='-1' maxSize='-1' dataType='13' elemType='1' repHandlerStruct='' visible='true' inheritsFrom='' V281='13' V1='4' name='id'>
          <structNode t='150' idref='1'/>
        </child>
        <child t='167' id='123' V167='21' V283='2' occurMaxTimes='1' minSize='-1' maxSize='-1' dataType='2' elemType='1' repHandlerStruct='' visible='true' inheritsFrom='' V281='13' V1='4' name='extCode'>
          <structNode t='150' idref='1'/>
        </child>
      </child>
    </child>
    <child t='167' id='124' V167='21' V283='2' occurMaxTimes='1' minSize='-1' maxSize='-1' groupType='1' repHandlerStruct='' visible='true' inheritsFrom='' V281='13' V1='4' name='productLineOptionAmountIVOsList'>
      <structNode t='150' idref='1'/>
      <child t='167' id='125' V167='21' inheritsFromIncarnation='10' inheritsFromTimestamp='0x19078f939c9' inheritsInThisStruct='true' V283='2' occurMaxTimes='-1' minSize='-1' maxSize='-1' inheritsFromCopyRule='20' groupType='3' repHandlerStruct='' visible='true' inheritsFrom='Structures/CI_QA_all_interfaces_20240703_mod/Types/interfaces/TProductLineOptionAmountIVO.xml' V281='13' V1='4' name='productLineOptionAmountIVOs' checksumValid='true' checksum='DaGurXKR/lg0fgEnbnbjnXBV7dI='>
        <structNode t='150' idref='1'/>
        <savedDerivedCopy t='167' id='126' V167='21' needInheritInit='true' inheritsInThisStruct='true' V283='2' occurMaxTimes='-1' minSize='-1' maxSize='-1' inheritsFromCopyRule='20' dataType='2' repHandlerStruct='' visible='true' inheritsFrom='Structures/CI_QA_all_interfaces_20240703_mod/Types/interfaces/TProductLineOptionAmountIVO.xml' V281='13' V1='4' name='productLineOptionAmountIVOs'>
        </savedDerivedCopy>
        <savedOrigCopyAtInheritsFrom t='167' id='127' V167='21' V283='2' occurMaxTimes='1' minSize='-1' maxSize='-1' groupType='3' repHandlerStruct='' visible='true' inheritsFrom='' namespaceIndex='1' V281='13' V1='4' name='TProductLineOptionAmountIVO'>
        </savedOrigCopyAtInheritsFrom>
      </child>
    </child>
    <child t='167' id='128' V167='21' V283='2' occurMaxTimes='1' minSize='-1' maxSize='-1' dataType='13' repHandlerStruct='' visible='true' inheritsFrom='' V281='13' V1='4' name='originLineOptionId'>
      <structNode t='150' idref='1'/>
    </child>
    <child t='167' id='129' V167='21' V283='2' occurMaxTimes='1' minSize='-1' maxSize='-1' groupType='1' repHandlerStruct='' visible='true' inheritsFrom='' V281='13' V1='4' name='productLienOptionPerilIVOsList'>
      <structNode t='150' idref='1'/>
      <child t='167' id='130' V167='21' inheritsFromIncarnation='17' inheritsFromTimestamp='0x19078f939c9' inheritsInThisStruct='true' V283='2' occurMaxTimes='-1' minSize='-1' maxSize='-1' inheritsFromCopyRule='20' groupType='3' repHandlerStruct='' visible='true' inheritsFrom='Structures/CI_QA_all_interfaces_20240703_mod/Types/interfaces/TProductLineOptionPerilIVO.xml' V281='13' V1='4' name='productLienOptionPerilIVOs' checksumValid='true' checksum='ht8b934Uw4JwkVpsmPWqeSM2Nzc='>
        <structNode t='150' idref='1'/>
        <savedDerivedCopy t='167' id='131' V167='21' needInheritInit='true' inheritsInThisStruct='true' V283='2' occurMaxTimes='-1' minSize='-1' maxSize='-1' inheritsFromCopyRule='20' dataType='2' repHandlerStruct='' visible='true' inheritsFrom='Structures/CI_QA_all_interfaces_20240703_mod/Types/interfaces/TProductLineOptionPerilIVO.xml' V281='13' V1='4' name='productLienOptionPerilIVOs'>
        </savedDerivedCopy>
        <savedOrigCopyAtInheritsFrom t='167' id='132' V167='21' V283='2' occurMaxTimes='1' minSize='-1' maxSize='-1' groupType='3' repHandlerStruct='' visible='true' inheritsFrom='' namespaceIndex='1' V281='13' V1='4' name='TProductLineOptionPerilIVO'>
        </savedOrigCopyAtInheritsFrom>
      </child>
    </child>
    <child t='167' id='133' V167='21' V283='2' occurMaxTimes='1' minSize='-1' maxSize='-1' dataType='2' repHandlerStruct='' visible='true' inheritsFrom='' V281='13' V1='4' name='productLineEntryTypeVORef' description='original type: class com.idit.reference.common.vo.TProductLineEntryTypeVO'>
      <structNode t='150' idref='1'/>
      <child t='167' id='134' V167='21' V283='2' occurMaxTimes='1' minSize='-1' maxSize='-1' groupType='3' repHandlerStruct='' inheritsFrom='' V281='13' V1='4' name='Attributes'>
        <structNode t='150' idref='1'/>
        <child t='167' id='135' V167='21' V283='2' occurMinTimes='1' occurMaxTimes='1' minSize='-1' maxSize='-1' dataType='13' elemType='1' repHandlerStruct='' visible='true' inheritsFrom='' V281='13' V1='4' name='id'>
          <structNode t='150' idref='1'/>
        </child>
        <child t='167' id='136' V167='21' V283='2' occurMaxTimes='1' minSize='-1' maxSize='-1' dataType='2' elemType='1' repHandlerStruct='' visible='true' inheritsFrom='' V281='13' V1='4' name='extCode'>
          <structNode t='150' idref='1'/>
        </child>
      </child>
    </child>
    <child t='167' id='137' V167='21' inheritsFromIncarnation='8' inheritsFromTimestamp='0x19078f939d1' inheritsInThisStruct='true' V283='2' occurMaxTimes='1' minSize='-1' maxSize='-1' inheritsFromCopyRule='20' groupType='3' repHandlerStruct='' visible='true' inheritsFrom='Structures/CI_QA_all_interfaces_20240703_mod/Types/interfaces/ValueIVO.xml' V281='13' V1='4' name='additionExcessRuleIVO'>
      <structNode t='150' idref='1'/>
      <savedDerivedCopy t='167' id='138' V167='21' needInheritInit='true' inheritsInThisStruct='true' V283='2' occurMaxTimes='1' minSize='-1' maxSize='-1' inheritsFromCopyRule='20' dataType='2' repHandlerStruct='' visible='true' inheritsFrom='Structures/CI_QA_all_interfaces_20240703_mod/Types/interfaces/ValueIVO.xml' V281='13' V1='4' name='additionExcessRuleIVO'>
      </savedDerivedCopy>
      <savedOrigCopyAtInheritsFrom t='167' id='139' V167='21' V283='2' occurMaxTimes='1' minSize='-1' maxSize='-1' groupType='3' repHandlerStruct='' visible='true' inheritsFrom='' namespaceIndex='1' V281='13' V1='4' name='ValueIVO'>
      </savedOrigCopyAtInheritsFrom>
    </child>
    <child t='167' id='140' V167='21' V283='2' occurMaxTimes='1' minSize='-1' maxSize='-1' dataType='2' repHandlerStruct='' visible='true' inheritsFrom='' V281='13' V1='4' name='perEventSurAmtTypeVORef' description='original type: class com.idit.reference.common.vo.TInsuranceAmountTypeVO'>
      <structNode t='150' idref='1'/>
      <child t='167' id='141' V167='21' V283='2' occurMaxTimes='1' minSize='-1' maxSize='-1' groupType='3' repHandlerStruct='' inheritsFrom='' V281='13' V1='4' name='Attributes'>
        <structNode t='150' idref='1'/>
        <child t='167' id='142' V167='21' V283='2' occurMinTimes='1' occurMaxTimes='1' minSize='-1' maxSize='-1' dataType='13' elemType='1' repHandlerStruct='' visible='true' inheritsFrom='' V281='13' V1='4' name='id'>
          <structNode t='150' idref='1'/>
        </child>
        <child t='167' id='143' V167='21' V283='2' occurMaxTimes='1' minSize='-1' maxSize='-1' dataType='2' elemType='1' repHandlerStruct='' visible='true' inheritsFrom='' V281='13' V1='4' name='extCode'>
          <structNode t='150' idref='1'/>
        </child>
      </child>
    </child>
    <child t='167' id='144' V167='21' inheritsFromIncarnation='8' inheritsFromTimestamp='0x19078f939d1' inheritsInThisStruct='true' V283='2' occurMaxTimes='1' minSize='-1' maxSize='-1' inheritsFromCopyRule='20' groupType='3' repHandlerStruct='' visible='true' inheritsFrom='Structures/CI_QA_all_interfaces_20240703_mod/Types/interfaces/ValueIVO.xml' V281='13' V1='4' name='perEventPerDayRuleIVO'>
      <structNode t='150' idref='1'/>
      <savedDerivedCopy t='167' id='145' V167='21' needInheritInit='true' inheritsInThisStruct='true' V283='2' occurMaxTimes='1' minSize='-1' maxSize='-1' inheritsFromCopyRule='20' dataType='2' repHandlerStruct='' visible='true' inheritsFrom='Structures/CI_QA_all_interfaces_20240703_mod/Types/interfaces/ValueIVO.xml' V281='13' V1='4' name='perEventPerDayRuleIVO'>
      </savedDerivedCopy>
      <savedOrigCopyAtInheritsFrom t='167' id='146' V167='21' V283='2' occurMaxTimes='1' minSize='-1' maxSize='-1' groupType='3' repHandlerStruct='' visible='true' inheritsFrom='' namespaceIndex='1' V281='13' V1='4' name='ValueIVO'>
      </savedOrigCopyAtInheritsFrom>
    </child>
    <child t='167' id='147' V167='21' V283='2' occurMaxTimes='1' minSize='-1' maxSize='-1' dataType='13' repHandlerStruct='' visible='true' inheritsFrom='' V281='13' V1='4' name='maxPriorActStartMonths'>
      <structNode t='150' idref='1'/>
    </child>
    <child t='167' id='148' V167='21' V283='2' occurMaxTimes='1' minSize='-1' maxSize='-1' dataType='2' repHandlerStruct='' visible='true' inheritsFrom='' V281='13' V1='4' name='perEventSurAmtDaysVORef' description='original type: class com.idit.reference.common.vo.TInsuranceAmountAttrTypeVO'>
      <structNode t='150' idref='1'/>
      <child t='167' id='149' V167='21' V283='2' occurMaxTimes='1' minSize='-1' maxSize='-1' groupType='3' repHandlerStruct='' inheritsFrom='' V281='13' V1='4' name='Attributes'>
        <structNode t='150' idref='1'/>
        <child t='167' id='150' V167='21' V283='2' occurMinTimes='1' occurMaxTimes='1' minSize='-1' maxSize='-1' dataType='13' elemType='1' repHandlerStruct='' visible='true' inheritsFrom='' V281='13' V1='4' name='id'>
          <structNode t='150' idref='1'/>
        </child>
        <child t='167' id='151' V167='21' V283='2' occurMaxTimes='1' minSize='-1' maxSize='-1' dataType='2' elemType='1' repHandlerStruct='' visible='true' inheritsFrom='' V281='13' V1='4' name='extCode'>
          <structNode t='150' idref='1'/>
        </child>
      </child>
    </child>
    <child t='167' id='152' V167='21' V283='2' occurMaxTimes='1' minSize='-1' maxSize='-1' dataType='1' repHandlerStruct='' visible='true' inheritsFrom='' V281='13' V1='4' name='shortTermFlag'>
      <structNode t='150' idref='1'/>
    </child>
    <child t='167' id='153' V167='21' V283='2' occurMaxTimes='1' minSize='-1' maxSize='-1' dataType='2' repHandlerStruct='' visible='true' inheritsFrom='' V281='13' V1='4' name='excAmntIndexMethodVORef' description='original type: class com.idit.reference.common.vo.TIndexationMethodVO'>
      <structNode t='150' idref='1'/>
      <child t='167' id='154' V167='21' V283='2' occurMaxTimes='1' minSize='-1' maxSize='-1' groupType='3' repHandlerStruct='' inheritsFrom='' V281='13' V1='4' name='Attributes'>
        <structNode t='150' idref='1'/>
        <child t='167' id='155' V167='21' V283='2' occurMinTimes='1' occurMaxTimes='1' minSize='-1' maxSize='-1' dataType='13' elemType='1' repHandlerStruct='' visible='true' inheritsFrom='' V281='13' V1='4' name='id'>
          <structNode t='150' idref='1'/>
        </child>
        <child t='167' id='156' V167='21' V283='2' occurMaxTimes='1' minSize='-1' maxSize='-1' dataType='2' elemType='1' repHandlerStruct='' visible='true' inheritsFrom='' V281='13' V1='4' name='extCode'>
          <structNode t='150' idref='1'/>
        </child>
      </child>
    </child>
    <child t='167' id='157' V167='21' V283='2' occurMaxTimes='1' minSize='-1' maxSize='-1' dataType='2' repHandlerStruct='' visible='true' inheritsFrom='' V281='13' V1='4' name='aggregatedSurAmtAttrTypeVORef' description='original type: class com.idit.reference.common.vo.TInsuranceAmountAttrTypeVO'>
      <structNode t='150' idref='1'/>
      <child t='167' id='158' V167='21' V283='2' occurMaxTimes='1' minSize='-1' maxSize='-1' groupType='3' repHandlerStruct='' inheritsFrom='' V281='13' V1='4' name='Attributes'>
        <structNode t='150' idref='1'/>
        <child t='167' id='159' V167='21' V283='2' occurMinTimes='1' occurMaxTimes='1' minSize='-1' maxSize='-1' dataType='13' elemType='1' repHandlerStruct='' visible='true' inheritsFrom='' V281='13' V1='4' name='id'>
          <structNode t='150' idref='1'/>
        </child>
        <child t='167' id='160' V167='21' V283='2' occurMaxTimes='1' minSize='-1' maxSize='-1' dataType='2' elemType='1' repHandlerStruct='' visible='true' inheritsFrom='' V281='13' V1='4' name='extCode'>
          <structNode t='150' idref='1'/>
        </child>
      </child>
    </child>
    <child t='167' id='161' V167='21' inheritsFromIncarnation='8' inheritsFromTimestamp='0x19078f939d1' inheritsInThisStruct='true' V283='2' occurMaxTimes='1' minSize='-1' maxSize='-1' inheritsFromCopyRule='20' groupType='3' repHandlerStruct='' visible='true' inheritsFrom='Structures/CI_QA_all_interfaces_20240703_mod/Types/interfaces/ValueIVO.xml' V281='13' V1='4' name='maximumDeductibleRuleIVO'>
      <structNode t='150' idref='1'/>
      <savedDerivedCopy t='167' id='162' V167='21' needInheritInit='true' inheritsInThisStruct='true' V283='2' occurMaxTimes='1' minSize='-1' maxSize='-1' inheritsFromCopyRule='20' dataType='2' repHandlerStruct='' visible='true' inheritsFrom='Structures/CI_QA_all_interfaces_20240703_mod/Types/interfaces/ValueIVO.xml' V281='13' V1='4' name='maximumDeductibleRuleIVO'>
      </savedDerivedCopy>
      <savedOrigCopyAtInheritsFrom t='167' id='163' V167='21' V283='2' occurMaxTimes='1' minSize='-1' maxSize='-1' groupType='3' repHandlerStruct='' visible='true' inheritsFrom='' namespaceIndex='1' V281='13' V1='4' name='ValueIVO'>
      </savedOrigCopyAtInheritsFrom>
    </child>
    <child t='167' id='164' V167='21' inheritsFromIncarnation='8' inheritsFromTimestamp='0x19078f939d1' inheritsInThisStruct='true' V283='2' occurMaxTimes='1' minSize='-1' maxSize='-1' inheritsFromCopyRule='20' groupType='3' repHandlerStruct='' visible='true' inheritsFrom='Structures/CI_QA_all_interfaces_20240703_mod/Types/interfaces/ValueIVO.xml' V281='13' V1='4' name='perClaimantSurAmountRuleIVO'>
      <structNode t='150' idref='1'/>
      <savedDerivedCopy t='167' id='165' V167='21' needInheritInit='true' inheritsInThisStruct='true' V283='2' occurMaxTimes='1' minSize='-1' maxSize='-1' inheritsFromCopyRule='20' dataType='2' repHandlerStruct='' visible='true' inheritsFrom='Structures/CI_QA_all_interfaces_20240703_mod/Types/interfaces/ValueIVO.xml' V281='13' V1='4' name='perClaimantSurAmountRuleIVO'>
      </savedDerivedCopy>
      <savedOrigCopyAtInheritsFrom t='167' id='166' V167='21' V283='2' occurMaxTimes='1' minSize='-1' maxSize='-1' groupType='3' repHandlerStruct='' visible='true' inheritsFrom='' namespaceIndex='1' V281='13' V1='4' name='ValueIVO'>
      </savedOrigCopyAtInheritsFrom>
    </child>
    <child t='167' id='167' V167='21' V283='2' occurMaxTimes='1' minSize='-1' maxSize='-1' dataType='2' repHandlerStruct='' visible='true' inheritsFrom='' V281='13' V1='4' name='expectedPayableValueFormulaVORef' description='original type: class com.idit.reference.common.vo.TPremiumCalculationFormulaVO'>
      <structNode t='150' idref='1'/>
      <child t='167' id='168' V167='21' V283='2' occurMaxTimes='1' minSize='-1' maxSize='-1' groupType='3' repHandlerStruct='' inheritsFrom='' V281='13' V1='4' name='Attributes'>
        <structNode t='150' idref='1'/>
        <child t='167' id='169' V167='21' V283='2' occurMinTimes='1' occurMaxTimes='1' minSize='-1' maxSize='-1' dataType='13' elemType='1' repHandlerStruct='' visible='true' inheritsFrom='' V281='13' V1='4' name='id'>
          <structNode t='150' idref='1'/>
        </child>
        <child t='167' id='170' V167='21' V283='2' occurMaxTimes='1' minSize='-1' maxSize='-1' dataType='2' elemType='1' repHandlerStruct='' visible='true' inheritsFrom='' V281='13' V1='4' name='extCode'>
          <structNode t='150' idref='1'/>
        </child>
      </child>
    </child>
    <child t='167' id='171' V167='21' inheritsFromIncarnation='8' inheritsFromTimestamp='0x19078f939d1' inheritsInThisStruct='true' V283='2' occurMaxTimes='1' minSize='-1' maxSize='-1' inheritsFromCopyRule='20' groupType='3' repHandlerStruct='' visible='true' inheritsFrom='Structures/CI_QA_all_interfaces_20240703_mod/Types/interfaces/ValueIVO.xml' V281='13' V1='4' name='condRuleIVO'>
      <structNode t='150' idref='1'/>
      <savedDerivedCopy t='167' id='172' V167='21' needInheritInit='true' inheritsInThisStruct='true' V283='2' occurMaxTimes='1' minSize='-1' maxSize='-1' inheritsFromCopyRule='20' dataType='2' repHandlerStruct='' visible='true' inheritsFrom='Structures/CI_QA_all_interfaces_20240703_mod/Types/interfaces/ValueIVO.xml' V281='13' V1='4' name='condRuleIVO'>
      </savedDerivedCopy>
      <savedOrigCopyAtInheritsFrom t='167' id='173' V167='21' V283='2' occurMaxTimes='1' minSize='-1' maxSize='-1' groupType='3' repHandlerStruct='' visible='true' inheritsFrom='' namespaceIndex='1' V281='13' V1='4' name='ValueIVO'>
      </savedOrigCopyAtInheritsFrom>
    </child>
    <child t='167' id='174' V167='21' V283='2' occurMaxTimes='1' minSize='-1' maxSize='-1' dataType='1' repHandlerStruct='' visible='true' inheritsFrom='' V281='13' V1='4' name='excessPerDamageFlag'>
      <structNode t='150' idref='1'/>
    </child>
    <child t='167' id='175' V167='21' inheritsFromIncarnation='8' inheritsFromTimestamp='0x19078f939d1' inheritsInThisStruct='true' V283='2' occurMaxTimes='1' minSize='-1' maxSize='-1' inheritsFromCopyRule='20' groupType='3' repHandlerStruct='' visible='true' inheritsFrom='Structures/CI_QA_all_interfaces_20240703_mod/Types/interfaces/ValueIVO.xml' V281='13' V1='4' name='claimantPerDayRuleIVO'>
      <structNode t='150' idref='1'/>
      <savedDerivedCopy t='167' id='176' V167='21' needInheritInit='true' inheritsInThisStruct='true' V283='2' occurMaxTimes='1' minSize='-1' maxSize='-1' inheritsFromCopyRule='20' dataType='2' repHandlerStruct='' visible='true' inheritsFrom='Structures/CI_QA_all_interfaces_20240703_mod/Types/interfaces/ValueIVO.xml' V281='13' V1='4' name='claimantPerDayRuleIVO'>
      </savedDerivedCopy>
      <savedOrigCopyAtInheritsFrom t='167' id='177' V167='21' V283='2' occurMaxTimes='1' minSize='-1' maxSize='-1' groupType='3' repHandlerStruct='' visible='true' inheritsFrom='' namespaceIndex='1' V281='13' V1='4' name='ValueIVO'>
      </savedOrigCopyAtInheritsFrom>
    </child>
    <child t='167' id='178' V167='21' inheritsFromIncarnation='8' inheritsFromTimestamp='0x19078f939d1' inheritsInThisStruct='true' V283='2' occurMaxTimes='1' minSize='-1' maxSize='-1' inheritsFromCopyRule='20' groupType='3' repHandlerStruct='' visible='true' inheritsFrom='Structures/CI_QA_all_interfaces_20240703_mod/Types/interfaces/ValueIVO.xml' V281='13' V1='4' name='excessBasisRuleIVO'>
      <structNode t='150' idref='1'/>
      <savedDerivedCopy t='167' id='179' V167='21' needInheritInit='true' inheritsInThisStruct='true' V283='2' occurMaxTimes='1' minSize='-1' maxSize='-1' inheritsFromCopyRule='20' dataType='2' repHandlerStruct='' visible='true' inheritsFrom='Structures/CI_QA_all_interfaces_20240703_mod/Types/interfaces/ValueIVO.xml' V281='13' V1='4' name='excessBasisRuleIVO'>
      </savedDerivedCopy>
      <savedOrigCopyAtInheritsFrom t='167' id='180' V167='21' V283='2' occurMaxTimes='1' minSize='-1' maxSize='-1' groupType='3' repHandlerStruct='' visible='true' inheritsFrom='' namespaceIndex='1' V281='13' V1='4' name='ValueIVO'>
      </savedOrigCopyAtInheritsFrom>
    </child>
    <child t='167' id='181' V167='21' V283='2' occurMaxTimes='1' minSize='-1' maxSize='-1' dataType='13' repHandlerStruct='' visible='true' inheritsFrom='' V281='13' V1='4' name='legalEntityRuleId'>
      <structNode t='150' idref='1'/>
    </child>
    <child t='167' id='182' V167='21' V283='2' occurMaxTimes='1' minSize='-1' maxSize='-1' dataType='2' repHandlerStruct='' visible='true' inheritsFrom='' V281='13' V1='4' name='periodTypeVORef' description='original type: class com.idit.reference.common.vo.TPeriodTypeVO'>
      <structNode t='150' idref='1'/>
      <child t='167' id='183' V167='21' V283='2' occurMaxTimes='1' minSize='-1' maxSize='-1' groupType='3' repHandlerStruct='' inheritsFrom='' V281='13' V1='4' name='Attributes'>
        <structNode t='150' idref='1'/>
        <child t='167' id='184' V167='21' V283='2' occurMinTimes='1' occurMaxTimes='1' minSize='-1' maxSize='-1' dataType='13' elemType='1' repHandlerStruct='' visible='true' inheritsFrom='' V281='13' V1='4' name='id'>
          <structNode t='150' idref='1'/>
        </child>
        <child t='167' id='185' V167='21' V283='2' occurMaxTimes='1' minSize='-1' maxSize='-1' dataType='2' elemType='1' repHandlerStruct='' visible='true' inheritsFrom='' V281='13' V1='4' name='extCode'>
          <structNode t='150' idref='1'/>
        </child>
      </child>
    </child>
    <child t='167' id='186' V167='21' V283='2' occurMaxTimes='1' minSize='-1' maxSize='-1' dataType='2' repHandlerStruct='' visible='true' inheritsFrom='' V281='13' V1='4' name='insuranceAmountAttrTypeVORef' description='original type: class com.idit.reference.common.vo.TInsuranceAmountAttrTypeVO'>
      <structNode t='150' idref='1'/>
      <child t='167' id='187' V167='21' V283='2' occurMaxTimes='1' minSize='-1' maxSize='-1' groupType='3' repHandlerStruct='' inheritsFrom='' V281='13' V1='4' name='Attributes'>
        <structNode t='150' idref='1'/>
        <child t='167' id='188' V167='21' V283='2' occurMinTimes='1' occurMaxTimes='1' minSize='-1' maxSize='-1' dataType='13' elemType='1' repHandlerStruct='' visible='true' inheritsFrom='' V281='13' V1='4' name='id'>
          <structNode t='150' idref='1'/>
        </child>
        <child t='167' id='189' V167='21' V283='2' occurMaxTimes='1' minSize='-1' maxSize='-1' dataType='2' elemType='1' repHandlerStruct='' visible='true' inheritsFrom='' V281='13' V1='4' name='extCode'>
          <structNode t='150' idref='1'/>
        </child>
      </child>
    </child>
    <child t='167' id='190' V167='21' inheritsFromIncarnation='8' inheritsFromTimestamp='0x19078f939d1' inheritsInThisStruct='true' V283='2' occurMaxTimes='1' minSize='-1' maxSize='-1' inheritsFromCopyRule='20' groupType='3' repHandlerStruct='' visible='true' inheritsFrom='Structures/CI_QA_all_interfaces_20240703_mod/Types/interfaces/ValueIVO.xml' V281='13' V1='4' name='limitBasisRuleIVO'>
      <structNode t='150' idref='1'/>
      <savedDerivedCopy t='167' id='191' V167='21' needInheritInit='true' inheritsInThisStruct='true' V283='2' occurMaxTimes='1' minSize='-1' maxSize='-1' inheritsFromCopyRule='20' dataType='2' repHandlerStruct='' visible='true' inheritsFrom='Structures/CI_QA_all_interfaces_20240703_mod/Types/interfaces/ValueIVO.xml' V281='13' V1='4' name='limitBasisRuleIVO'>
      </savedDerivedCopy>
      <savedOrigCopyAtInheritsFrom t='167' id='192' V167='21' V283='2' occurMaxTimes='1' minSize='-1' maxSize='-1' groupType='3' repHandlerStruct='' visible='true' inheritsFrom='' namespaceIndex='1' V281='13' V1='4' name='ValueIVO'>
      </savedOrigCopyAtInheritsFrom>
    </child>
    <child t='167' id='193' V167='21' V283='2' occurMaxTimes='1' minSize='-1' maxSize='-1' dataType='13' repHandlerStruct='' visible='true' inheritsFrom='' V281='13' V1='4' name='defaultExtendedReportingMonths'>
      <structNode t='150' idref='1'/>
    </child>
    <child t='167' id='194' V167='21' inheritsFromIncarnation='8' inheritsFromTimestamp='0x19078f939d1' inheritsInThisStruct='true' V283='2' occurMaxTimes='1' minSize='-1' maxSize='-1' inheritsFromCopyRule='20' groupType='3' repHandlerStruct='' visible='true' inheritsFrom='Structures/CI_QA_all_interfaces_20240703_mod/Types/interfaces/ValueIVO.xml' V281='13' V1='4' name='geoLimitRuleIVO'>
      <structNode t='150' idref='1'/>
      <savedDerivedCopy t='167' id='195' V167='21' needInheritInit='true' inheritsInThisStruct='true' V283='2' occurMaxTimes='1' minSize='-1' maxSize='-1' inheritsFromCopyRule='20' dataType='2' repHandlerStruct='' visible='true' inheritsFrom='Structures/CI_QA_all_interfaces_20240703_mod/Types/interfaces/ValueIVO.xml' V281='13' V1='4' name='geoLimitRuleIVO'>
      </savedDerivedCopy>
      <savedOrigCopyAtInheritsFrom t='167' id='196' V167='21' V283='2' occurMaxTimes='1' minSize='-1' maxSize='-1' groupType='3' repHandlerStruct='' visible='true' inheritsFrom='' namespaceIndex='1' V281='13' V1='4' name='ValueIVO'>
      </savedOrigCopyAtInheritsFrom>
    </child>
    <child t='167' id='197' V167='21' V283='2' occurMaxTimes='1' minSize='-1' maxSize='-1' dataType='30' repHandlerStruct='' visible='true' inheritsFrom='' V281='13' V1='4' name='excAmntBaseIndexDate'>
      <structNode t='150' idref='1'/>
    </child>
    <child t='167' id='198' V167='21' V283='2' occurMaxTimes='1' minSize='-1' maxSize='-1' dataType='2' repHandlerStruct='' visible='true' inheritsFrom='' V281='13' V1='4' name='perClaimantSurAmtDaysVORef' description='original type: class com.idit.reference.common.vo.TInsuranceAmountAttrTypeVO'>
      <structNode t='150' idref='1'/>
      <child t='167' id='199' V167='21' V283='2' occurMaxTimes='1' minSize='-1' maxSize='-1' groupType='3' repHandlerStruct='' inheritsFrom='' V281='13' V1='4' name='Attributes'>
        <structNode t='150' idref='1'/>
        <child t='167' id='200' V167='21' V283='2' occurMinTimes='1' occurMaxTimes='1' minSize='-1' maxSize='-1' dataType='13' elemType='1' repHandlerStruct='' visible='true' inheritsFrom='' V281='13' V1='4' name='id'>
          <structNode t='150' idref='1'/>
        </child>
        <child t='167' id='201' V167='21' V283='2' occurMaxTimes='1' minSize='-1' maxSize='-1' dataType='2' elemType='1' repHandlerStruct='' visible='true' inheritsFrom='' V281='13' V1='4' name='extCode'>
          <structNode t='150' idref='1'/>
        </child>
      </child>
    </child>
    <child t='167' id='202' V167='21' V283='2' occurMaxTimes='1' minSize='-1' maxSize='-1' dataType='2' repHandlerStruct='' visible='true' inheritsFrom='' V281='13' V1='4' name='perilInsAmntIndMethVORef' description='original type: class com.idit.reference.common.vo.TIndexationMethodVO'>
      <structNode t='150' idref='1'/>
      <child t='167' id='203' V167='21' V283='2' occurMaxTimes='1' minSize='-1' maxSize='-1' groupType='3' repHandlerStruct='' inheritsFrom='' V281='13' V1='4' name='Attributes'>
        <structNode t='150' idref='1'/>
        <child t='167' id='204' V167='21' V283='2' occurMinTimes='1' occurMaxTimes='1' minSize='-1' maxSize='-1' dataType='13' elemType='1' repHandlerStruct='' visible='true' inheritsFrom='' V281='13' V1='4' name='id'>
          <structNode t='150' idref='1'/>
        </child>
        <child t='167' id='205' V167='21' V283='2' occurMaxTimes='1' minSize='-1' maxSize='-1' dataType='2' elemType='1' repHandlerStruct='' visible='true' inheritsFrom='' V281='13' V1='4' name='extCode'>
          <structNode t='150' idref='1'/>
        </child>
      </child>
    </child>
    <child t='167' id='206' V167='21' inheritsFromIncarnation='8' inheritsFromTimestamp='0x19078f939d1' inheritsInThisStruct='true' V283='2' occurMaxTimes='1' minSize='-1' maxSize='-1' inheritsFromCopyRule='20' groupType='3' repHandlerStruct='' visible='true' inheritsFrom='Structures/CI_QA_all_interfaces_20240703_mod/Types/interfaces/ValueIVO.xml' V281='13' V1='4' name='additionalDeductibleRuleIVO'>
      <structNode t='150' idref='1'/>
      <savedDerivedCopy t='167' id='207' V167='21' needInheritInit='true' inheritsInThisStruct='true' V283='2' occurMaxTimes='1' minSize='-1' maxSize='-1' inheritsFromCopyRule='20' dataType='2' repHandlerStruct='' visible='true' inheritsFrom='Structures/CI_QA_all_interfaces_20240703_mod/Types/interfaces/ValueIVO.xml' V281='13' V1='4' name='additionalDeductibleRuleIVO'>
      </savedDerivedCopy>
      <savedOrigCopyAtInheritsFrom t='167' id='208' V167='21' V283='2' occurMaxTimes='1' minSize='-1' maxSize='-1' groupType='3' repHandlerStruct='' visible='true' inheritsFrom='' namespaceIndex='1' V281='13' V1='4' name='ValueIVO'>
      </savedOrigCopyAtInheritsFrom>
    </child>
  </rootElem>
  <defaultRep t='172' id='209' V172='6' autoFixNamespaceMismatch='true' V170='10' V692='1' V690='1' ignoreExcluded='true' fixInvalidCharacters='true' V1='4' name='XML'>
    <namespaceContainers t='220' ref='Namespace Containers/CI_QA_all_interfaces_20240703_mod.xml'/>
  </defaultRep>
  <namespaceList t='161' id='210' V161='1' namespaceUri='___osdtDummy___' V1='4'>
  </namespaceList>
  <namespaceList t='161' id='211' V161='1' namespaceUri='http://www.idit.co.il/schemas/all/interfaces' namespacePrefix='interfaces' V1='4'>
  </namespaceList>
  <child t='162' id='212' V1='4' name='Representations'>
    <child t='172' idref='209'/>
  </child>
  <child t='165' id='213' V1='4' name='Document Bindings'>
    <child t='166' id='214' V166='5' docType='1' V1='4' name='/interfaces:TProductLineOptionIVO'>
      <elemNode t='167' idref='2'/>
    </child>
  </child>
</root>
